Workbook
Name SlicerCache_Table_1_Col_1: #N/A

Sheet Echelle de maturité
A1: Niveaux de Maturité | B1: Signification | C1: Libéllé | D1: Code couleur
A2: 1 | B2: Une conscience insuffisante des risques cyber pesant sur l'organisation. Pas ou peu de mesures spécifiques mises en oeuvre en matière de cybersécurité. | C2: 1 - Insuffisant
A3: 2 | B3: Une prise de conscience de l'existence de risques cyber pour l'organisation et une volonté de mettre en place des premières mesures cyber pertinentes. | C3: 2 - Émergent
A4: 3 | B4: Une conscience partagée des risques cyber pour l'organisation et la volonté de formaliser un plan d'action cyber complet tout en ajustant les moyens en conséquence. | C4: 3 - Intermédiaire
A5: 4 | B5: Une cartographie précise de ses risques cyber pour l'organisation, un plan d'action cyber approfondi et des moyens humains et budgétaires dédiés. | C5: 4 - Confirmé
A6: 5 | B6: Des objectifs de réduction des risques cyber intégrés à la stratégie de l'organisation. Des moyens humains, budgétaires conséquents, un plan d'action cyber exhaustif, adapté aux menaces stratégiques. | C6: 5 - Optimal
A7: NA | B7: Le critère ou l'exigence évalué n'est pas pertinent au regard des activités, du périmètre technique ou du cadre réglementaire de l'organisation. | C7: Non applicable
A32: DORA (Digital Operational Resilience Act, 2022) est un règlement européen visant à renforcer la résilience opérationnelle numérique du secteur financier. | B32: ISO 27001 (2005, révision 2022) est une norme internationale définissant les exigences pour la mise en place d'un système de management de la sécurité de l'information (SMSI).
A33: NIS2 (Network and Information Security, 2022) est une directive européenne qui élargit les exigences de cybersécurité à de nouveaux secteurs essentiels. | B33: ISO 27002 (2005, révision 2022) est une norme internationale qui fournit un ensemble de bonnes pratiques et de contrôles de sécurité de l'information.
A34: PSSI (Politique de Sécurité des Systèmes d'Information) définit le plan d'action et les règles de sécurité à appliquer au sein d'une organisation. | B34: ISO 27005 (2008, révision 2022) est une norme internationale qui fournit des lignes directrices pour la gestion des risques liés à la sécurité de l'information.
A35: GRC (Gouvernance, Risques et Conformité) est une approche intégrée permettant d'aligner la stratégie sur les objectifs tout en gérant les risques. | B35: MEHARI (Méthode Harmonisée d'Analyse de Risques, 1996) est une méthode globale d'évaluation et de management des risques liés à la sécurité de l'information.
A36: ANSSI (Agence Nationale de la Sécurité des Systèmes d'Information, 2009) est l'autorité française chargée de sécuriser le développement du numérique.
A37: CIS Controls (Center for Internet Security, 2008) est un ensemble de bonnes pratiques et de mesures défensives pour atténuer les cyberattaques courantes.

Sheet Guide dhygiène informatique ANS
A3: Chapitres | B3: ID | C3: Règle de bonnes pratiques | D3: Description de la règle | E3: Description intégrale | F3: Type d'actifs | G3: Preuves attendues | H3: Niveau de maturité | I3: Description du niveau | K3: Chapitres (Tri)
A4: SENSIBILISER ET FORMER | B4: 1 | C4: Former les équipes opérationnelles à la sécurité des systèmes d’information | D4: Les équipes opérationnelles disposant d'accès privilégiés doivent être formées à la sécurité des systèmes d'information dès leur prise de fonction. Ces formations doivent être renouvelées régulièrement et adaptées aux responsabilités de chaque métier afin de limiter les risques liés aux erreurs humaines et aux mauvaises pratiques. | E4: Voir règle | F4: Identités et accès, Systèmes d’exploitation, Réseaux, Logiciels | G4: Politique ou plan de formation SSI, registre des formations réalisées, attestations de participation, supports de formation, clauses de formation SSI dans les contrats de prestation | H4: 2 - Émergent | I4: {=IF(H4="", "", XLOOKUP(H4, 'Echelle de maturité'!$C$2:$C$7, 'Echelle de maturité'!$B$2:$B$7, ""))} -> Une prise de conscience de l'existence de risques cyber pour l'organisation et une volonté de mettre en place des premières mesures cyber pertinentes. | K4: =IFERROR(__xludf.DUMMYFUNCTION("ARRAYFORMULA(LET(filled, SCAN("""", A4:A45, LAMBDA(acc, v, IF(v="""", acc, v))), IF(filled="""","""", TEXT(MATCH(filled, UNIQUE(FILTER(A4:A45, A4:A45<>"""")), 0), ""00"") & "" - "" & filled)))"),"01 - SENSIBILISER ET FORMER") -> 01 - SENSIBILISER ET FORMER
B5: 2 | C5: Sensibiliser les utilisateurs aux bonnes pratiques élémentaires de sécurité informatique | D5: Tous les utilisateurs doivent être sensibilisés dès leur arrivée aux enjeux de sécurité et aux règles de bon usage du système d’information. Ces actions doivent être régulières et adaptées afin d’ancrer les bonnes pratiques et réduire les risques liés aux comportements humains. | E5: Voir règle | F5: Identités et accès, Matériels, Systèmes d’exploitation | G5: Programme de sensibilisation SSI, supports de communication (emails, intranet, affiches), comptes-rendus de sessions, registre des campagnes de sensibilisation, charte informatique signée (option renforcée) | H5: 5 - Optimal | I5: {=IF(H5="", "", XLOOKUP(H5, 'Echelle de maturité'!$C$2:$C$7, 'Echelle de maturité'!$B$2:$B$7, ""))} -> Des objectifs de réduction des risques cyber intégrés à la stratégie de l'organisation. Des moyens humains, budgétaires conséquents, un plan d'action cyber exhaustif, adapté aux menaces stratégiques. | K5: =IFERROR(__xludf.DUMMYFUNCTION("""COMPUTED_VALUE"""),"01 - SENSIBILISER ET FORMER") -> 01 - SENSIBILISER ET FORMER
B6: 3 | C6: Maîtriser les risques de l’infogérance | D6: L’externalisation du SI ou des données doit être précédée d’une analyse de risques SSI afin d’identifier les exigences de sécurité à imposer au prestataire. Ces exigences doivent être formalisées contractuellement pour garantir la maîtrise, la réversibilité et le maintien du niveau de sécurité. | E6: Voir règle | F6: Données, Services, Applications, Infrastructures | G6: Analyse de risques SSI, cahier des charges de sécurité, contrats avec clauses SSI, plan d’assurance sécurité (PAS), procédures de réversibilité et de restitution des données | H6: 5 - Optimal | I6: {=IF(H6="", "", XLOOKUP(H6, 'Echelle de maturité'!$C$2:$C$7, 'Echelle de maturité'!$B$2:$B$7, ""))} -> Des objectifs de réduction des risques cyber intégrés à la stratégie de l'organisation. Des moyens humains, budgétaires conséquents, un plan d'action cyber exhaustif, adapté aux menaces stratégiques. | K6: =IFERROR(__xludf.DUMMYFUNCTION("""COMPUTED_VALUE"""),"01 - SENSIBILISER ET FORMER") -> 01 - SENSIBILISER ET FORMER
A7: CONNAÎTRE LE SYSTÈME D’INFORMATION | B7: 4 | C7: Identifier les informations et serveurs les plus sensibles et maintenir un schéma du réseau | D7: Les données sensibles doivent être identifiées et localisées dans le système d’information afin de déterminer les actifs critiques associés. Une cartographie à jour du SI doit permettre de visualiser les flux, les zones réseau et les composants hébergeant ces données | E7: Voir règle | F7: Données, Matériels, Réseaux, Systèmes d’exploitation | G7: Registre des données sensibles, cartographie réseau à jour, schéma d’architecture SI, inventaire des actifs critiques, documentation des flux et interconnexions | H7: 3 - Intermédiaire | I7: {=IF(H7="", "", XLOOKUP(H7, 'Echelle de maturité'!$C$2:$C$7, 'Echelle de maturité'!$B$2:$B$7, ""))} -> Une conscience partagée des risques cyber pour l'organisation et la volonté de formaliser un plan d'action cyber complet tout en ajustant les moyens en conséquence. | K7: =IFERROR(__xludf.DUMMYFUNCTION("""COMPUTED_VALUE"""),"02 - CONNAÎTRE LE SYSTÈME D’INFORMATION") -> 02 - CONNAÎTRE LE SYSTÈME D’INFORMATION
B8: 5 | C8: Disposer d’un inventaire exhaustif des comptes privilégiés et le maintenir à jour | D8: Les comptes disposant de droits élevés doivent être inventoriés et maintenus à jour afin de limiter les risques d’abus ou de compromission. Une revue régulière des droits permet de supprimer les accès obsolètes et de garantir la maîtrise des privilèges. | E8: Voir règle | F8: Identités et accès, Systèmes d’exploitation, Applications, Données | G8: Inventaire des comptes à privilèges, registre des comptes de service et administrateurs, procédures de revue périodique des droits, comptes-rendus de revues d’habilitation, règles de nomenclature des comptes | H8: Non Applicable | I8: {=IF(H8="", "", XLOOKUP(H8, 'Echelle de maturité'!$C$2:$C$7, 'Echelle de maturité'!$B$2:$B$7, ""))} -> Le critère ou l'exigence évalué n'est pas pertinent au regard des activités, du périmètre technique ou du cadre réglementaire de l'organisation. | K8: =IFERROR(__xludf.DUMMYFUNCTION("""COMPUTED_VALUE"""),"02 - CONNAÎTRE LE SYSTÈME D’INFORMATION") -> 02 - CONNAÎTRE LE SYSTÈME D’INFORMATION
B9: 6 | C9: Organiser les procédures d’arrivée, de départ et de changement de fonction des utilisateurs | D9: Les droits d’accès doivent être attribués, modifiés et supprimés en fonction des mouvements de personnel (arrivées, départs, changements de poste). Les procédures associées doivent garantir la révocation immédiate des accès lors d’un départ ou d’une évolution de fonction. | E9: Voir règle | F9: Identités et accès, Applications, Services, Matériels, Données | G9: Procédures RH et SSI de gestion des arrivées/départs/mobilité, tickets ou workflows d’onboarding/offboarding, preuves de désactivation de comptes, registres d’attribution/restitution des équipements et badges, matrices d’habilitation mises à jour | H9: 1 - Insuffisant | I9: {=IF(H9="", "", XLOOKUP(H9, 'Echelle de maturité'!$C$2:$C$7, 'Echelle de maturité'!$B$2:$B$7, ""))} -> Une conscience insuffisante des risques cyber pesant sur l'organisation. Pas ou peu de mesures spécifiques mises en oeuvre en matière de cybersécurité. | K9: =IFERROR(__xludf.DUMMYFUNCTION("""COMPUTED_VALUE"""),"02 - CONNAÎTRE LE SYSTÈME D’INFORMATION") -> 02 - CONNAÎTRE LE SYSTÈME D’INFORMATION
B10: 7 | C10: Autoriser la connexion au réseau de l’entité aux seuls équipements maîtrisés | D10: Seuls les équipements maîtrisés par l’entité doivent être autorisés à se connecter aux réseaux internes afin de réduire les risques d’intrusion et de compromission. Les équipements personnels ou visiteurs doivent être isolés via des réseaux dédiés ou des mesures de contrôle adaptées. | E10: Voir règle | F10: Matériels, Réseaux, Services | G10: Politique d’usage des équipements (BYOD), configuration des réseaux Wi-Fi (SSID invités/entreprise), règles de filtrage réseau, documentation NAC (ex : 802.1X), schéma d’architecture réseau | H10: 5 - Optimal | I10: {=IF(H10="", "", XLOOKUP(H10, 'Echelle de maturité'!$C$2:$C$7, 'Echelle de maturité'!$B$2:$B$7, ""))} -> Des objectifs de réduction des risques cyber intégrés à la stratégie de l'organisation. Des moyens humains, budgétaires conséquents, un plan d'action cyber exhaustif, adapté aux menaces stratégiques. | K10: =IFERROR(__xludf.DUMMYFUNCTION("""COMPUTED_VALUE"""),"02 - CONNAÎTRE LE SYSTÈME D’INFORMATION") -> 02 - CONNAÎTRE LE SYSTÈME D’INFORMATION
A11: AUTHENTIFIER ET CONTROLER LES ACCÈS | B11: 8 | C11: Identifier nommément chaque personne accédant au système et distinguer les rôles utilisateur/administrateur | D11: Les accès au système d’information doivent être réalisés au moyen de comptes nominatifs afin de garantir la traçabilité des actions. Les administrateurs doivent disposer d’un compte dédié à l’administration, distinct de leur compte utilisateur courant, et utilisé exclusivement pour les tâches d’administration. | E11: Voir règle | F11: Identités et accès, Logiciels, Services | G11: Politique de gestion des comptes, inventaire des comptes utilisateurs, administrateurs et de service, configuration des annuaires d'authentification, procédures d'administration, journaux de connexion et de journalisation des comptes (niveau renforcé) | H11: 4 - Confirmé | I11: {=IF(H11="", "", XLOOKUP(H11, 'Echelle de maturité'!$C$2:$C$7, 'Echelle de maturité'!$B$2:$B$7, ""))} -> Une cartographie précise de ses risques cyber pour l'organisation, un plan d'action cyber approfondi et des moyens humains et budgétaires dédiés. | K11: =IFERROR(__xludf.DUMMYFUNCTION("""COMPUTED_VALUE"""),"03 - AUTHENTIFIER ET CONTROLER LES ACCÈS") -> 03 - AUTHENTIFIER ET CONTROLER LES ACCÈS
B12: 9 | C12: Attribuer les bons droits sur les ressources sensibles du système d’information | D12: Les ressources contenant des informations sensibles doivent être identifiées et leur accès strictement limité aux utilisateurs autorisés. Les droits d'accès doivent être régulièrement revus afin de garantir leur adéquation avec les besoins réels et d'éviter toute exposition non maîtrisée des données. | E12: Voir règle | F12: Données, Applications, Services, Stockage | G12: Inventaire des ressources sensibles, matrices d'habilitation, listes de contrôle d'accès (ACL), procédures de gestion des droits, rapports de revue des habilitations, configuration des partages et bases de données | H12: 2 - Émergent | I12: {=IF(H12="", "", XLOOKUP(H12, 'Echelle de maturité'!$C$2:$C$7, 'Echelle de maturité'!$B$2:$B$7, ""))} -> Une prise de conscience de l'existence de risques cyber pour l'organisation et une volonté de mettre en place des premières mesures cyber pertinentes. | K12: =IFERROR(__xludf.DUMMYFUNCTION("""COMPUTED_VALUE"""),"03 - AUTHENTIFIER ET CONTROLER LES ACCÈS") -> 03 - AUTHENTIFIER ET CONTROLER LES ACCÈS
B13: 10 | C13: Définir et vérifier des règles de choix et de dimensionnement des mots de passe | D13: Les utilisateurs doivent appliquer des règles de création et d’utilisation de mots de passe garantissant un niveau de sécurité adapté. Des mécanismes techniques doivent compléter la sensibilisation afin de prévenir l’utilisation de mots de passe faibles ou compromis. | E13: Voir règle | F13: Identités et accès, Applications, Services | G13: Politique de mots de passe, configuration des règles de complexité et de verrouillage des comptes, rapports d’audit de robustesse des mots de passe, supports de sensibilisation, paramètres d’authentification des systèmes | H13: 4 - Confirmé | I13: {=IF(H13="", "", XLOOKUP(H13, 'Echelle de maturité'!$C$2:$C$7, 'Echelle de maturité'!$B$2:$B$7, ""))} -> Une cartographie précise de ses risques cyber pour l'organisation, un plan d'action cyber approfondi et des moyens humains et budgétaires dédiés. | K13: =IFERROR(__xludf.DUMMYFUNCTION("""COMPUTED_VALUE"""),"03 - AUTHENTIFIER ET CONTROLER LES ACCÈS") -> 03 - AUTHENTIFIER ET CONTROLER LES ACCÈS
B14: 11 | C14: Protéger les mots de passe stockés sur les systèmes | D14: Les mots de passe ne doivent pas être stockés sous des formes non sécurisées (fichiers, notes, navigateur, e-mail). Ils doivent être protégés via des solutions dédiées garantissant leur chiffrement et leur confinement. | E14: Voir règle | F14: Identités et accès, Logiciels | G14: Politique de gestion des mots de passe, déploiement d’un coffre-fort de mots de passe, configuration des outils de gestion des identifiants, recommandations de sécurité utilisateur, audits de configuration des navigateurs et postes | H14: 1 - Insuffisant | I14: {=IF(H14="", "", XLOOKUP(H14, 'Echelle de maturité'!$C$2:$C$7, 'Echelle de maturité'!$B$2:$B$7, ""))} -> Une conscience insuffisante des risques cyber pesant sur l'organisation. Pas ou peu de mesures spécifiques mises en oeuvre en matière de cybersécurité. | K14: =IFERROR(__xludf.DUMMYFUNCTION("""COMPUTED_VALUE"""),"03 - AUTHENTIFIER ET CONTROLER LES ACCÈS") -> 03 - AUTHENTIFIER ET CONTROLER LES ACCÈS
B15: 12 | C15: Changer les éléments d’authentification par défaut sur les équipements et services | D15: Les identifiants et mots de passe par défaut des systèmes et équipements doivent être modifiés dès leur installation. Ils doivent être remplacés par des secrets conformes aux règles de sécurité afin de limiter les risques de compromission initiale. | E15: Voir règle | F15: Matériels, Logiciels, Réseaux, Identités et accès | G15: Procédures d’installation et de durcissement, configurations des équipements, politique de gestion des secrets, inventaire des comptes par défaut supprimés ou modifiés, preuves de changement des identifiants initiaux | H15: Non Applicable | I15: {=IF(H15="", "", XLOOKUP(H15, 'Echelle de maturité'!$C$2:$C$7, 'Echelle de maturité'!$B$2:$B$7, ""))} -> Le critère ou l'exigence évalué n'est pas pertinent au regard des activités, du périmètre technique ou du cadre réglementaire de l'organisation. | K15: =IFERROR(__xludf.DUMMYFUNCTION("""COMPUTED_VALUE"""),"03 - AUTHENTIFIER ET CONTROLER LES ACCÈS") -> 03 - AUTHENTIFIER ET CONTROLER LES ACCÈS
B16: 13 | C16: Privilégier lorsque c’est possible une authentification forte | D16: L’accès aux systèmes doit reposer sur une authentification forte combinant au moins deux facteurs distincts. Cette approche réduit significativement le risque de compromission lié au vol ou à la faiblesse d’un seul facteur d’authentification. | E16: Voir règle | F16: Identités et accès, Applications, Services | G16: Politique d’authentification, configuration MFA des systèmes, rapports de déploiement MFA, preuves d’activation sur les applications critiques, documentation des méthodes d’authentification utilisées (OTP, cartes à puce, etc.) | H16: 3 - Intermédiaire | I16: {=IF(H16="", "", XLOOKUP(H16, 'Echelle de maturité'!$C$2:$C$7, 'Echelle de maturité'!$B$2:$B$7, ""))} -> Une conscience partagée des risques cyber pour l'organisation et la volonté de formaliser un plan d'action cyber complet tout en ajustant les moyens en conséquence. | K16: =IFERROR(__xludf.DUMMYFUNCTION("""COMPUTED_VALUE"""),"03 - AUTHENTIFIER ET CONTROLER LES ACCÈS") -> 03 - AUTHENTIFIER ET CONTROLER LES ACCÈS
A17: SÉCURISER LES POSTES | B17: 14 | C17: Mettre en place un niveau de sécurité minimal sur l’ensemble du parc informatique | D17: L’ensemble du parc informatique doit appliquer un niveau minimal de sécurité incluant la limitation des logiciels, la protection locale et le chiffrement des données. Les systèmes doivent être configurés pour réduire la surface d’attaque et isoler les environnements non conformes si nécessaire. | E17: Voir règle | F17: Matériels, Logiciels, Systèmes d’exploitation, Données | G17: Politique de durcissement des postes/serveurs, configurations antivirus et pare-feu locaux, paramétrage des postes (désactivation autorun, restriction logiciels), preuves de chiffrement des disques, procédures d’isolement des postes non conformes | H17: 5 - Optimal | I17: {=IF(H17="", "", XLOOKUP(H17, 'Echelle de maturité'!$C$2:$C$7, 'Echelle de maturité'!$B$2:$B$7, ""))} -> Des objectifs de réduction des risques cyber intégrés à la stratégie de l'organisation. Des moyens humains, budgétaires conséquents, un plan d'action cyber exhaustif, adapté aux menaces stratégiques. | K17: =IFERROR(__xludf.DUMMYFUNCTION("""COMPUTED_VALUE"""),"04 - SÉCURISER LES POSTES") -> 04 - SÉCURISER LES POSTES
B18: 15 | C18: Se protéger des menaces relatives à l’utilisation de supports amovibles | D18: L’usage des supports amovibles doit être encadré afin de limiter les risques de propagation de malware et de fuite de données. Leur utilisation doit être maîtrisée, et les périphériques non fiables doivent être interdits ou strictement contrôlés avant usage. | E18: Voir règle | F18: Matériels, Logiciels, Données | G18: Politique d’usage des supports amovibles, configurations de contrôle (blocage/exécution, antivirus), règles de sécurité des postes, procédures de mise au rebut/destruction sécurisée, journaux ou outils de contrôle des périphériques USB | H18: 5 - Optimal | I18: {=IF(H18="", "", XLOOKUP(H18, 'Echelle de maturité'!$C$2:$C$7, 'Echelle de maturité'!$B$2:$B$7, ""))} -> Des objectifs de réduction des risques cyber intégrés à la stratégie de l'organisation. Des moyens humains, budgétaires conséquents, un plan d'action cyber exhaustif, adapté aux menaces stratégiques. | K18: =IFERROR(__xludf.DUMMYFUNCTION("""COMPUTED_VALUE"""),"04 - SÉCURISER LES POSTES") -> 04 - SÉCURISER LES POSTES
B19: 16 | C19: Utiliser un outil de gestion centralisée afin d’homogénéiser les politiques de sécurité | D19: Les politiques de sécurité doivent être homogènes et appliquées de manière centralisée sur l’ensemble du parc informatique. Une gestion centralisée permet d’assurer la cohérence des configurations et d’accélérer l’application de mesures correctives en cas d’incident. | E19: Voir règle | F19: Matériels, Logiciels, Systèmes d’exploitation, Réseaux | G19: Architecture de gestion centralisée (ex. AD, MDM, GPO), configuration des politiques de sécurité appliquées, inventaire des équipements gérés, documentation des politiques de durcissement, procédures de déploiement et de mise à jour centralisée | H19: Non Applicable | I19: {=IF(H19="", "", XLOOKUP(H19, 'Echelle de maturité'!$C$2:$C$7, 'Echelle de maturité'!$B$2:$B$7, ""))} -> Le critère ou l'exigence évalué n'est pas pertinent au regard des activités, du périmètre technique ou du cadre réglementaire de l'organisation. | K19: =IFERROR(__xludf.DUMMYFUNCTION("""COMPUTED_VALUE"""),"04 - SÉCURISER LES POSTES") -> 04 - SÉCURISER LES POSTES
B20: 17 | C20: Activer et configurer le parefeu local des postes de travail | D20: Les postes de travail doivent disposer d’un pare-feu local activé afin de limiter les communications non autorisées et réduire les risques de propagation latérale. Une politique de filtrage adaptée permet de restreindre les flux inutiles et de protéger les systèmes contre les accès non souhaités. | E20: Voir règle | F20: Matériels, Systèmes d’exploitation, Réseaux | G20: Configuration des pare-feu locaux (Windows/Linux), politiques de filtrage appliquées, documentation des règles de sécurité réseau sur postes, éventuellement journaux de blocage des flux, procédures de durcissement des postes | H20: Non Applicable | I20: {=IF(H20="", "", XLOOKUP(H20, 'Echelle de maturité'!$C$2:$C$7, 'Echelle de maturité'!$B$2:$B$7, ""))} -> Le critère ou l'exigence évalué n'est pas pertinent au regard des activités, du périmètre technique ou du cadre réglementaire de l'organisation. | K20: =IFERROR(__xludf.DUMMYFUNCTION("""COMPUTED_VALUE"""),"04 - SÉCURISER LES POSTES") -> 04 - SÉCURISER LES POSTES
B21: 18 | C21: Chiffrer les données sensibles transmises par voie Internet | D21: Les données sensibles doivent être chiffrées avant toute transmission ou stockage sur des services externes non maîtrisés. Les secrets nécessaires au déchiffrement doivent être transmis via un canal distinct et de confiance. | E21: Voir règle | F21: Données, Logiciels, Services | G21: Politique de chiffrement des données, configuration des outils de chiffrement (email, cloud, fichiers), procédures de gestion des clés et secrets, preuves d’utilisation de solutions de chiffrement, recommandations utilisateurs | H21: Non Applicable | I21: {=IF(H21="", "", XLOOKUP(H21, 'Echelle de maturité'!$C$2:$C$7, 'Echelle de maturité'!$B$2:$B$7, ""))} -> Le critère ou l'exigence évalué n'est pas pertinent au regard des activités, du périmètre technique ou du cadre réglementaire de l'organisation. | K21: =IFERROR(__xludf.DUMMYFUNCTION("""COMPUTED_VALUE"""),"04 - SÉCURISER LES POSTES") -> 04 - SÉCURISER LES POSTES
A22: SÉCURISER LE RÉSEAU | B22: 19 | C22: Segmenter le réseau et mettre en place un cloisonnement entre ces zones | D22: Le réseau doit être segmenté en zones homogènes selon les niveaux de criticité et les usages afin de limiter les possibilités de déplacement latéral en cas de compromission. Des mécanismes de filtrage doivent contrôler les communications entre ces zones. | E22: Voir règle | F22: Réseaux, Infrastructures, Matériels | G22: Schéma d’architecture réseau, plan de segmentation (VLAN / sous-réseaux), règles de filtrage inter-zones (pare-feu), documentation d’architecture sécurité réseau, configuration des équipements réseau | H22: 2 - Émergent | I22: {=IF(H22="", "", XLOOKUP(H22, 'Echelle de maturité'!$C$2:$C$7, 'Echelle de maturité'!$B$2:$B$7, ""))} -> Une prise de conscience de l'existence de risques cyber pour l'organisation et une volonté de mettre en place des premières mesures cyber pertinentes. | K22: =IFERROR(__xludf.DUMMYFUNCTION("""COMPUTED_VALUE"""),"05 - SÉCURISER LE RÉSEAU") -> 05 - SÉCURISER LE RÉSEAU
B23: 20 | C23: S’assurer de la sécurité des réseaux d’accès Wi-Fi et de la séparation des usages | D23: Les réseaux Wi-Fi doivent être sécurisés par des mécanismes de chiffrement robustes et une authentification adaptée afin de limiter les risques d’intrusion. Les accès Wi-Fi doivent être segmentés selon les usages pour éviter tout accès non autorisé au système d’information interne. | E23: Voir règle | F23: Réseaux, Matériels, Systèmes d’exploitation | G23: Configuration des points d’accès Wi-Fi (WPA2/WPA3, AES), schéma de segmentation Wi-Fi (SSID/VLAN), règles de filtrage réseau, documentation d’authentification (certificats ou équivalent), configuration d’administration sécurisée des équipements Wi-Fi | H23: 4 - Confirmé | I23: {=IF(H23="", "", XLOOKUP(H23, 'Echelle de maturité'!$C$2:$C$7, 'Echelle de maturité'!$B$2:$B$7, ""))} -> Une cartographie précise de ses risques cyber pour l'organisation, un plan d'action cyber approfondi et des moyens humains et budgétaires dédiés. | K23: =IFERROR(__xludf.DUMMYFUNCTION("""COMPUTED_VALUE"""),"05 - SÉCURISER LE RÉSEAU") -> 05 - SÉCURISER LE RÉSEAU
B24: 21 | C24: Utiliser des protocoles réseaux sécurisés dès qu’ils existent | D24: Les communications doivent utiliser des protocoles sécurisés intégrant des mécanismes de chiffrement et d’intégrité dès que possible. Les protocoles non sécurisés doivent être remplacés par leurs équivalents sécurisés afin de protéger les échanges de données. | E24: Voir règle | F24: Réseaux, Services, Logiciels | G24: Configuration des services réseau (HTTPS, SSH, SMTPS, etc.), désactivation des protocoles non sécurisés (HTTP, Telnet, etc.), règles de configuration des serveurs et équipements réseau, scans de sécurité ou rapports d’audit des protocoles actifs | H24: Non Applicable | I24: {=IF(H24="", "", XLOOKUP(H24, 'Echelle de maturité'!$C$2:$C$7, 'Echelle de maturité'!$B$2:$B$7, ""))} -> Le critère ou l'exigence évalué n'est pas pertinent au regard des activités, du périmètre technique ou du cadre réglementaire de l'organisation. | K24: =IFERROR(__xludf.DUMMYFUNCTION("""COMPUTED_VALUE"""),"05 - SÉCURISER LE RÉSEAU") -> 05 - SÉCURISER LE RÉSEAU
B25: 22 | C25: Mettre en place une passerelle d’accès sécurisé à Internet | D25: Les accès Internet doivent transiter via une passerelle sécurisée intégrant filtrage et proxy afin de contrôler et journaliser les flux. Les postes utilisateurs ne doivent pas disposer d’un accès direct à Internet pour limiter les risques de compromission. | E25: Voir règle | F25: Réseaux, Services, Matériels | G25: Architecture de passerelle Internet, configuration du pare-feu et du proxy, règles de filtrage web, journaux de proxy, procédures d’administration et de maintien en conditions de sécurité, configuration DNS des postes | H25: 3 - Intermédiaire | I25: {=IF(H25="", "", XLOOKUP(H25, 'Echelle de maturité'!$C$2:$C$7, 'Echelle de maturité'!$B$2:$B$7, ""))} -> Une conscience partagée des risques cyber pour l'organisation et la volonté de formaliser un plan d'action cyber complet tout en ajustant les moyens en conséquence. | K25: =IFERROR(__xludf.DUMMYFUNCTION("""COMPUTED_VALUE"""),"05 - SÉCURISER LE RÉSEAU") -> 05 - SÉCURISER LE RÉSEAU
B26: 23 | C26: Cloisonner les services visibles depuis Internet du reste du système d’information | D26: Les services exposés sur Internet doivent être hébergés dans une infrastructure dédiée et isolée du reste du système d’information. Les flux entrants doivent être filtrés et contrôlés via des mécanismes de sécurité adaptés, notamment des reverse proxy. | E26: Voir règle | F26: Réseaux, Infrastructures, Services, Matériels | G26: Schéma d’architecture d’hébergement (DMZ), configuration des reverse proxy, règles de filtrage réseau, documentation de segmentation des environnements, inventaire des services exposés, procédures d’administration et de sécurisation des infrastructures | H26: 1 - Insuffisant | I26: {=IF(H26="", "", XLOOKUP(H26, 'Echelle de maturité'!$C$2:$C$7, 'Echelle de maturité'!$B$2:$B$7, ""))} -> Une conscience insuffisante des risques cyber pesant sur l'organisation. Pas ou peu de mesures spécifiques mises en oeuvre en matière de cybersécurité. | K26: =IFERROR(__xludf.DUMMYFUNCTION("""COMPUTED_VALUE"""),"05 - SÉCURISER LE RÉSEAU") -> 05 - SÉCURISER LE RÉSEAU
B27: 24 | C27: Protéger sa messagerie professionnelle | D27: La messagerie doit être protégée contre les menaces (malwares, phishing, fraude) via des mécanismes techniques et organisationnels adaptés. Les échanges doivent être sécurisés et les usages à risque (redirection externe, ouverture de contenus non vérifiés) encadrés. | E27: Voir règle | F27: Services, Réseaux, Logiciels, Données | G27: Configuration de la passerelle de messagerie, solution antivirus/anti-malware mail, activation TLS, politiques de sécurité messagerie, configuration anti-spam, enregistrements DNS (SPF, DKIM, DMARC), procédures de sensibilisation et règles d’usage | H27: 2 - Émergent | I27: {=IF(H27="", "", XLOOKUP(H27, 'Echelle de maturité'!$C$2:$C$7, 'Echelle de maturité'!$B$2:$B$7, ""))} -> Une prise de conscience de l'existence de risques cyber pour l'organisation et une volonté de mettre en place des premières mesures cyber pertinentes. | K27: =IFERROR(__xludf.DUMMYFUNCTION("""COMPUTED_VALUE"""),"05 - SÉCURISER LE RÉSEAU") -> 05 - SÉCURISER LE RÉSEAU
B28: 25 | C28: Sécuriser les interconnexions réseau dédiées avec les partenaires | D28: Les interconnexions avec des partenaires doivent être encadrées par des tunnels sécurisés et un filtrage strict des flux. Les échanges doivent être limités au strict nécessaire opérationnel afin de réduire la surface d’exposition. | E28: Voir règle | F28: Réseaux, Services, Infrastructures | G28: Schémas d’interconnexion, configuration VPN/IPsec, règles de pare-feu, matrice des flux autorisés, documentation de filtrage dédié, éventuellement configuration IDS/IPS | H28: 2 - Émergent | I28: {=IF(H28="", "", XLOOKUP(H28, 'Echelle de maturité'!$C$2:$C$7, 'Echelle de maturité'!$B$2:$B$7, ""))} -> Une prise de conscience de l'existence de risques cyber pour l'organisation et une volonté de mettre en place des premières mesures cyber pertinentes. | K28: =IFERROR(__xludf.DUMMYFUNCTION("""COMPUTED_VALUE"""),"05 - SÉCURISER LE RÉSEAU") -> 05 - SÉCURISER LE RÉSEAU
B29: 26 | C29: Contrôler et protéger l’accès aux salles serveurs et aux locaux techniques | D29: Les accès aux locaux techniques doivent être strictement contrôlés afin de limiter les intrusions physiques et les accès non autorisés aux systèmes. Les points d’accès réseau en zones accessibles doivent être maîtrisés ou désactivés pour éviter toute connexion non autorisée. | E29: Voir règle | F29: Matériels, Réseaux, Infrastructures | G29: Contrôle d’accès aux locaux (badges/serrures), journaux de contrôle d’accès physique, politique de gestion des accès physiques, inventaire des prises réseau actives/inactives, procédures de gestion des accès et revues périodiques des habilitations physiques | H29: 1 - Insuffisant | I29: {=IF(H29="", "", XLOOKUP(H29, 'Echelle de maturité'!$C$2:$C$7, 'Echelle de maturité'!$B$2:$B$7, ""))} -> Une conscience insuffisante des risques cyber pesant sur l'organisation. Pas ou peu de mesures spécifiques mises en oeuvre en matière de cybersécurité. | K29: =IFERROR(__xludf.DUMMYFUNCTION("""COMPUTED_VALUE"""),"05 - SÉCURISER LE RÉSEAU") -> 05 - SÉCURISER LE RÉSEAU
A30: SÉCURISER L’ADMINISTRATION | B30: 27 | C30: Interdire l’accès à Internet depuis les postes ou serveurs utilisés pour l’administration du système d’information | D30: Les environnements d’administration doivent être isolés d’Internet afin de réduire les risques d’exposition aux attaques. Les usages nécessitant Internet doivent être réalisés depuis un environnement distinct ou contrôlé pour éviter toute compromission des accès privilégiés. | E30: Voir règle | F30: Matériels, Systèmes d’exploitation, Réseaux, Logiciels | G30: Architecture des postes d’administration, règles de segmentation réseau, configuration des accès Internet (blocage ou isolation), documentation des environnements séparés (bureautique vs admin), procédures de transfert sécurisé de mises à jour | H30: 3 - Intermédiaire | I30: {=IF(H30="", "", XLOOKUP(H30, 'Echelle de maturité'!$C$2:$C$7, 'Echelle de maturité'!$B$2:$B$7, ""))} -> Une conscience partagée des risques cyber pour l'organisation et la volonté de formaliser un plan d'action cyber complet tout en ajustant les moyens en conséquence. | K30: =IFERROR(__xludf.DUMMYFUNCTION("""COMPUTED_VALUE"""),"06 - SÉCURISER L’ADMINISTRATION") -> 06 - SÉCURISER L’ADMINISTRATION
B31: 28 | C31: Utiliser un réseau dédié et cloisonné pour l’administration du système d’information | D31: Le réseau d’administration doit être isolé des autres réseaux afin de limiter les risques de compromission par rebond. Les flux d’administration doivent être strictement séparés et protégés par des mécanismes de cloisonnement adaptés. | E31: Voir règle | F31: Réseaux, Infrastructures, Matériels | G31: Schéma d’architecture réseau, configuration VLAN ou IPsec, règles de segmentation réseau, documentation du réseau d’administration, règles de filtrage inter-réseaux | H31: 3 - Intermédiaire | I31: {=IF(H31="", "", XLOOKUP(H31, 'Echelle de maturité'!$C$2:$C$7, 'Echelle de maturité'!$B$2:$B$7, ""))} -> Une conscience partagée des risques cyber pour l'organisation et la volonté de formaliser un plan d'action cyber complet tout en ajustant les moyens en conséquence. | K31: =IFERROR(__xludf.DUMMYFUNCTION("""COMPUTED_VALUE"""),"06 - SÉCURISER L’ADMINISTRATION") -> 06 - SÉCURISER L’ADMINISTRATION
B32: 29 | C32: Limiter au strict besoin opérationnel les droits d’administration sur les postes de travail | D32: Les utilisateurs ne doivent pas disposer de droits d’administration sur leurs postes de travail afin de limiter les risques d’exécution de logiciels malveillants et de modifications système non maîtrisées. Les élévations de privilèges doivent rester exceptionnelles, tracées et temporaires. | E32: Voir règle | F32: Matériels, Systèmes d’exploitation, Logiciels | G32: Politique de gestion des droits utilisateurs, configuration des postes (droits standards), inventaire des comptes locaux administrateurs, procédures de délégation temporaire de privilèges, journaux d’audit des élévations de droits | H32: Non Applicable | I32: {=IF(H32="", "", XLOOKUP(H32, 'Echelle de maturité'!$C$2:$C$7, 'Echelle de maturité'!$B$2:$B$7, ""))} -> Le critère ou l'exigence évalué n'est pas pertinent au regard des activités, du périmètre technique ou du cadre réglementaire de l'organisation. | K32: =IFERROR(__xludf.DUMMYFUNCTION("""COMPUTED_VALUE"""),"06 - SÉCURISER L’ADMINISTRATION") -> 06 - SÉCURISER L’ADMINISTRATION
A33: GÉRER LE NOMADISME | B33: 30 | C33: Prendre des mesures de sécurisation physique des terminaux nomades | D33: Les terminaux nomades doivent être protégés contre la perte, le vol et les accès non autorisés car ils peuvent contenir des données sensibles. Des mesures de protection physique et logique doivent être mises en place pour réduire leur exposition aux risques. | E33: Voir règle | F33: Matériels, Données, Systèmes d’exploitation | G33: Politique de sécurité des terminaux nomades, activation du chiffrement des disques, déploiement de filtres de confidentialité écran, procédures de gestion des pertes/vols, documentation sur l’authentification forte ou supports matériels complémentaires | H33: 2 - Émergent | I33: {=IF(H33="", "", XLOOKUP(H33, 'Echelle de maturité'!$C$2:$C$7, 'Echelle de maturité'!$B$2:$B$7, ""))} -> Une prise de conscience de l'existence de risques cyber pour l'organisation et une volonté de mettre en place des premières mesures cyber pertinentes. | K33: =IFERROR(__xludf.DUMMYFUNCTION("""COMPUTED_VALUE"""),"07 - GÉRER LE NOMADISME") -> 07 - GÉRER LE NOMADISME
B34: 31 | C34: Chiffrer les données sensibles, en particulier sur le matériel potentiellement perdable | D34: Les données stockées sur les terminaux et supports nomades doivent être chiffrées afin de protéger leur confidentialité en cas de perte ou de vol. L’accès aux données doit être conditionné à un secret robuste et unique. | E34: Voir règle | F34: Données, Matériels, Systèmes d’exploitation | G34: Politique de chiffrement des supports nomades, configuration du chiffrement de disque (ex. BitLocker, LUKS), procédures de gestion des clés de chiffrement, vérification de l’activation du chiffrement sur les équipements | H34: 3 - Intermédiaire | I34: {=IF(H34="", "", XLOOKUP(H34, 'Echelle de maturité'!$C$2:$C$7, 'Echelle de maturité'!$B$2:$B$7, ""))} -> Une conscience partagée des risques cyber pour l'organisation et la volonté de formaliser un plan d'action cyber complet tout en ajustant les moyens en conséquence. | K34: =IFERROR(__xludf.DUMMYFUNCTION("""COMPUTED_VALUE"""),"07 - GÉRER LE NOMADISME") -> 07 - GÉRER LE NOMADISME
B35: 32 | C35: Sécuriser la connexion réseau des postes utilisés en situation de nomadisme | D35: Les connexions distantes depuis des équipements nomades doivent transiter via un tunnel VPN sécurisé afin de protéger les échanges avec le système d’information. Le trafic doit être encapsulé dans ce tunnel pour éviter toute exposition directe sur Internet. | E35: Voir règle | F35: Réseaux, Systèmes d’exploitation, Services, Identités et accès | G35: Configuration de la solution VPN (IPsec/SSL), politiques de connexion distante, règles de routage forcé (full tunnel), documentation de la passerelle VPN, configuration d’authentification des accès distants | H35: 4 - Confirmé | I35: {=IF(H35="", "", XLOOKUP(H35, 'Echelle de maturité'!$C$2:$C$7, 'Echelle de maturité'!$B$2:$B$7, ""))} -> Une cartographie précise de ses risques cyber pour l'organisation, un plan d'action cyber approfondi et des moyens humains et budgétaires dédiés. | K35: =IFERROR(__xludf.DUMMYFUNCTION("""COMPUTED_VALUE"""),"07 - GÉRER LE NOMADISME") -> 07 - GÉRER LE NOMADISME
B36: 33 | C36: Adopter des politiques de sécurité dédiées aux terminaux mobiles | D36: Les terminaux mobiles utilisés en contexte professionnel doivent être sécurisés et gérés de manière homogène afin de réduire les risques liés à la compromission ou à la fuite de données. L’usage personnel et professionnel doit être séparé autant que possible. | E36: Voir règle | F36: Matériels, Systèmes d’exploitation, Applications, Données | G36: Politique de gestion des terminaux mobiles (MDM), configuration des politiques de sécurité (verrouillage, restrictions applications), inventaire des équipements mobiles, règles de séparation des usages, procédures de configuration initiale des appareils | H36: 5 - Optimal | I36: {=IF(H36="", "", XLOOKUP(H36, 'Echelle de maturité'!$C$2:$C$7, 'Echelle de maturité'!$B$2:$B$7, ""))} -> Des objectifs de réduction des risques cyber intégrés à la stratégie de l'organisation. Des moyens humains, budgétaires conséquents, un plan d'action cyber exhaustif, adapté aux menaces stratégiques. | K36: =IFERROR(__xludf.DUMMYFUNCTION("""COMPUTED_VALUE"""),"07 - GÉRER LE NOMADISME") -> 07 - GÉRER LE NOMADISME
A37: MAINTENIR LE SYSTÈME D’INFORMATION À JOUR | B37: 34 | C37: Définir une politique de mise à jour des composants du système d’information | D37: Les vulnérabilités doivent être corrigées via l’application régulière des correctifs de sécurité publiés par les éditeurs. Une politique de mise à jour structurée doit garantir l’identification, la qualification et le déploiement des correctifs dans des délais maîtrisés. | E37: Voir règle | F37: Logiciels, Systèmes d’exploitation, Matériels, Réseaux | G37: Politique de gestion des correctifs, inventaire des composants du SI, procédures de patch management, rapports de déploiement des mises à jour, outils de gestion des mises à jour (WSUS, équivalent), liste des systèmes obsolètes isolés | H37: 2 - Émergent | I37: {=IF(H37="", "", XLOOKUP(H37, 'Echelle de maturité'!$C$2:$C$7, 'Echelle de maturité'!$B$2:$B$7, ""))} -> Une prise de conscience de l'existence de risques cyber pour l'organisation et une volonté de mettre en place des premières mesures cyber pertinentes. | K37: =IFERROR(__xludf.DUMMYFUNCTION("""COMPUTED_VALUE"""),"08 - MAINTENIR LE SYSTÈME D’INFORMATION À JOUR") -> 08 - MAINTENIR LE SYSTÈME D’INFORMATION À JOUR
B38: 35 | C38: Anticiper la fin de la maintenance des logiciels et systèmes et limiter les adhérences logicielles | D38: Les systèmes et logiciels doivent être maintenus à jour et remplacés avant leur fin de support afin de limiter les vulnérabilités exploitables. Une stratégie d’anticipation de l’obsolescence doit être mise en place pour assurer la continuité de sécurité. | E38: Voir règle | F38: Logiciels, Systèmes d’exploitation, Matériels, Infrastructures | G38: Inventaire des logiciels et systèmes, suivi des versions et dates de fin de support (EOL/EOS), stratégie de gestion de l’obsolescence, plan de migration ou de remplacement, procédures de mise à jour et de migration, documentation de tests de non-régression | H38: 5 - Optimal | I38: {=IF(H38="", "", XLOOKUP(H38, 'Echelle de maturité'!$C$2:$C$7, 'Echelle de maturité'!$B$2:$B$7, ""))} -> Des objectifs de réduction des risques cyber intégrés à la stratégie de l'organisation. Des moyens humains, budgétaires conséquents, un plan d'action cyber exhaustif, adapté aux menaces stratégiques. | K38: =IFERROR(__xludf.DUMMYFUNCTION("""COMPUTED_VALUE"""),"08 - MAINTENIR LE SYSTÈME D’INFORMATION À JOUR") -> 08 - MAINTENIR LE SYSTÈME D’INFORMATION À JOUR
A39: SUPERVISER, AUDITER, RÉAGIR | B39: 36 | C39: Activer et configurer les journaux des composants les plus importants | D39: Les composants critiques du système d’information doivent générer des journaux exploitables permettant de détecter les incidents et tentatives d’intrusion. Les événements de sécurité doivent être conservés et synchronisés dans le temps pour permettre leur analyse et leur corrélation. | E39: Voir règle | F39: Réseaux, Logiciels, Systèmes d’exploitation, Services, Matériels | G39: Politique de journalisation, configuration des logs (serveurs, applications, pare-feu), règles de rétention des journaux, configuration NTP, preuve de centralisation des logs (SIEM ou équivalent), exemples de journaux collectés | H39: 2 - Émergent | I39: {=IF(H39="", "", XLOOKUP(H39, 'Echelle de maturité'!$C$2:$C$7, 'Echelle de maturité'!$B$2:$B$7, ""))} -> Une prise de conscience de l'existence de risques cyber pour l'organisation et une volonté de mettre en place des premières mesures cyber pertinentes. | K39: =IFERROR(__xludf.DUMMYFUNCTION("""COMPUTED_VALUE"""),"09 - SUPERVISER, AUDITER, RÉAGIR") -> 09 - SUPERVISER, AUDITER, RÉAGIR
B40: 37 | C40: Définir et appliquer une politique de sauvegarde des composants critiques | D40: Une politique de sauvegarde doit garantir la disponibilité des données, systèmes et logiciels en cas d’incident ou d’intrusion. Elle doit définir les modalités de sauvegarde, de stockage sécurisé et de restauration régulière des informations critiques. | E40: Voir règle | F40: Données, Logiciels, Systèmes d’exploitation, Infrastructures | G40: Politique de sauvegarde, liste des données et systèmes sauvegardés, configuration des outils de backup, procédures de restauration, preuves de tests de restauration, rapports d’exercices de reprise, règles de stockage et de rétention des sauvegardes | H40: 4 - Confirmé | I40: {=IF(H40="", "", XLOOKUP(H40, 'Echelle de maturité'!$C$2:$C$7, 'Echelle de maturité'!$B$2:$B$7, ""))} -> Une cartographie précise de ses risques cyber pour l'organisation, un plan d'action cyber approfondi et des moyens humains et budgétaires dédiés. | K40: =IFERROR(__xludf.DUMMYFUNCTION("""COMPUTED_VALUE"""),"09 - SUPERVISER, AUDITER, RÉAGIR") -> 09 - SUPERVISER, AUDITER, RÉAGIR
B41: 38 | C41: Procéder à des contrôles et audits de sécurité réguliers puis appliquer les actions correctives associées | D41: Des audits de sécurité doivent être réalisés régulièrement afin d’évaluer l’efficacité des mesures mises en place et détecter les écarts entre les règles et leur application. Les résultats doivent donner lieu à des plans d’actions suivis dans le temps. | E41: Voir règle | F41: Documentation, Systèmes d’information (globaux), Réseaux, Logiciels, Infrastructures | G41: Rapports d’audit internes ou externes, plan d’actions correctives, tableaux de suivi des actions, comptes rendus de revues périodiques, indicateurs de suivi (KPI sécurité), preuves de réalisation des corrections | H41: 3 - Intermédiaire | I41: {=IF(H41="", "", XLOOKUP(H41, 'Echelle de maturité'!$C$2:$C$7, 'Echelle de maturité'!$B$2:$B$7, ""))} -> Une conscience partagée des risques cyber pour l'organisation et la volonté de formaliser un plan d'action cyber complet tout en ajustant les moyens en conséquence. | K41: =IFERROR(__xludf.DUMMYFUNCTION("""COMPUTED_VALUE"""),"09 - SUPERVISER, AUDITER, RÉAGIR") -> 09 - SUPERVISER, AUDITER, RÉAGIR
B42: 39 | C42: Désigner un référent en sécurité des systèmes d’information et le faire connaître auprès du personnel | D42: Une entité doit désigner un référent SSI chargé de centraliser les questions, incidents et bonnes pratiques de sécurité. Ce référent assure la diffusion des règles et contribue à l’amélioration continue de la sécurité du système d’information. | E42: Voir règle | F42: Documentation, Systèmes d’information, Services | G42: Nomination officielle du référent SSI, description de rôle et responsabilités, procédures de traitement des incidents, supports de sensibilisation, plan de formation SSI, canaux de communication SSI internes | H42: 4 - Confirmé | I42: {=IF(H42="", "", XLOOKUP(H42, 'Echelle de maturité'!$C$2:$C$7, 'Echelle de maturité'!$B$2:$B$7, ""))} -> Une cartographie précise de ses risques cyber pour l'organisation, un plan d'action cyber approfondi et des moyens humains et budgétaires dédiés. | K42: =IFERROR(__xludf.DUMMYFUNCTION("""COMPUTED_VALUE"""),"09 - SUPERVISER, AUDITER, RÉAGIR") -> 09 - SUPERVISER, AUDITER, RÉAGIR
B43: 40 | C43: Définir une procédure de gestion des incidents de sécurité | D43: Tout comportement suspect ou incident de sécurité doit être détecté, isolé et traité selon une procédure définie afin de limiter la propagation et les impacts. Les incidents doivent être analysés et documentés pour permettre une réponse adaptée et une amélioration continue de la sécurité. | E43: Voir règle | F43: Systèmes d’information, Données, Logiciels, Réseaux | G43: Procédure de gestion des incidents, registre des incidents de sécurité, rapports d’analyse d’incidents, preuves d’isolement des systèmes compromis, tickets ou comptes rendus d’intervention, plan de remédiation et actions correctives | H43: 5 - Optimal | I43: {=IF(H43="", "", XLOOKUP(H43, 'Echelle de maturité'!$C$2:$C$7, 'Echelle de maturité'!$B$2:$B$7, ""))} -> Des objectifs de réduction des risques cyber intégrés à la stratégie de l'organisation. Des moyens humains, budgétaires conséquents, un plan d'action cyber exhaustif, adapté aux menaces stratégiques. | K43: =IFERROR(__xludf.DUMMYFUNCTION("""COMPUTED_VALUE"""),"09 - SUPERVISER, AUDITER, RÉAGIR") -> 09 - SUPERVISER, AUDITER, RÉAGIR
A44: POUR ALLER PLUS LOIN | B44: 41 | C44: Mener une analyse de risques formelle | D44: Toute décision de sécurité doit être basée sur une analyse de risques prenant en compte le contexte, la probabilité et l’impact des menaces. Les mesures de sécurité doivent être justifiées par un traitement structuré des risques et validées au niveau approprié. | E44: Voir règle | F44: Systèmes d’information, Données, Logiciels, Réseaux, Infrastructures | G44: Analyses de risques (type EBIOS ou équivalent), cartographie des risques, plans de traitement des risques, décisions de sécurité validées, documentation de contexte de sécurité, registres de risques et de suivi | H44: 2 - Émergent | I44: {=IF(H44="", "", XLOOKUP(H44, 'Echelle de maturité'!$C$2:$C$7, 'Echelle de maturité'!$B$2:$B$7, ""))} -> Une prise de conscience de l'existence de risques cyber pour l'organisation et une volonté de mettre en place des premières mesures cyber pertinentes. | K44: =IFERROR(__xludf.DUMMYFUNCTION("""COMPUTED_VALUE"""),"10 - POUR ALLER PLUS LOIN") -> 10 - POUR ALLER PLUS LOIN
B45: 42 | C45: Privilégier l’usage de produits et de services qualifiés par l’ANSSI | D45: Les solutions de sécurité et services critiques doivent être choisis en privilégiant les produits et prestataires qualifiés par l’ANSSI afin de garantir un niveau de confiance et de sécurité éprouvé. Cette démarche permet de réduire les risques liés à l’usage de solutions non évaluées. | E45: Voir règle | F45: Logiciels, Services, Infrastructures | G45: Liste des produits et services utilisés, preuves de qualification ANSSI (PASSI, PRIS, PDIS, SecNumCloud), dossiers de sélection des solutions, contrats ou fiches techniques des prestataires, documentation d’architecture intégrant des solutions qualifiées | H45: 4 - Confirmé | I45: {=IF(H45="", "", XLOOKUP(H45, 'Echelle de maturité'!$C$2:$C$7, 'Echelle de maturité'!$B$2:$B$7, ""))} -> Une cartographie précise de ses risques cyber pour l'organisation, un plan d'action cyber approfondi et des moyens humains et budgétaires dédiés. | K45: =IFERROR(__xludf.DUMMYFUNCTION("""COMPUTED_VALUE"""),"10 - POUR ALLER PLUS LOIN") -> 10 - POUR ALLER PLUS LOIN
A46: Guide d'hygiène informatique de l'ANSSI | H46: =(COUNTIF(H4:H45,"1 - Insuffisant")*1 +COUNTIF(F4:H45,"2 - Émergent")*2 +COUNTIF(H4:H45,"3 - Intermédiaire")*3 +COUNTIF(H4:H45,"4 - Confirmé")*4 +COUNTIF(H4:H45,"5 - Optimal")*5) & "/" & (ROWS(H4:H45)*5) -> 111/210 | I46: =ROUND((LEFT(H46,SEARCH("/",H46)-1)/RIGHT(H46,LEN(H46)-SEARCH("/",H46)))*5,2)&" / 5" -> 2,64 / 5
A134: Chapitres | B134: id | C134: Niveau
A135: SENSIBILISER ET FORMER | B135: 1 | C135: =IFERROR(VALUE(LEFT($H4, 1)), "") -> 2
A136: SENSIBILISER ET FORMER | B136: 2 | C136: =IFERROR(VALUE(LEFT($H5, 1)), "") -> 5
A137: SENSIBILISER ET FORMER | B137: 3 | C137: =IFERROR(VALUE(LEFT($H6, 1)), "") -> 5
A138: CONNAÎTRE LE SYSTÈME D’INFORMATION | B138: 4 | C138: =IFERROR(VALUE(LEFT($H7, 1)), "") -> 3
A139: CONNAÎTRE LE SYSTÈME D’INFORMATION | B139: 5 | C139: =IFERROR(VALUE(LEFT($H8, 1)), "")
A140: CONNAÎTRE LE SYSTÈME D’INFORMATION | B140: 6 | C140: =IFERROR(VALUE(LEFT($H9, 1)), "") -> 1
A141: CONNAÎTRE LE SYSTÈME D’INFORMATION | B141: 7 | C141: =IFERROR(VALUE(LEFT($H10, 1)), "") -> 5
A142: AUTHENTIFIER ET CONTROLER LES ACCÈS | B142: 8 | C142: =IFERROR(VALUE(LEFT($H11, 1)), "") -> 4
A143: AUTHENTIFIER ET CONTROLER LES ACCÈS | B143: 9 | C143: =IFERROR(VALUE(LEFT($H12, 1)), "") -> 2
A144: AUTHENTIFIER ET CONTROLER LES ACCÈS | B144: 10 | C144: =IFERROR(VALUE(LEFT($H13, 1)), "") -> 4
A145: AUTHENTIFIER ET CONTROLER LES ACCÈS | B145: 11 | C145: =IFERROR(VALUE(LEFT($H14, 1)), "") -> 1
A146: AUTHENTIFIER ET CONTROLER LES ACCÈS | B146: 12 | C146: =IFERROR(VALUE(LEFT($H15, 1)), "")
... A154: SÉCURISER LE RÉSEAU | B154: 20 | C154: =IFERROR(VALUE(LEFT($H23, 1)), "") -> 4
A155: SÉCURISER LE RÉSEAU | B155: 21 | C155: =IFERROR(VALUE(LEFT($H24, 1)), "") | G155: Score max | H155: Reste à atteindre
A156: SÉCURISER LE RÉSEAU | B156: 22 | C156: =IFERROR(VALUE(LEFT($H25, 1)), "") -> 3 | G156: 30 | H156: =MAX(0,G156-F156) -> 16
A157: SÉCURISER LE RÉSEAU | B157: 23 | C157: =IFERROR(VALUE(LEFT($H26, 1)), "") -> 1 | G157: 20 | H157: =MAX(0,G157-F157) -> 11
A158: SÉCURISER LE RÉSEAU | B158: 24 | C158: =IFERROR(VALUE(LEFT($H27, 1)), "") -> 2 | G158: 20 | H158: =MAX(0,G158-F158) -> 6
A159: SÉCURISER LE RÉSEAU | B159: 25 | C159: =IFERROR(VALUE(LEFT($H28, 1)), "") -> 2 | G159: 10 | H159: =MAX(0,G159-F159) -> 3
A160: SÉCURISER LE RÉSEAU | B160: 26 | C160: =IFERROR(VALUE(LEFT($H29, 1)), "") -> 1 | G160: 10 | H160: =MAX(0,G160-F160) -> 4
A161: SÉCURISER L’ADMINISTRATION | B161: 27 | C161: =IFERROR(VALUE(LEFT($H30, 1)), "") -> 3 | G161: 15 | H161: =MAX(0,G161-F161) -> 9
A162: SÉCURISER L’ADMINISTRATION | B162: 28 | C162: =IFERROR(VALUE(LEFT($H31, 1)), "") -> 3 | G162: 40 | H162: =MAX(0,G162-F162) -> 25
A163: SÉCURISER L’ADMINISTRATION | B163: 29 | C163: =IFERROR(VALUE(LEFT($H32, 1)), "") | G163: 25 | H163: =MAX(0,G163-F163) -> 15
A164: GÉRER LE NOMADISME | B164: 30 | C164: =IFERROR(VALUE(LEFT($H33, 1)), "") -> 2 | G164: 15 | H164: =MAX(0,G164-F164) -> 3
A165: GÉRER LE NOMADISME | B165: 31 | C165: =IFERROR(VALUE(LEFT($H34, 1)), "") -> 3 | G165: 25 | H165: =MAX(0,G165-F165) -> 7
A166: GÉRER LE NOMADISME | B166: 32 | C166: =IFERROR(VALUE(LEFT($H35, 1)), "") -> 4 | G166: 210 | H166: =MAX(0,G166-F166) -> 99
A167: GÉRER LE NOMADISME | B167: 33 | C167: =IFERROR(VALUE(LEFT($H36, 1)), "") -> 5
A168: MAINTENIR LE SYSTÈME D’INFORMATION À JOUR | B168: 34 | C168: =IFERROR(VALUE(LEFT($H37, 1)), "") -> 2
A169: MAINTENIR LE SYSTÈME D’INFORMATION À JOUR | B169: 35 | C169: =IFERROR(VALUE(LEFT($H38, 1)), "") -> 5
A170: SUPERVISER, AUDITER, RÉAGIR | B170: 36 | C170: =IFERROR(VALUE(LEFT($H39, 1)), "") -> 2
A171: SUPERVISER, AUDITER, RÉAGIR | B171: 37 | C171: =IFERROR(VALUE(LEFT($H40, 1)), "") -> 4
A172: SUPERVISER, AUDITER, RÉAGIR | B172: 38 | C172: =IFERROR(VALUE(LEFT($H41, 1)), "") -> 3
A173: SUPERVISER, AUDITER, RÉAGIR | B173: 39 | C173: =IFERROR(VALUE(LEFT($H42, 1)), "") -> 4
A174: SUPERVISER, AUDITER, RÉAGIR | B174: 40 | C174: =IFERROR(VALUE(LEFT($H43, 1)), "") -> 5
A175: POUR ALLER PLUS LOIN | B175: 41 | C175: =IFERROR(VALUE(LEFT($H44, 1)), "") -> 2
A176: POUR ALLER PLUS LOIN | B176: 42 | C176: =IFERROR(VALUE(LEFT($H45, 1)), "") -> 4
A327: Niveau | B327: Nombre
A328: 1 - Insuffisant | B328: =COUNTIF($H$3:$H$100,A328) -> 4
A329: 2 - Émergent | B329: =COUNTIF($H$3:$H$100,A329) -> 9
A330: 3 - Intermédiaire | B330: =COUNTIF($H$3:$H$100,A330) -> 7
A331: 4 - Confirmé | B331: =COUNTIF($H$3:$H$100,A331) -> 7
A332: 5 - Optimal | B332: =COUNTIF($H$3:$H$100,A332) -> 8
A333: Non applicable | B333: =COUNTIF($H$3:$H$100,A333) -> 7

Sheet Dashboard guide de lANSSI

Sheet DORA
A2: Domaine | B2: ID Contrôle | C2: Exigence / contrôle | D2: Description simple | E2: Description complète | F2: Type d’actif | G2: Fonction sécurité | H2: Preuve attendue | I2: Niveau de maturité | J2: Description du niveau | K2: Risque encouru | L2: Commentaire | M2: Recommendation
A3: I. GESTION DES RISQUES TIC | B3: 1 | C3: Définir la responsabilité de la direction | D3: Impliquer activement la direction générale dans la sécurité de l'information, incluant la validation des budgets et l'endossement de la responsabilité des risques numériques. | E3: La direction doit porter la responsabilité finale de la gestion du risque TIC. Elle doit valider les politiques, approuver et revoir la stratégie de résilience numérique, les plans de continuité, les plans de réponse et de récupération, les audits TIC, les budgets et les dispositifs de suivi des prestataires TIC. | F3: Organisation | G3: Gouverner | H3: Procès-verbal, politique validée, responsabilités formalisées | I3: 5 - Optimal | J3: {=IFERROR(INDEX('Echelle de maturité'!$B$2:$B$7, MATCH(I3, 'Echelle de maturité'!$C$2:$C$7, 0)), "")} -> Des objectifs de réduction des risques cyber intégrés à la stratégie de l'organisation. Des moyens humains, budgétaires conséquents, un plan d'action cyber exhaustif, adapté aux menaces stratégiques. | K3: {=MAP(C3:C34, I3:I34, LAMBDA(exigence, niveau, IF(OR(niveau="1 - Insuffisant", niveau="2 - Émergent"), IFERROR(VLOOKUP(exigence, {"Définir la responsabilité de la direction","Absence de vision stratégique et de budget adéquat. En cas de crise, la responsabilité légale des dirigeants peut être engagée." ; "Définir les rôles et responsabilités TIC","Confusion dans les actions de sécurité et conflits d'intérêts. Risque d'inaction ou de mauvaise gestion lors d'un incident critique." ; "Mettre en place un cadre de gestion des risques TIC","Pilotage à l'aveugle de la sécurité. Les vulnérabilités majeures peuvent passer inaperçues jusqu'à l'exploitation par un attaquant." ; "Documenter les politiques, procédures et outils TIC","Perte de connaissance et pratiques hétérogènes. Difficulté à maintenir un niveau de sécurité constant et à prouver la conformité." ; "Réaliser des audits internes TIC","Sentiment de fausse sécurité. Les failles systémiques s'accumulent sans être détectées ni corrigées." ; "Définir une stratégie de résilience numérique","Incapacité à maintenir l'activité en cas de crise majeure. Risque de paralysie prolongée et de pertes financières massives." ; "Identifier les actifs informationnels et TIC","Impossibilité de protéger ce qu'on ne connaît pas. Des actifs critiques 'fantômes' peuvent servir de porte d'entrée aux attaquants." ; "Protéger les actifs TIC","Exposition directe aux cyberattaques. Risque élevé de compromission, de vol de données ou de destruction d'infrastructures." ; "Maintenir des systèmes TIC fiables et à jour","Exploitation facile de vulnérabilités connues par les cybercriminels. Risque d'intrusion automatisée via des failles non patchées." ; "Détecter les anomalies et incidents TIC","Les attaquants peuvent rester cachés longtemps dans le réseau. L'impact de l'attaque s'aggrave avec le temps de détection." ; "Mettre en place une politique de continuité TIC","Arrêt total des opérations en cas de sinistre. Incapacité à fournir les services essentiels aux clients." ; "Définir des plans de réponse et de récupération","Panique et désorganisation lors d'une cyberattaque. Les dommages s'amplifient par manque de réaction coordonnée." ; "Définir des sauvegardes et restaurations","Perte définitive de données critiques suite à un ransomware ou un sinistre. Impossibilité de relancer l'activité." ; "Mettre en place un processus de gestion des incidents TIC","Traitement inefficace des incidents. Les mêmes attaques peuvent se reproduire sans amélioration des défenses." ; "Classifier les incidents selon leur gravité","Gaspillage des ressources sur des incidents mineurs au détriment des crises réelles. Risque de mauvaise appréciation de l'impact." ; "Notifier les incidents TIC majeurs","Sanctions réglementaires sévères et amendes. Perte de confiance des autorités et des partenaires." ; "Conserver une trace des incidents TIC","Incapacité à tirer les leçons du passé. L'organisation reste vulnérable aux mêmes méthodes d'attaque." ; "Prévoir une stratégie de communication en cas d’incident TIC","Communication chaotique en temps de crise. Atteinte grave à la réputation et perte de confiance des clients." ; "Réaliser des tests de résilience basiques","Découverte des failles par les attaquants plutôt que par l'organisation. Augmentation de la surface d'attaque exploitable." ; "Réaliser des tests de pénétration fondés sur la menace (TLPT)","Illusion de sécurité face à des attaquants avancés. Les défenses ne sont pas éprouvées contre des scénarios réels complexes." ; "Corriger les faiblesses détectées lors des tests","Les vulnérabilités connues restent exploitables. Négligence coupable facilitant grandement le travail des cybercriminels." ; "Gérer les risques liés aux tiers TIC","Compromission de l'organisation via un partenaire moins sécurisé (attaque par rebond). Fuite de données confiées à des tiers." ; "Tenir un registre des contrats TIC","Perte de contrôle sur les prestataires et les données externalisées. Difficulté à évaluer l'exposition globale aux risques." ; "Évaluer les prestataires avant contrat","Intégration de partenaires vulnérables dans l'écosystème. Introduction de failles de sécurité dès le début de la relation." ; "Définir les exigences contractuelles","Aucun levier juridique pour imposer des mesures de sécurité. Impossibilité d'exiger des réparations en cas de défaillance du tiers." ; "Prévoir des droits d’audit et de contrôle","Confiance aveugle envers les prestataires. Impossibilité de vérifier la réalité des mesures de sécurité annoncées." ; "Prévoir une stratégie de sortie","Dépendance totale à un prestataire (vendor lock-in). Risque de paralysie si le partenaire fait faillite ou subit une attaque." ; "Participer au partage d'informations sur les menaces","Isolement face aux nouvelles menaces. L'organisation réagit avec retard par rapport au reste du secteur financier." ; "Réaliser des revues post-incident","Répétition des mêmes erreurs de gestion de crise. Aucune amélioration continue de la résilience." ; "Intégrer les leçons apprises","Stagnation du niveau de sécurité. L'organisation n'évolue pas au même rythme que les techniques d'attaque." ; "Former et sensibiliser le personnel","Les employés deviennent le maillon faible (phishing, ingénierie sociale). Augmentation des incidents liés à des erreurs humaines." ; "Suivre les évolutions technologiques et les cybermenaces","Obsolescence des mesures de défense. L'organisation devient une cible facile pour les nouvelles méthodes d'attaque."}, 2, FALSE), ""), "")))}
B4: 2 | C4: Définir les rôles et responsabilités TIC | D4: Définir clairement et formaliser les rôles et responsabilités de chaque collaborateur en matière de sécurité de l'information. | E4: Définir clairement les rôles et responsabilités liés aux fonctions TIC, à la sécurité, à la gestion des risques, au contrôle et à l’audit. L’organisation doit assurer une séparation suffisante entre les fonctions de gestion du risque TIC, les fonctions de contrôle et l’audit interne afin d’éviter les conflits d’intérêts. | F4: Organisation | G4: Gouverner | H4: Organigramme, fiches de rôles, matrice RACI | I4: 2 - Émergent | J4: {=IFERROR(INDEX('Echelle de maturité'!$B$2:$B$7, MATCH(I4, 'Echelle de maturité'!$C$2:$C$7, 0)), "")} -> Une prise de conscience de l'existence de risques cyber pour l'organisation et une volonté de mettre en place des premières mesures cyber pertinentes. | K4: Confusion dans les actions de sécurité et conflits d'intérêts. Risque d'inaction ou de mauvaise gestion lors d'un incident critique.
B5: 3 | C5: Mettre en place un cadre de gestion des risques TIC | D5: Structurer la démarche de sécurité via un cadre de référence documentant l'identification, l'évaluation et le traitement des risques TIC. | E5: Mettre en place un cadre de gestion des risques TIC solide, complet et documenté, intégré au dispositif global de gestion des risques. Ce cadre doit permettre d’identifier, de protéger, de détecter, de répondre, de récupérer et de suivre les risques liés aux technologies de l’information et de la communication. | F5: Organisation | G5: Gouverner | H5: Politique de gestion des risques TIC, procédure, registre des risques | I5: 4 - Confirmé | J5: {=IFERROR(INDEX('Echelle de maturité'!$B$2:$B$7, MATCH(I5, 'Echelle de maturité'!$C$2:$C$7, 0)), "")} -> Une cartographie précise de ses risques cyber pour l'organisation, un plan d'action cyber approfondi et des moyens humains et budgétaires dédiés.
B6: 4 | C6: Documenter les politiques, procédures et outils TIC | D6: Documenter, valider par la direction et mettre à jour régulièrement l'ensemble des politiques et procédures de sécurité de l'information. | E6: Documenter les stratégies, politiques, procédures, protocoles et outils TIC nécessaires à la gestion du risque TIC. Cette documentation doit être tenue à jour, revue régulièrement et permettre de démontrer la manière dont l’organisation protège ses actifs informationnels, ses systèmes, ses infrastructures et ses services critiques. | F6: Organisation | G6: Gouverner | H6: Politiques, procédures et stratégies documentées | I6: 4 - Confirmé | J6: {=IFERROR(INDEX('Echelle de maturité'!$B$2:$B$7, MATCH(I6, 'Echelle de maturité'!$C$2:$C$7, 0)), "")} -> Une cartographie précise de ses risques cyber pour l'organisation, un plan d'action cyber approfondi et des moyens humains et budgétaires dédiés.
B7: 5 | C7: Réaliser des audits internes TIC | D7: Réaliser régulièrement des audits internes ou externes indépendants pour vérifier l'application des règles de sécurité et identifier les axes d'amélioration. | E7: Soumettre régulièrement le cadre de gestion des risques TIC à des audits internes réalisés par des personnes disposant de compétences suffisantes en risque TIC et d’une indépendance appropriée. Les constats d’audit doivent donner lieu à un suivi formalisé et à la correction des points critiques identifiés. | F7: Processus | G7: Gouverner / Évaluer | H7: Rapports d'audit interne, plan d'action post-audit. | I7: 5 - Optimal | J7: {=IFERROR(INDEX('Echelle de maturité'!$B$2:$B$7, MATCH(I7, 'Echelle de maturité'!$C$2:$C$7, 0)), "")} -> Des objectifs de réduction des risques cyber intégrés à la stratégie de l'organisation. Des moyens humains, budgétaires conséquents, un plan d'action cyber exhaustif, adapté aux menaces stratégiques.
B8: 6 | C8: Définir une stratégie de résilience numérique | D8: Élaborer une stratégie de résilience numérique à long terme pour assurer la continuité des opérations en cas d'incident informatique majeur. | E8: Définir une stratégie de résilience opérationnelle numérique expliquant comment le cadre de gestion du risque TIC soutient les objectifs de l’organisation. Cette stratégie doit préciser la tolérance au risque TIC, les objectifs de sécurité, les mécanismes de détection et de protection, les tests de résilience et la stratégie de communication en cas d’incident. | F8: Organisation | G8: Gouverner | H8: Stratégie de résilience numérique documentée et approuvée | I8: 5 - Optimal | J8: {=IFERROR(INDEX('Echelle de maturité'!$B$2:$B$7, MATCH(I8, 'Echelle de maturité'!$C$2:$C$7, 0)), "")} -> Des objectifs de réduction des risques cyber intégrés à la stratégie de l'organisation. Des moyens humains, budgétaires conséquents, un plan d'action cyber exhaustif, adapté aux menaces stratégiques.
B9: 7 | C9: Identifier les actifs informationnels et TIC | D9: Réaliser un inventaire exhaustif et évaluer la criticité des actifs matériels, logiciels et des données sensibles. | E9: Identifier, classer et documenter les actifs informationnels et TIC nécessaires aux activités de l’organisation. Cela comprend notamment les données, logiciels, matériels, serveurs, infrastructures, locaux sensibles, services critiques, dépendances internes et externes, ainsi que leurs interconnexions. | F9: Matériel / Logiciel / Information | G9: Identifier | H9: Cartographie des actifs, registre des actifs | I9: 5 - Optimal | J9: {=IFERROR(INDEX('Echelle de maturité'!$B$2:$B$7, MATCH(I9, 'Echelle de maturité'!$C$2:$C$7, 0)), "")} -> Des objectifs de réduction des risques cyber intégrés à la stratégie de l'organisation. Des moyens humains, budgétaires conséquents, un plan d'action cyber exhaustif, adapté aux menaces stratégiques.
B10: 8 | C10: Protéger les actifs TIC | D10: Implémenter des mesures de protection techniques et organisationnelles (gestion des accès, mots de passe robustes, chiffrement) pour sécuriser les actifs. | E10: Protéger les actifs informationnels et TIC contre les risques, notamment les dommages, les accès non autorisés, les usages abusifs, les pertes d’intégrité, d’authenticité, de confidentialité ou de disponibilité. Les mesures doivent couvrir les accès, les systèmes, les données, les infrastructures et les composants physiques sensibles. | F10: Matériel / Logiciel / Information | G10: Protéger | H10: Politiques de sécurité, preuves de chiffrement, gestion des accès | I10: 4 - Confirmé | J10: {=IFERROR(INDEX('Echelle de maturité'!$B$2:$B$7, MATCH(I10, 'Echelle de maturité'!$C$2:$C$7, 0)), "")} -> Une cartographie précise de ses risques cyber pour l'organisation, un plan d'action cyber approfondi et des moyens humains et budgétaires dédiés.
B11: 9 | C11: Maintenir des systèmes TIC fiables et à jour | D11: Maintenir en condition de sécurité les systèmes par l'application régulière et systématique des correctifs et mises à jour de sécurité. | E11: Utiliser et maintenir des systèmes, protocoles et outils TIC fiables, adaptés à l’activité, suffisamment résilients et régulièrement mis à jour. Les systèmes doivent permettre d’assurer la sécurité, la continuité des services, la disponibilité, l’intégrité, l’authenticité et la confidentialité des données. | F11: Matériel / Logiciel | G11: Protéger | H11: Politique de gestion des correctifs, rapports de mise à jour | I11: 5 - Optimal | J11: {=IFERROR(INDEX('Echelle de maturité'!$B$2:$B$7, MATCH(I11, 'Echelle de maturité'!$C$2:$C$7, 0)), "")} -> Des objectifs de réduction des risques cyber intégrés à la stratégie de l'organisation. Des moyens humains, budgétaires conséquents, un plan d'action cyber exhaustif, adapté aux menaces stratégiques.
B12: 10 | C12: Détecter les anomalies et incidents TIC | D12: Déployer des solutions de détection pour identifier rapidement les activités suspectes ou malveillantes sur le réseau et les systèmes. | E12: Mettre en place des mécanismes permettant d’identifier rapidement les sources de risque TIC, les anomalies, les activités suspectes, les incidents et les points de défaillance. Ces mécanismes doivent permettre une détection rapide et un traitement efficace des incidents liés aux TIC. | F12: Matériel / Logiciel / Réseau | G12: Détecter | H12: Outils de surveillance (SIEM, SOC), journaux d'événements | I12: 1 - Insuffisant | J12: {=IFERROR(INDEX('Echelle de maturité'!$B$2:$B$7, MATCH(I12, 'Echelle de maturité'!$C$2:$C$7, 0)), "")} -> Une conscience insuffisante des risques cyber pesant sur l'organisation. Pas ou peu de mesures spécifiques mises en oeuvre en matière de cybersécurité. | K12: Les attaquants peuvent rester cachés longtemps dans le réseau. L'impact de l'attaque s'aggrave avec le temps de détection.
B13: 11 | C13: Mettre en place une politique de continuité TIC | D13: Élaborer un plan de continuité d'activité (PCA) pour garantir le maintien des services essentiels en cas de défaillance majeure des systèmes TIC. | E13: Établir une politique de continuité d’activité TIC permettant de maintenir les fonctions critiques ou importantes en cas d’incident ou de perturbation importante. Cette politique doit intégrer l’analyse d’impact, les dépendances critiques, les prestataires tiers, les systèmes de sauvegarde et les scénarios de crise. | F13: Organisation / Processus | G13: Répondre / Récupérer | H13: Politique de continuité des activités (PCA/PRA) | I13: 1 - Insuffisant | J13: {=IFERROR(INDEX('Echelle de maturité'!$B$2:$B$7, MATCH(I13, 'Echelle de maturité'!$C$2:$C$7, 0)), "")} -> Une conscience insuffisante des risques cyber pesant sur l'organisation. Pas ou peu de mesures spécifiques mises en oeuvre en matière de cybersécurité. | K13: Arrêt total des opérations en cas de sinistre. Incapacité à fournir les services essentiels aux clients.
B14: 12 | C14: Définir des plans de réponse et de récupération | D14: Formaliser et tester régulièrement les plans de réponse aux incidents pour assurer une réaction efficace et coordonnée en cas de cyberattaque. | E14: Mettre en place des plans de réponse et de récupération TIC afin de gérer rapidement les incidents, limiter leurs impacts, restaurer les services affectés et assurer le retour à un fonctionnement sécurisé. Ces plans doivent être testés, revus et adaptés aux fonctions critiques ou importantes. | F14: Organisation / Processus | G14: Répondre / Récupérer | H14: Plans de réponse aux incidents, rapports de tests | I14: 4 - Confirmé | J14: {=IFERROR(INDEX('Echelle de maturité'!$B$2:$B$7, MATCH(I14, 'Echelle de maturité'!$C$2:$C$7, 0)), "")} -> Une cartographie précise de ses risques cyber pour l'organisation, un plan d'action cyber approfondi et des moyens humains et budgétaires dédiés.
B15: 13 | C15: Définir des sauvegardes et restaurations | D15: Mettre en œuvre une politique de sauvegarde régulière et sécurisée, accompagnée de tests fréquents de restauration des données. | E15: Définir des politiques et procédures de sauvegarde, de restauration et de récupération permettant de restaurer les systèmes et les données avec un temps d’arrêt limité, une perte minimale et un haut niveau d’intégrité. Les sauvegardes doivent être adaptées à la criticité des données et testées régulièrement. | F15: Information / Logiciel | G15: Récupérer | H15: Politique de sauvegarde, journaux de sauvegarde, tests de restauration | I15: 2 - Émergent | J15: {=IFERROR(INDEX('Echelle de maturité'!$B$2:$B$7, MATCH(I15, 'Echelle de maturité'!$C$2:$C$7, 0)), "")} -> Une prise de conscience de l'existence de risques cyber pour l'organisation et une volonté de mettre en place des premières mesures cyber pertinentes. | K15: Perte définitive de données critiques suite à un ransomware ou un sinistre. Impossibilité de relancer l'activité.
A16: II. GESTION, CLASSIFICATION ET SIGNALEMENT DES INCIDENTS LIÉS AUX TIC | B16: 14 | C16: Mettre en place un processus de gestion des incidents TIC | D16: Établir un processus formel pour le signalement, l'analyse, la résolution et la communication liés aux incidents informatiques. | E16: Établir et mettre en œuvre un processus de gestion des incidents TIC permettant de détecter, gérer, suivre et notifier les incidents. Ce processus doit permettre l’enregistrement des incidents, l’analyse des causes, le traitement, le suivi et la prévention de leur réapparition. | F16: Processus | G16: Répondre | H16: Procédure de gestion des incidents, registre des incidents | I16: 2 - Émergent | J16: {=IFERROR(INDEX('Echelle de maturité'!$B$2:$B$7, MATCH(I16, 'Echelle de maturité'!$C$2:$C$7, 0)), "")} -> Une prise de conscience de l'existence de risques cyber pour l'organisation et une volonté de mettre en place des premières mesures cyber pertinentes. | K16: Traitement inefficace des incidents. Les mêmes attaques peuvent se reproduire sans amélioration des défenses.
B17: 15 | C17: Classifier les incidents selon leur gravité | D17: Définir une méthodologie de classification des incidents selon leur gravité afin d'adapter les mesures de réponse de manière proportionnée. | E17: Classifier les incidents TIC selon leur priorité, leur gravité et leur impact. La classification doit prendre en compte les clients ou contreparties touchés, la durée de l’incident, l’étendue géographique, les pertes de données, la criticité des services affectés et l’impact économique. | F17: Processus | G17: Identifier / Répondre | H17: Critères de classification, rapports d'incidents classifiés | I17: 2 - Émergent | J17: {=IFERROR(INDEX('Echelle de maturité'!$B$2:$B$7, MATCH(I17, 'Echelle de maturité'!$C$2:$C$7, 0)), "")} -> Une prise de conscience de l'existence de risques cyber pour l'organisation et une volonté de mettre en place des premières mesures cyber pertinentes. | K17: Gaspillage des ressources sur des incidents mineurs au détriment des crises réelles. Risque de mauvaise appréciation de l'impact.
B18: 16 | C18: Notifier les incidents TIC majeurs | D18: L’organisation doit déclarer les incidents TIC majeurs aux autorités compétentes selon les modalités prévues. | E18: Notifier les incidents TIC majeurs aux autorités compétentes selon les modalités et délais prévus. L’organisation doit être capable d’identifier les incidents majeurs, de préparer les informations nécessaires et de transmettre les déclarations officielles aux autorités concernées. | F18: Processus | G18: Notifier | H18: Procédure de notification, modèle de déclaration, registre des incidents déclarés | I18: 2 - Émergent | J18: {=IFERROR(INDEX('Echelle de maturité'!$B$2:$B$7, MATCH(I18, 'Echelle de maturité'!$C$2:$C$7, 0)), "")} -> Une prise de conscience de l'existence de risques cyber pour l'organisation et une volonté de mettre en place des premières mesures cyber pertinentes. | K18: Sanctions réglementaires sévères et amendes. Perte de confiance des autorités et des partenaires.
B19: 17 | C19: Conserver une trace des incidents TIC | D19: L’organisation doit documenter les incidents, leur gravité, leur traitement et les actions correctives mises en place. | E19: Enregistrer tous les incidents TIC et les cybermenaces significatives. L’organisation doit conserver une traçabilité des incidents, documenter leur traitement, identifier les causes profondes, suivre les actions correctives et utiliser ces informations pour éviter que les incidents ne se reproduisent. | F19: Information / Organisation | G19: Récupérer | I19: 3 - Intermédiaire | J19: {=IFERROR(INDEX('Echelle de maturité'!$B$2:$B$7, MATCH(I19, 'Echelle de maturité'!$C$2:$C$7, 0)), "")} -> Une conscience partagée des risques cyber pour l'organisation et la volonté de formaliser un plan d'action cyber complet tout en ajustant les moyens en conséquence.
B20: 18 | C20: Prévoir une stratégie de communication en cas d’incident TIC | D20: L’organisation doit savoir comment communiquer en cas d’incident TIC important, en interne et si nécessaire vers les autorités, clients ou parties concernées. | E20: Prévoir une stratégie de communication en cas d’incident TIC. L’organisation doit définir comment communiquer avec le personnel, les parties externes, les médias, les clients et les autorités compétentes, ainsi que les procédures d’escalade interne et de notification lorsque cela est nécessaire. | F20: Processus | G20: Évaluer | H20: Plan de communication de crise, procédure de communication, modèles de messages | I20: 3 - Intermédiaire | J20: {=IFERROR(INDEX('Echelle de maturité'!$B$2:$B$7, MATCH(I20, 'Echelle de maturité'!$C$2:$C$7, 0)), "")} -> Une conscience partagée des risques cyber pour l'organisation et la volonté de formaliser un plan d'action cyber complet tout en ajustant les moyens en conséquence.
A21: III. TESTS DE RÉSILIENCE OPÉRATIONNELLE NUMÉRIQUE | B21: 19 | C21: Réaliser des tests de résilience basiques | D21: Effectuer régulièrement des tests de vulnérabilité et des évaluations de la sécurité du réseau. | E21: Mettre en place un programme de tests de résilience opérationnelle numérique afin de vérifier régulièrement l’efficacité des outils, systèmes, protocoles, procédures et mesures de sécurité TIC. Ces tests doivent permettre d’identifier les faiblesses, vulnérabilités ou lacunes dans le dispositif de résilience. | F21: Réseau / Logiciel | G21: Évaluer | H21: Rapports de tests de vulnérabilité, plan de remédiation | I21: 4 - Confirmé | J21: {=IFERROR(INDEX('Echelle de maturité'!$B$2:$B$7, MATCH(I21, 'Echelle de maturité'!$C$2:$C$7, 0)), "")} -> Une cartographie précise de ses risques cyber pour l'organisation, un plan d'action cyber approfondi et des moyens humains et budgétaires dédiés.
B22: 20 | C22: Réaliser des tests de pénétration fondés sur la menace (TLPT) | D22: Pour les entités critiques, réaliser des tests avancés simulant des attaques réelles (Red Teaming). | E22: Réaliser, pour les entités concernées, des tests avancés de pénétration fondés sur la menace, appelés TLPT. Ces tests doivent simuler des attaques réalistes sur les fonctions critiques ou importantes et être réalisés selon des exigences encadrées, avec des testeurs disposant des compétences et garanties nécessaires. | F22: Organisation / Réseau / Logiciel | G22: Évaluer | H22: Rapports TLPT, attestations de réalisation | I22: 4 - Confirmé | J22: {=IFERROR(INDEX('Echelle de maturité'!$B$2:$B$7, MATCH(I22, 'Echelle de maturité'!$C$2:$C$7, 0)), "")} -> Une cartographie précise de ses risques cyber pour l'organisation, un plan d'action cyber approfondi et des moyens humains et budgétaires dédiés.
B23: 21 | C23: Corriger les faiblesses détectées lors des tests | D23: Après les tests, l’organisation doit analyser les résultats, corriger les vulnérabilités et suivre les actions de remédiation. | E23: Analyser les résultats des tests de résilience et mettre en place des plans de remédiation. Les vulnérabilités, faiblesses ou insuffisances détectées doivent être corrigées, documentées et suivies jusqu’à leur résolution afin d’améliorer le niveau de résilience numérique. | F23: Organisation / Processus | G23: Améliorer | H23: Plan de remédiation, suivi des corrections, rapport de test | I23: 2 - Émergent | J23: {=IFERROR(INDEX('Echelle de maturité'!$B$2:$B$7, MATCH(I23, 'Echelle de maturité'!$C$2:$C$7, 0)), "")} -> Une prise de conscience de l'existence de risques cyber pour l'organisation et une volonté de mettre en place des premières mesures cyber pertinentes. | K23: Les vulnérabilités connues restent exploitables. Négligence coupable facilitant grandement le travail des cybercriminels.
A24: IV. GESTION DES RISQUES LIÉS AUX PRESTATAIRES TIERS DE SERVICES TIC | B24: 22 | C24: Gérer les risques liés aux tiers TIC | D24: Évaluer les risques avant de contracter avec un prestataire tiers et tenir un registre des accords. | E24: Gérer les risques liés aux prestataires tiers TIC comme une composante du risque TIC global. L’organisation reste pleinement responsable de ses obligations même lorsqu’elle externalise des services TIC, et doit surveiller les dépendances, la criticité des services et l’impact potentiel sur la continuité des activités. | F24: Organisation | G24: Gouverner / Évaluer | H24: Registre des informations, évaluations des risques tiers | I24: 4 - Confirmé | J24: {=IFERROR(INDEX('Echelle de maturité'!$B$2:$B$7, MATCH(I24, 'Echelle de maturité'!$C$2:$C$7, 0)), "")} -> Une cartographie précise de ses risques cyber pour l'organisation, un plan d'action cyber approfondi et des moyens humains et budgétaires dédiés.
B25: 23 | C25: Tenir un registre des contrats TIC | D25: L’organisation doit maintenir un registre des contrats conclus avec les prestataires TIC. | E25: Maintenir et mettre à jour un registre des contrats conclus avec les prestataires tiers TIC. Ce registre doit distinguer les contrats portant sur des fonctions critiques ou importantes et contenir les informations nécessaires à la supervision des dépendances et des services TIC externalisés. | F25: Organisation | G25: Identifier | H25: Registre des contrats TIC, liste des prestataires, cartographie des dépendances | I25: 4 - Confirmé | J25: {=IFERROR(INDEX('Echelle de maturité'!$B$2:$B$7, MATCH(I25, 'Echelle de maturité'!$C$2:$C$7, 0)), "")} -> Une cartographie précise de ses risques cyber pour l'organisation, un plan d'action cyber approfondi et des moyens humains et budgétaires dédiés.
B26: 24 | C26: Évaluer les prestataires avant contrat | D26: Avant de signer, l’organisation doit analyser la criticité du service, les risques associés et la capacité du prestataire à respecter les exigences de sécurité. | E26: Évaluer les prestataires TIC avant la conclusion d’un contrat. L’organisation doit analyser la criticité du service, les risques associés, les conditions de supervision, les conflits d’intérêts possibles, les dépendances et la capacité du prestataire à respecter les exigences de sécurité et de résilience. | F26: Organisation | G26: Évaluer | H26: Analyse précontractuelle, questionnaire fournisseur, due diligence | I26: 4 - Confirmé | J26: {=IFERROR(INDEX('Echelle de maturité'!$B$2:$B$7, MATCH(I26, 'Echelle de maturité'!$C$2:$C$7, 0)), "")} -> Une cartographie précise de ses risques cyber pour l'organisation, un plan d'action cyber approfondi et des moyens humains et budgétaires dédiés.
B27: 25 | C27: Définir les exigences contractuelles | D27: S'assurer que les contrats avec les tiers incluent des clauses spécifiques de sécurité, d'audit et de résiliation. | E27: Définir dans les contrats TIC les exigences essentielles relatives aux services fournis, aux niveaux de service, aux lieux de traitement des données, à la disponibilité, l’intégrité, la sécurité, la protection des données, l’assistance en cas d’incident, la coopération avec les autorités et les conditions de résiliation. | F27: Organisation | G27: Gouverner | H27: Contrats signés avec clauses DORA, politique d'externalisation | I27: 5 - Optimal | J27: {=IFERROR(INDEX('Echelle de maturité'!$B$2:$B$7, MATCH(I27, 'Echelle de maturité'!$C$2:$C$7, 0)), "")} -> Des objectifs de réduction des risques cyber intégrés à la stratégie de l'organisation. Des moyens humains, budgétaires conséquents, un plan d'action cyber exhaustif, adapté aux menaces stratégiques.
B28: 26 | C28: Prévoir des droits d’audit et de contrôle | D28: Les contrats doivent permettre à l’organisation de contrôler ou auditer le prestataire TIC lorsque nécessaire. | E28: Prévoir dans les contrats des droits d’accès, d’inspection et d’audit permettant à l’organisation, à un tiers désigné ou à l’autorité compétente de contrôler le prestataire TIC. Ces droits doivent permettre de vérifier la performance, la sécurité et la maîtrise des risques liés au prestataire. | F28: Organisation | G28: Contrôler | H28: Clauses d’audit, rapports fournisseur, droit d’accès / inspection | I28: 5 - Optimal | J28: {=IFERROR(INDEX('Echelle de maturité'!$B$2:$B$7, MATCH(I28, 'Echelle de maturité'!$C$2:$C$7, 0)), "")} -> Des objectifs de réduction des risques cyber intégrés à la stratégie de l'organisation. Des moyens humains, budgétaires conséquents, un plan d'action cyber exhaustif, adapté aux menaces stratégiques.
B29: 27 | C29: Prévoir une stratégie de sortie | D29: L’organisation doit pouvoir changer de prestataire ou réinternaliser le service sans interruption majeure. | E29: Prévoir une stratégie de sortie pour les services TIC externalisés, notamment lorsque ceux-ci soutiennent des fonctions critiques ou importantes. Cette stratégie doit permettre de changer de prestataire, de transférer le service ou de le réinternaliser en limitant les interruptions et les risques pour l’activité. | F29: Organisation | G29: Récupérer | H29: Plan de sortie, clauses de réversibilité, procédure de transfert | I29: 5 - Optimal | J29: {=IFERROR(INDEX('Echelle de maturité'!$B$2:$B$7, MATCH(I29, 'Echelle de maturité'!$C$2:$C$7, 0)), "")} -> Des objectifs de réduction des risques cyber intégrés à la stratégie de l'organisation. Des moyens humains, budgétaires conséquents, un plan d'action cyber exhaustif, adapté aux menaces stratégiques.
A30: V. PARTAGE D'INFORMATIONS | B30: 28 | C30: Participer au partage d'informations sur les menaces | D30: Mettre en place des accords pour partager des renseignements sur les cybermenaces avec d'autres entités financières. | E30: Participer, lorsque cela est approprié, à des dispositifs de partage d’informations sur les cybermenaces et vulnérabilités. Ce partage doit permettre d’améliorer la prévention, la détection, la réponse collective et la capacité du secteur financier à limiter la propagation des risques TIC. | F30: Information / Organisation | G30: Protéger / Répondre | H30: Accords de partage d'informations, preuves de participation à des réseaux d'échange | I30: 5 - Optimal | J30: {=IFERROR(INDEX('Echelle de maturité'!$B$2:$B$7, MATCH(I30, 'Echelle de maturité'!$C$2:$C$7, 0)), "")} -> Des objectifs de réduction des risques cyber intégrés à la stratégie de l'organisation. Des moyens humains, budgétaires conséquents, un plan d'action cyber exhaustif, adapté aux menaces stratégiques.
A31: VI. APPRENTISSAGE ET EVOLUTION | B31: 29 | C31: Réaliser des revues post-incident | D31: Après un incident TIC majeur, l’organisation doit analyser les causes, vérifier si les procédures ont été suivies et identifier les améliorations nécessaires. | E31: Réaliser des revues post-incident après un incident TIC majeur ayant perturbé les activités essentielles. Ces revues doivent analyser les causes, vérifier si les procédures ont été suivies, évaluer l’efficacité de la réponse, de l’escalade, de l’analyse technique et de la communication interne ou externe. | F31: Processus | G31: Améliorer | H31: Rapport post-incident, plan d’action | I31: 5 - Optimal | J31: {=IFERROR(INDEX('Echelle de maturité'!$B$2:$B$7, MATCH(I31, 'Echelle de maturité'!$C$2:$C$7, 0)), "")} -> Des objectifs de réduction des risques cyber intégrés à la stratégie de l'organisation. Des moyens humains, budgétaires conséquents, un plan d'action cyber exhaustif, adapté aux menaces stratégiques.
B32: 30 | C32: Intégrer les leçons apprises | D32: Les incidents réels, les tests et les audits doivent servir à améliorer l’évaluation des risques TIC. | E32: Intégrer de manière continue les leçons tirées des incidents réels, des tests de résilience, des audits, des plans de continuité et des échanges avec d’autres acteurs dans le processus d’évaluation du risque TIC. Ces enseignements doivent servir à revoir et améliorer le cadre de gestion du risque TIC. | F32: Organisation / Processus | G32: Améliorer | H32: Plan d’amélioration, suivi des corrections | I32: 5 - Optimal | J32: {=IFERROR(INDEX('Echelle de maturité'!$B$2:$B$7, MATCH(I32, 'Echelle de maturité'!$C$2:$C$7, 0)), "")} -> Des objectifs de réduction des risques cyber intégrés à la stratégie de l'organisation. Des moyens humains, budgétaires conséquents, un plan d'action cyber exhaustif, adapté aux menaces stratégiques.
B33: 31 | C33: Former et sensibiliser le personnel | D33: Le personnel et la direction doivent être formés aux risques TIC et à la résilience numérique. | E33: Développer des programmes de sensibilisation à la sécurité TIC et de formation à la résilience opérationnelle numérique. Ces formations doivent être intégrées au parcours de formation du personnel et concerner aussi la direction, avec un niveau adapté aux responsabilités de chacun. | F33: Personnel / Organisation | G33: Sensibiliser | H33: Plan de formation, preuve de participation | I33: 3 - Intermédiaire | J33: {=IFERROR(INDEX('Echelle de maturité'!$B$2:$B$7, MATCH(I33, 'Echelle de maturité'!$C$2:$C$7, 0)), "")} -> Une conscience partagée des risques cyber pour l'organisation et la volonté de formaliser un plan d'action cyber complet tout en ajustant les moyens en conséquence.
B34: 32 | C34: Suivre les évolutions technologiques et les cybermenaces | D34: L’organisation doit suivre les nouvelles menaces et technologies afin d’adapter son dispositif de sécurité. | E34: Assurer une veille continue sur les évolutions technologiques, les nouvelles menaces, les formes récentes de cyberattaques et les pratiques de gestion du risque TIC. L’organisation doit utiliser cette veille pour adapter ses exigences de sécurité et maintenir un niveau de résilience numérique adapté. | F34: Organisation / Information | G34: Améliorer / Détecter | H34: Veille cyber, rapports de surveillance | I34: Non applicable | J34: {=IFERROR(INDEX('Echelle de maturité'!$B$2:$B$7, MATCH(I34, 'Echelle de maturité'!$C$2:$C$7, 0)), "")} -> Le critère ou l'exigence évalué n'est pas pertinent au regard des activités, du périmètre technique ou du cadre réglementaire de l'organisation.
A35: Score global DORA | I35: =(COUNTIF(I3:I34,"1 - Insuffisant")*1 +COUNTIF(I3:I34,"2 - Émergent")*2 +COUNTIF(I3:I34,"3 - Intermédiaire")*3 +COUNTIF(I3:I34,"4 - Confirmé")*4 +COUNTIF(I3:I34,"5 - Optimal")*5) & "/" & (ROWS(I3:I34)*5) -> 114/160 | J35: =ROUND((LEFT(I35,SEARCH("/",I35)-1)/RIGHT(I35,LEN(I35)-SEARCH("/",I35)))*5,2)&" / 5" -> 3,56 / 5

Sheet Dashboard Dora
G1: Niveau de maturité | H1: Nombre
G2: Insuffisant | H2: =COUNTIF(DORA!I:I,"1 - Insuffisant") -> 2
G3: Émergent | H3: =COUNTIF(DORA!I:I,"2 - Émergent") -> 6
G4: Intermédiaire | H4: =COUNTIF(DORA!I:I,"3 - Intermédiaire") -> 3
G5: Confirmé | H5: =COUNTIF(DORA!I:I,"4 - Confirmé") -> 9
G6: Optimal | H6: =COUNTIF(DORA!I:I,"5 - Optimal") -> 11
G7: Non Applicable | H7: =COUNTIF(DORA!I:I,"Non applicable") -> 1
A25: =IFERROR(__xludf.DUMMYFUNCTION("QUERY({SCAN("""", DORA!A3:A34, LAMBDA(acc, val, IF(val="""", acc, val))), DORA!C3:C34}, ""SELECT Col1, COUNT(Col2) WHERE Col1 IS NOT NULL GROUP BY Col1 LABEL Col1 'Domaine', COUNT(Col2) """"Nombre d'exigences"""""")"),"Domaine") -> Domaine | B25: =IFERROR(__xludf.DUMMYFUNCTION("""COMPUTED_VALUE"""),"Nombre d'exigences") -> Nombre d'exigences
A26: =IFERROR(__xludf.DUMMYFUNCTION("""COMPUTED_VALUE"""),"I. GESTION DES RISQUES TIC") -> I. GESTION DES RISQUES TIC | B26: =IFERROR(__xludf.DUMMYFUNCTION("""COMPUTED_VALUE"""),13.0) -> 13
A27: =IFERROR(__xludf.DUMMYFUNCTION("""COMPUTED_VALUE"""),"II. GESTION, CLASSIFICATION ET SIGNALEMENT DES INCIDENTS LIÉS AUX TIC") -> II. GESTION, CLASSIFICATION ET SIGNALEMENT DES INCIDENTS LIÉS AUX TIC | B27: =IFERROR(__xludf.DUMMYFUNCTION("""COMPUTED_VALUE"""),5.0) -> 5
A28: =IFERROR(__xludf.DUMMYFUNCTION("""COMPUTED_VALUE"""),"III. TESTS DE RÉSILIENCE OPÉRATIONNELLE NUMÉRIQUE") -> III. TESTS DE RÉSILIENCE OPÉRATIONNELLE NUMÉRIQUE | B28: =IFERROR(__xludf.DUMMYFUNCTION("""COMPUTED_VALUE"""),3.0) -> 3
A29: =IFERROR(__xludf.DUMMYFUNCTION("""COMPUTED_VALUE"""),"IV. GESTION DES RISQUES LIÉS AUX PRESTATAIRES TIERS DE SERVICES TIC") -> IV. GESTION DES RISQUES LIÉS AUX PRESTATAIRES TIERS DE SERVICES TIC | B29: =IFERROR(__xludf.DUMMYFUNCTION("""COMPUTED_VALUE"""),6.0) -> 6
A30: =IFERROR(__xludf.DUMMYFUNCTION("""COMPUTED_VALUE"""),"V. PARTAGE D'INFORMATIONS") -> V. PARTAGE D'INFORMATIONS | B30: =IFERROR(__xludf.DUMMYFUNCTION("""COMPUTED_VALUE"""),1.0) -> 1
A31: =IFERROR(__xludf.DUMMYFUNCTION("""COMPUTED_VALUE"""),"VI. APPRENTISSAGE ET EVOLUTION") -> VI. APPRENTISSAGE ET EVOLUTION | B31: =IFERROR(__xludf.DUMMYFUNCTION("""COMPUTED_VALUE"""),4.0) -> 4
J47: =IFERROR(__xludf.DUMMYFUNCTION("QUERY({SCAN("""", DORA!A3:A34, LAMBDA(acc, val, IF(val="""", acc, val))), DORA!G3:G34}, ""SELECT Col1, Col2, COUNT(Col2) WHERE Col2 IS NOT NULL GROUP BY Col1, Col2 LABEL Col1 'Domaine', Col2 'Fonction sécurité', COUNT(Col2) 'Nombre'"")"),"Domaine") -> Domaine | K47: =IFERROR(__xludf.DUMMYFUNCTION("""COMPUTED_VALUE"""),"Fonction sécurité") -> Fonction sécurité | L47: =IFERROR(__xludf.DUMMYFUNCTION("""COMPUTED_VALUE"""),"Nombre") -> Nombre | M47: Total
J48: =IFERROR(__xludf.DUMMYFUNCTION("""COMPUTED_VALUE"""),"I. GESTION DES RISQUES TIC") -> I. GESTION DES RISQUES TIC | K48: =IFERROR(__xludf.DUMMYFUNCTION("""COMPUTED_VALUE"""),"Détecter") -> Détecter | L48: =IFERROR(__xludf.DUMMYFUNCTION("""COMPUTED_VALUE"""),1.0) -> 1 | M48: =SUM(L48:L54) -> 13
K49: =IFERROR(__xludf.DUMMYFUNCTION("""COMPUTED_VALUE"""),"Gouverner") -> Gouverner | L49: =IFERROR(__xludf.DUMMYFUNCTION("""COMPUTED_VALUE"""),5.0) -> 5
K50: =IFERROR(__xludf.DUMMYFUNCTION("""COMPUTED_VALUE"""),"Gouverner / Évaluer") -> Gouverner / Évaluer | L50: =IFERROR(__xludf.DUMMYFUNCTION("""COMPUTED_VALUE"""),1.0) -> 1
K51: =IFERROR(__xludf.DUMMYFUNCTION("""COMPUTED_VALUE"""),"Identifier") -> Identifier | L51: =IFERROR(__xludf.DUMMYFUNCTION("""COMPUTED_VALUE"""),1.0) -> 1
K52: =IFERROR(__xludf.DUMMYFUNCTION("""COMPUTED_VALUE"""),"Protéger") -> Protéger | L52: =IFERROR(__xludf.DUMMYFUNCTION("""COMPUTED_VALUE"""),2.0) -> 2
K53: =IFERROR(__xludf.DUMMYFUNCTION("""COMPUTED_VALUE"""),"Récupérer") -> Récupérer | L53: =IFERROR(__xludf.DUMMYFUNCTION("""COMPUTED_VALUE"""),1.0) -> 1
K54: =IFERROR(__xludf.DUMMYFUNCTION("""COMPUTED_VALUE"""),"Répondre / Récupérer") -> Répondre / Récupérer | L54: =IFERROR(__xludf.DUMMYFUNCTION("""COMPUTED_VALUE"""),2.0) -> 2
J55: =IFERROR(__xludf.DUMMYFUNCTION("""COMPUTED_VALUE"""),"II. GESTION, CLASSIFICATION ET SIGNALEMENT DES INCIDENTS LIÉS AUX TIC") -> II. GESTION, CLASSIFICATION ET SIGNALEMENT DES INCIDENTS LIÉS AUX TIC | K55: =IFERROR(__xludf.DUMMYFUNCTION("""COMPUTED_VALUE"""),"Identifier / Répondre") -> Identifier / Répondre | L55: =IFERROR(__xludf.DUMMYFUNCTION("""COMPUTED_VALUE"""),1.0) -> 1 | M55: =SUM(L55:L59) -> 5
K56: =IFERROR(__xludf.DUMMYFUNCTION("""COMPUTED_VALUE"""),"Notifier") -> Notifier | L56: =IFERROR(__xludf.DUMMYFUNCTION("""COMPUTED_VALUE"""),1.0) -> 1
K57: =IFERROR(__xludf.DUMMYFUNCTION("""COMPUTED_VALUE"""),"Récupérer") -> Récupérer | L57: =IFERROR(__xludf.DUMMYFUNCTION("""COMPUTED_VALUE"""),1.0) -> 1
K58: =IFERROR(__xludf.DUMMYFUNCTION("""COMPUTED_VALUE"""),"Répondre") -> Répondre | L58: =IFERROR(__xludf.DUMMYFUNCTION("""COMPUTED_VALUE"""),1.0) -> 1
K59: =IFERROR(__xludf.DUMMYFUNCTION("""COMPUTED_VALUE"""),"Évaluer") -> Évaluer | L59: =IFERROR(__xludf.DUMMYFUNCTION("""COMPUTED_VALUE"""),1.0) -> 1
J60: =IFERROR(__xludf.DUMMYFUNCTION("""COMPUTED_VALUE"""),"III. TESTS DE RÉSILIENCE OPÉRATIONNELLE NUMÉRIQUE") -> III. TESTS DE RÉSILIENCE OPÉRATIONNELLE NUMÉRIQUE | K60: =IFERROR(__xludf.DUMMYFUNCTION("""COMPUTED_VALUE"""),"Améliorer") -> Améliorer | L60: =IFERROR(__xludf.DUMMYFUNCTION("""COMPUTED_VALUE"""),1.0) -> 1 | M60: =SUM(L60:L61) -> 3
K61: =IFERROR(__xludf.DUMMYFUNCTION("""COMPUTED_VALUE"""),"Évaluer") -> Évaluer | L61: =IFERROR(__xludf.DUMMYFUNCTION("""COMPUTED_VALUE"""),2.0) -> 2
J62: =IFERROR(__xludf.DUMMYFUNCTION("""COMPUTED_VALUE"""),"IV. GESTION DES RISQUES LIÉS AUX PRESTATAIRES TIERS DE SERVICES TIC") -> IV. GESTION DES RISQUES LIÉS AUX PRESTATAIRES TIERS DE SERVICES TIC | K62: =IFERROR(__xludf.DUMMYFUNCTION("""COMPUTED_VALUE"""),"Contrôler") -> Contrôler | L62: =IFERROR(__xludf.DUMMYFUNCTION("""COMPUTED_VALUE"""),1.0) -> 1 | M62: =SUM(L62:L67) -> 6
K63: =IFERROR(__xludf.DUMMYFUNCTION("""COMPUTED_VALUE"""),"Gouverner") -> Gouverner | L63: =IFERROR(__xludf.DUMMYFUNCTION("""COMPUTED_VALUE"""),1.0) -> 1
K64: =IFERROR(__xludf.DUMMYFUNCTION("""COMPUTED_VALUE"""),"Gouverner / Évaluer") -> Gouverner / Évaluer | L64: =IFERROR(__xludf.DUMMYFUNCTION("""COMPUTED_VALUE"""),1.0) -> 1
K65: =IFERROR(__xludf.DUMMYFUNCTION("""COMPUTED_VALUE"""),"Identifier") -> Identifier | L65: =IFERROR(__xludf.DUMMYFUNCTION("""COMPUTED_VALUE"""),1.0) -> 1
K66: =IFERROR(__xludf.DUMMYFUNCTION("""COMPUTED_VALUE"""),"Récupérer") -> Récupérer | L66: =IFERROR(__xludf.DUMMYFUNCTION("""COMPUTED_VALUE"""),1.0) -> 1
K67: =IFERROR(__xludf.DUMMYFUNCTION("""COMPUTED_VALUE"""),"Évaluer") -> Évaluer | L67: =IFERROR(__xludf.DUMMYFUNCTION("""COMPUTED_VALUE"""),1.0) -> 1
J68: =IFERROR(__xludf.DUMMYFUNCTION("""COMPUTED_VALUE"""),"V. PARTAGE D'INFORMATIONS") -> V. PARTAGE D'INFORMATIONS | K68: =IFERROR(__xludf.DUMMYFUNCTION("""COMPUTED_VALUE"""),"Protéger / Répondre") -> Protéger / Répondre | L68: =IFERROR(__xludf.DUMMYFUNCTION("""COMPUTED_VALUE"""),1.0) -> 1 | M68: =SUM(L68) -> 1
J69: =IFERROR(__xludf.DUMMYFUNCTION("""COMPUTED_VALUE"""),"VI. APPRENTISSAGE ET EVOLUTION") -> VI. APPRENTISSAGE ET EVOLUTION | K69: =IFERROR(__xludf.DUMMYFUNCTION("""COMPUTED_VALUE"""),"Améliorer") -> Améliorer | L69: =IFERROR(__xludf.DUMMYFUNCTION("""COMPUTED_VALUE"""),2.0) -> 2 | M69: =SUM(L69:L71) -> 4
K70: =IFERROR(__xludf.DUMMYFUNCTION("""COMPUTED_VALUE"""),"Améliorer / Détecter") -> Améliorer / Détecter | L70: =IFERROR(__xludf.DUMMYFUNCTION("""COMPUTED_VALUE"""),1.0) -> 1
K71: =IFERROR(__xludf.DUMMYFUNCTION("""COMPUTED_VALUE"""),"Sensibiliser") -> Sensibiliser | L71: =IFERROR(__xludf.DUMMYFUNCTION("""COMPUTED_VALUE"""),1.0) -> 1
J72: Total Général | L72: =SUM(M48:M71) -> 32

Sheet NIS2
A2: Domaine | B2: ID | C2: Exigence / contrôle | D2: Description | E2: Preuve attendue | F2: Niveau de maturité | G2: Description du niveau | H2: Commentaire / recommandation | J2: Domaine (Tri)
A3: Gouvernance | B3: 1 | C3: Identifier l’assujettissement NIS2 (secteur, taille, services) | D3: Déterminer si l’entité est concernée et définir le périmètre (entités, sites, services). | E3: Analyse d’éligibilité NIS2 , cartographie des services critiques , justification écrite datée/validée. | F3: 5 - Optimal | G3: {=IF(F3="", "", IFERROR(INDEX('Echelle de maturité'!$B$2:$B$7, MATCH(F3, 'Echelle de maturité'!$C$2:$C$7, 0)), ""))} -> Des objectifs de réduction des risques cyber intégrés à la stratégie de l'organisation. Des moyens humains, budgétaires conséquents, un plan d'action cyber exhaustif, adapté aux menaces stratégiques. | H3: =IF($F3="1 - Insuffisant", "Réaliser une analyse d'assujettissement NIS2 en identifiant les secteurs concernés, les entités, les sites et les services critiques. Formaliser les résultats dans un document validé par la direction.", IF($F3="2 - Émergent", "Structurer et documenter l'analyse d'assujettissement. Définir précisément le périmètre concerné, identifier les services critiques et formaliser les critères de qualification retenus.", IF($F3="3 - Intermédiaire", "Compléter la cartographie des services critiques, consolider les justifications d'assujettissement et mettre en place un processus formel de validation et de revue périodique.", IF($F3="4 - Confirmé", "Maintenir la revue régulière de l'analyse d'assujettissement, mettre à jour le périmètre lors des évolutions de l'organisation et conserver les preuves de validation et de suivi.", IF($F3="5 - Optimal", "Assurer une amélioration continue du processus d'assujettissement NIS2, intégrer les évolutions réglementaires et organisationnelles dans les mécanismes de gouvernance et renforcer les indicateurs de pilotage associés.", IF($F3="Non applicable", "Non applicable.", "")))))) -> Assurer une amélioration continue du processus d'assujettissement NIS2, intégrer les évolutions réglementaires et organisationnelles dans les mécanismes de gouvernance et renforcer les indicateurs de pilotage associés. | J3: =IFERROR(__xludf.DUMMYFUNCTION("ARRAYFORMULA(LET(filled, SCAN("""", A3:A35, LAMBDA(acc, v, IF(v="""", acc, v))), IF(filled="""","""", TEXT(MATCH(filled, UNIQUE(FILTER(A3:A35, A3:A35<>"""")), 0), ""00"") & "" - "" & filled)))"),"01 - Gouvernance") -> 01 - Gouvernance
B4: 2 | C4: Rôles et responsabilités cybersécurité (RSSI, IT, métiers) | D4: Définir qui fait quoi : pilotage, exploitation, validation, escalade. | E4: Organigramme , fiches de poste/lettres de mission , matrice RACI cybersécurité | F4: 3 - Intermédiaire | G4: {=IF(F4="", "", IFERROR(INDEX('Echelle de maturité'!$B$2:$B$7, MATCH(F4, 'Echelle de maturité'!$C$2:$C$7, 0)), ""))} -> Une conscience partagée des risques cyber pour l'organisation et la volonté de formaliser un plan d'action cyber complet tout en ajustant les moyens en conséquence. | H4: =IF($F4="1 - Insuffisant", "Désigner un responsable cybersécurité (RSSI ou équivalent), identifier les principales responsabilités de sécurité et formaliser les missions essentielles dans un document validé par la direction.", IF($F4="2 - Émergent", "Formaliser les rôles existants, définir les responsabilités clés en matière de cybersécurité, établir un organigramme fonctionnel et documenter les premiers éléments d'une matrice RACI.", IF($F4="3 - Intermédiaire", "Compléter les fiches de poste et la matrice RACI, préciser les responsabilités de pilotage, d'exploitation, de contrôle et d'escalade, puis assurer leur diffusion et leur compréhension par les parties prenantes.", IF($F4="4 - Confirmé", "Maintenir à jour les rôles, responsabilités et la matrice RACI, réaliser des revues périodiques et adapter la gouvernance cybersécurité aux évolutions de l'organisation, du système d'information et des prestataires.", IF($F4="5 - Optimal", "Renforcer l'amélioration continue de la gouvernance cybersécurité en évaluant régulièrement l'efficacité des responsabilités attribuées, en intégrant les retours d'expérience et en alignant les rôles sur les objectifs stratégiques de gestion des risques.", IF($F4="Non applicable", "Non applicable.", "")))))) -> Compléter les fiches de poste et la matrice RACI, préciser les responsabilités de pilotage, d'exploitation, de contrôle et d'escalade, puis assurer leur diffusion et leur compréhension par les parties prenantes. | J4: =IFERROR(__xludf.DUMMYFUNCTION("""COMPUTED_VALUE"""),"01 - Gouvernance") -> 01 - Gouvernance
B5: 3 | C5: Supervision par la direction (pilotage, arbitrages) | D5: La direction suit les risques cyber, valide les priorités et arbitre les budgets. | E5: PV de comité (mensuel/trimestriel) , décisions , budget , KPI/KRI. | F5: 5 - Optimal | G5: {=IF(F5="", "", IFERROR(INDEX('Echelle de maturité'!$B$2:$B$7, MATCH(F5, 'Echelle de maturité'!$C$2:$C$7, 0)), ""))} -> Des objectifs de réduction des risques cyber intégrés à la stratégie de l'organisation. Des moyens humains, budgétaires conséquents, un plan d'action cyber exhaustif, adapté aux menaces stratégiques. | H5: =IF($F5="1 - Insuffisant", "Mettre en place une gouvernance cybersécurité impliquant la direction, définir une fréquence de pilotage, formaliser les comptes rendus de réunion et initier le suivi des actions prioritaires ainsi que des ressources nécessaires.", IF($F5="2 - Émergent", "Formaliser les instances de gouvernance, définir les rôles des participants, documenter les décisions prises et mettre en place un premier tableau de bord de suivi des risques et actions cybersécurité.", IF($F5="3 - Intermédiaire", "Renforcer le pilotage en définissant des indicateurs de performance et de risque pertinents, en assurant le suivi systématique des plans d'actions et en intégrant la planification budgétaire aux processus de gouvernance.", IF($F5="4 - Confirmé", "Maintenir et améliorer le dispositif de pilotage en analysant les tendances des indicateurs, en intégrant les résultats des audits, incidents et exercices, et en ajustant régulièrement les priorités de sécurité.", IF($F5="5 - Optimal", "Développer une démarche d'amélioration continue fondée sur les indicateurs stratégiques de risque, l'anticipation des menaces émergentes et l'alignement permanent des investissements cybersécurité avec les objectifs de l'organisation.", IF($F5="Non applicable", "Non applicable.", "")))))) -> Développer une démarche d'amélioration continue fondée sur les indicateurs stratégiques de risque, l'anticipation des menaces émergentes et l'alignement permanent des investissements cybersécurité avec les objectifs de l'organisation. | J5: =IFERROR(__xludf.DUMMYFUNCTION("""COMPUTED_VALUE"""),"01 - Gouvernance") -> 01 - Gouvernance
B6: 4 | C6: PSSI + politiques de sécurité maintenues à jour | D6: Avoir des règles écrites (accès, mots de passe, sauvegardes, incidents…) et les mettre à jour. | E6: PSSI , politiques datées , preuve d’approbation direction , preuve de diffusion. | F6: 3 - Intermédiaire | G6: {=IF(F6="", "", IFERROR(INDEX('Echelle de maturité'!$B$2:$B$7, MATCH(F6, 'Echelle de maturité'!$C$2:$C$7, 0)), ""))} -> Une conscience partagée des risques cyber pour l'organisation et la volonté de formaliser un plan d'action cyber complet tout en ajustant les moyens en conséquence. | H6: =IF($F6="1 - Insuffisant", "Rédiger une PSSI ainsi que les politiques et procédures cybersécurité essentielles (gestion des accès, mots de passe, sauvegardes, gestion des incidents, fournisseurs, cloud), puis les faire approuver par la direction et diffuser aux parties prenantes con"&"cernées.", IF($F6="2 - Émergent", "Formaliser et structurer le corpus documentaire cybersécurité, définir les responsabilités de gestion documentaire, dater les documents et obtenir une validation formelle de la direction.", IF($F6="3 - Intermédiaire", "Compléter le corpus documentaire afin de couvrir l'ensemble des domaines cybersécurité pertinents, organiser sa diffusion aux collaborateurs concernés et mettre en place un processus de revue périodique documenté.", IF($F6="4 - Confirmé", "Maintenir les politiques et procédures à jour, réaliser des revues régulières, vérifier leur application opérationnelle et assurer la traçabilité des validations et mises à jour.", IF($F6="5 - Optimal", "Mettre en œuvre une démarche d'amélioration continue du référentiel documentaire en l'alignant sur l'évolution des risques, des exigences réglementaires et des objectifs stratégiques de l'organisation, tout en mesurant son niveau d'appropriation et son ef"&"ficacité.", IF($F6="Non applicable", "Non applicable.", "")))))) -> Compléter le corpus documentaire afin de couvrir l'ensemble des domaines cybersécurité pertinents, organiser sa diffusion aux collaborateurs concernés et mettre en place un processus de revue périodique documenté. | J6: =IFERROR(__xludf.DUMMYFUNCTION("""COMPUTED_VALUE"""),"01 - Gouvernance") -> 01 - Gouvernance
A7: Gestion des risques | B7: 5 | C7: Méthode de gestion des risques cyber formalisée | D7: Identifier, évaluer et traiter les risques cyber sur le périmètre NIS2 (SI, services, processus critiques). | E7: Méthodologie (ISO 27005 / EBIOS / ....), registre des risques, plan de traitement, revues périodiques, validation. | F7: Non applicable | G7: {=IF(F7="", "", IFERROR(INDEX('Echelle de maturité'!$B$2:$B$7, MATCH(F7, 'Echelle de maturité'!$C$2:$C$7, 0)), ""))} -> Le critère ou l'exigence évalué n'est pas pertinent au regard des activités, du périmètre technique ou du cadre réglementaire de l'organisation. | H7: =IF($F7="1 - Insuffisant", "Définir une méthodologie de gestion des risques cybersécurité (ISO 27005, EBIOS RM ou équivalent), identifier les principaux risques cyber de l'organisation et mettre en place un registre des risques ainsi qu'un plan de traitement initial.", IF($F7="2 - Émergent", "Formaliser la démarche de gestion des risques, documenter les critères d'évaluation (impact, vraisemblance, criticité), consolider le registre des risques et attribuer les responsabilités de traitement.", IF($F7="3 - Intermédiaire", "Étendre l'analyse des risques à l'ensemble des activités, processus et actifs critiques, homogénéiser les méthodes d'évaluation et assurer le suivi régulier des plans de traitement et des risques résiduels.", IF($F7="4 - Confirmé", "Maintenir la revue périodique des risques, intégrer les résultats des audits, incidents et évolutions du contexte de menace, et suivre des indicateurs permettant de piloter l'efficacité du traitement des risques.", IF($F7="5 - Optimal", "Renforcer l'amélioration continue du dispositif de gestion des risques en intégrant les risques cyber à la gouvernance globale de l'organisation, en anticipant les menaces émergentes et en utilisant les résultats pour orienter les décisions stratégiques e"&"t les investissements de sécurité.", IF($F7="Non applicable", "Non applicable.", "")))))) -> Non applicable. | J7: =IFERROR(__xludf.DUMMYFUNCTION("""COMPUTED_VALUE"""),"02 - Gestion des risques") -> 02 - Gestion des risques
B8: 6 | C8: Inventaire des actifs (SI, logiciels, services) et propriétaires | D8: Maintenir un inventaire à jour des actifs (postes, serveurs, applis, services cloud) et des propriétaires. | E8: Inventaire/CMDB, liste logiciels, cartographie, propriétaires d’actifs, fréquence de mise à jour. | F8: 4 - Confirmé | G8: {=IF(F8="", "", IFERROR(INDEX('Echelle de maturité'!$B$2:$B$7, MATCH(F8, 'Echelle de maturité'!$C$2:$C$7, 0)), ""))} -> Une cartographie précise de ses risques cyber pour l'organisation, un plan d'action cyber approfondi et des moyens humains et budgétaires dédiés. | H8: =IF($F8="1 - Insuffisant", "Mettre en place un inventaire centralisé des actifs (matériels, logiciels, services cloud et actifs critiques), identifier leurs propriétaires et définir un processus de mise à jour avec responsabilités clairement attribuées.", IF($F8="2 - Émergent", "Formaliser la gestion de l'inventaire en centralisant les informations dans un outil dédié ou un référentiel unique, compléter les informations essentielles sur les actifs et planifier des mises à jour régulières.", IF($F8="3 - Intermédiaire", "Étendre l'inventaire à l'ensemble des actifs du périmètre, y compris les services cloud, applications métier et fournisseurs critiques, et améliorer la fiabilité des données grâce à des processus de contrôle et de mise à jour structurés.", IF($F8="4 - Confirmé", "Maintenir la qualité et l'exhaustivité de l'inventaire par des revues périodiques, des contrôles réguliers et son intégration avec les processus de gestion des vulnérabilités, des correctifs et des changements.", IF($F8="5 - Optimal", "Optimiser la gestion des actifs en automatisant la découverte et la mise à jour des inventaires, en suivant des indicateurs de qualité et de couverture, et en intégrant l'inventaire aux processus stratégiques de gestion des risques et de pilotage de la cy"&"bersécurité.", IF($F8="Non applicable", "Non applicable.", "")))))) -> Maintenir la qualité et l'exhaustivité de l'inventaire par des revues périodiques, des contrôles réguliers et son intégration avec les processus de gestion des vulnérabilités, des correctifs et des changements. | J8: =IFERROR(__xludf.DUMMYFUNCTION("""COMPUTED_VALUE"""),"02 - Gestion des risques") -> 02 - Gestion des risques
B9: 7 | C9: Classification des données et règles de protection | D9: Identifier les données sensibles et appliquer des règles de protection (accès, stockage, partage, chiffrement). | E9: Politique de classification, registre de données sensibles, règles de stockage/partage, exemples d’étiquetage, contrôles. | F9: 5 - Optimal | G9: {=IF(F9="", "", IFERROR(INDEX('Echelle de maturité'!$B$2:$B$7, MATCH(F9, 'Echelle de maturité'!$C$2:$C$7, 0)), ""))} -> Des objectifs de réduction des risques cyber intégrés à la stratégie de l'organisation. Des moyens humains, budgétaires conséquents, un plan d'action cyber exhaustif, adapté aux menaces stratégiques. | H9: =IF($F9="1 - Insuffisant", "Définir une politique de classification des données, identifier les informations sensibles et formaliser les règles de protection, de stockage, de partage et d'accès.", IF($F9="2 - Émergent", "Initier la classification des données les plus critiques, sensibiliser les utilisateurs et documenter les premières règles de gestion et de protection des informations.", IF($F9="3 - Intermédiaire", "Étendre la classification à l'ensemble des données du périmètre, mettre en œuvre des mesures de protection adaptées et assurer leur application de manière cohérente.", IF($F9="4 - Confirmé", "Contrôler régulièrement l'application de la classification, renforcer les mesures de protection et intégrer la gestion des données dans les processus de gestion des risques.", IF($F9="5 - Optimal", "Optimiser la gouvernance des données par l'automatisation de la classification, le suivi d'indicateurs de conformité et l'amélioration continue des mesures de protection en fonction des risques et des évolutions réglementaires.", IF($F9="Non applicable", "Non applicable.", "")))))) -> Optimiser la gouvernance des données par l'automatisation de la classification, le suivi d'indicateurs de conformité et l'amélioration continue des mesures de protection en fonction des risques et des évolutions réglementaires. | J9: =IFERROR(__xludf.DUMMYFUNCTION("""COMPUTED_VALUE"""),"02 - Gestion des risques") -> 02 - Gestion des risques
B10: 8 | C10: Gestion des vulnérabilités (détection, priorisation, correction) | D10: Détecter les vulnérabilités, prioriser selon le risque et corriger dans des délais définis (SLA). | E10: Outils de scan, rapports, tickets, SLA, exceptions approuvées, suivi jusqu’à clôture. | F10: 5 - Optimal | G10: {=IF(F10="", "", IFERROR(INDEX('Echelle de maturité'!$B$2:$B$7, MATCH(F10, 'Echelle de maturité'!$C$2:$C$7, 0)), ""))} -> Des objectifs de réduction des risques cyber intégrés à la stratégie de l'organisation. Des moyens humains, budgétaires conséquents, un plan d'action cyber exhaustif, adapté aux menaces stratégiques. | H10: =IF($F10="1 - Insuffisant", "Mettre en place un processus de gestion des vulnérabilités, réaliser des scans réguliers des actifs exposés, identifier les vulnérabilités critiques et définir les responsabilités de traitement.", IF($F10="2 - Émergent", "Formaliser le processus de gestion des vulnérabilités en définissant les méthodes de détection, les critères de priorisation, le workflow de correction et les responsabilités associées.", IF($F10="3 - Intermédiaire", "Étendre la couverture des analyses à l'ensemble du périmètre concerné (serveurs, postes de travail, équipements réseau, services cloud et applications), formaliser les délais de traitement selon la criticité et assurer le suivi des actions correctives.", IF($F10="4 - Confirmé", "Maintenir une surveillance régulière des vulnérabilités, suivre les corrections au travers d'indicateurs de performance, gérer formellement les exceptions et intégrer les résultats aux processus de gestion des risques et de gestion des changements.", IF($F10="5 - Optimal", "Optimiser la gestion des vulnérabilités par l'automatisation des détections et des remédiations lorsque cela est pertinent, piloter l'activité à l'aide d'indicateurs avancés et adapter en continu les priorités en fonction de l'évolution des menaces et de "&"l'exposition aux risques.", IF($F10="Non applicable", "Non applicable.", "")))))) -> Optimiser la gestion des vulnérabilités par l'automatisation des détections et des remédiations lorsque cela est pertinent, piloter l'activité à l'aide d'indicateurs avancés et adapter en continu les priorités en fonction de l'évolution des menaces et de l'exposition aux risques. | J10: =IFERROR(__xludf.DUMMYFUNCTION("""COMPUTED_VALUE"""),"02 - Gestion des risques") -> 02 - Gestion des risques
B11: 9 | C11: Patch management (OS, applications, firmware) | D11: Définir, appliquer et suivre les mises à jour de sécurité sur le périmètre NIS2 (postes, serveurs, équipements réseau, applications, cloud). | E11: Politique de patch management, inventaire des actifs couverts, calendrier/plan de déploiement, tableaux de conformité, rapports de déploiement, gestion des exceptions (approbation + durée), preuves de tests si nécessaire. | F11: 3 - Intermédiaire | G11: {=IF(F11="", "", IFERROR(INDEX('Echelle de maturité'!$B$2:$B$7, MATCH(F11, 'Echelle de maturité'!$C$2:$C$7, 0)), ""))} -> Une conscience partagée des risques cyber pour l'organisation et la volonté de formaliser un plan d'action cyber complet tout en ajustant les moyens en conséquence. | H11: =IF($F11="1 - Insuffisant", "Définir un processus de gestion des correctifs de sécurité, identifier les actifs concernés, attribuer les responsabilités de déploiement et mettre en place un suivi minimal des mises à jour de sécurité.", IF($F11="2 - Émergent", "Formaliser la politique de gestion des correctifs en définissant les fréquences de mise à jour, les critères de priorisation, les délais de traitement attendus et les rôles des parties prenantes.", IF($F11="3 - Intermédiaire", "Étendre la gestion des correctifs à l'ensemble des actifs du périmètre (postes de travail, serveurs, équipements réseau, applications et services cloud), formaliser les délais de traitement selon la criticité et assurer le suivi systématique des déploieme"&"nts.", IF($F11="4 - Confirmé", "Maintenir la conformité du parc en réalisant un suivi régulier des correctifs déployés, gérer formellement les exceptions, produire des indicateurs de pilotage et intégrer le processus aux activités de gestion des vulnérabilités et des changements.", IF($F11="5 - Optimal", "Optimiser la gestion des correctifs par l'automatisation du déploiement et du contrôle de conformité, piloter l'activité à l'aide d'indicateurs avancés et adapter en continu les priorités de remédiation en fonction des menaces, des vulnérabilités exploité"&"es et de l'exposition aux risques.", IF($F11="Non applicable", "Non applicable.", "")))))) -> Étendre la gestion des correctifs à l'ensemble des actifs du périmètre (postes de travail, serveurs, équipements réseau, applications et services cloud), formaliser les délais de traitement selon la criticité et assurer le suivi systématique des déploiements. | J11: =IFERROR(__xludf.DUMMYFUNCTION("""COMPUTED_VALUE"""),"02 - Gestion des risques") -> 02 - Gestion des risques
A12: Contrôle d’accès / IAM | B12: 10 | C12: Gestion du cycle de vie des comptes (arrivée, départ, mobilité) | D12: Créer/modifier/supprimer les comptes de façon contrôlée et rapide, surtout lors des départs et changements de poste. | E12: Procédure IAM, workflow/tickets RH-IT, preuves de suppression à la sortie, revues, journal des comptes. | F12: 5 - Optimal | G12: {=IF(F12="", "", IFERROR(INDEX('Echelle de maturité'!$B$2:$B$7, MATCH(F12, 'Echelle de maturité'!$C$2:$C$7, 0)), ""))} -> Des objectifs de réduction des risques cyber intégrés à la stratégie de l'organisation. Des moyens humains, budgétaires conséquents, un plan d'action cyber exhaustif, adapté aux menaces stratégiques. | H12: =IF($F12="1 - Insuffisant", "Mettre en place un processus de gestion des arrivées, départs et changements de fonction, définir les responsabilités associées et garantir la création, la modification et la suppression des comptes utilisateurs de manière contrôlée.", IF($F12="2 - Émergent", "Formaliser les procédures de gestion des identités et des accès, documenter les étapes du processus, définir les délais de traitement et mettre en place un mécanisme de traçabilité des actions réalisées.", IF($F12="3 - Intermédiaire", "Étendre et homogénéiser le processus sur l'ensemble du périmètre concerné, renforcer les contrôles sur les comptes inactifs, partagés ou orphelins, et assurer le suivi systématique des demandes et des exceptions.", IF($F12="4 - Confirmé", "Maintenir l'efficacité du processus par des revues régulières des comptes et habilitations, suivre des indicateurs de performance, gérer formellement les exceptions et intégrer le processus aux activités RH et de gestion des accès.", IF($F12="5 - Optimal", "Optimiser la gestion des identités et des accès par l'automatisation des workflows, l'intégration entre les systèmes RH et IT, le pilotage par des indicateurs avancés et l'amélioration continue des mécanismes de contrôle et de traçabilité.", IF($F12="Non applicable", "Non applicable.", "")))))) -> Optimiser la gestion des identités et des accès par l'automatisation des workflows, l'intégration entre les systèmes RH et IT, le pilotage par des indicateurs avancés et l'amélioration continue des mécanismes de contrôle et de traçabilité. | J12: =IFERROR(__xludf.DUMMYFUNCTION("""COMPUTED_VALUE"""),"03 - Contrôle d’accès / IAM") -> 03 - Contrôle d’accès / IAM
B13: 11 | C13: MFA obligatoire pour accès distants et comptes sensibles | D13: Activer l’authentification forte (MFA) pour VPN, messagerie, cloud, admin et accès critiques. | E13: Paramétrage IAM/SSO, taux de couverture MFA, exceptions approuvées, preuves de configuration. | F13: 5 - Optimal | G13: {=IF(F13="", "", IFERROR(INDEX('Echelle de maturité'!$B$2:$B$7, MATCH(F13, 'Echelle de maturité'!$C$2:$C$7, 0)), ""))} -> Des objectifs de réduction des risques cyber intégrés à la stratégie de l'organisation. Des moyens humains, budgétaires conséquents, un plan d'action cyber exhaustif, adapté aux menaces stratégiques. | H13: =IF($F13="1 - Insuffisant", "Déployer l'authentification multifacteur (MFA) sur les accès les plus sensibles, notamment les comptes administrateurs, les accès distants, les services cloud et les systèmes critiques de l'organisation.", IF($F13="2 - Émergent", "Formaliser une politique d'authentification multifacteur définissant les populations concernées, les systèmes couverts, les méthodes autorisées et les modalités de déploiement et de gestion des exceptions.", IF($F13="3 - Intermédiaire", "Étendre progressivement l'authentification multifacteur à l'ensemble des applications et services critiques identifiés, assurer le suivi de la couverture et encadrer formellement les dérogations.", IF($F13="4 - Confirmé", "Maintenir un niveau élevé de couverture MFA, réaliser des revues régulières des exceptions, suivre des indicateurs de déploiement et contrôler l'efficacité des mécanismes d'authentification mis en œuvre.", IF($F13="5 - Optimal", "Optimiser les mécanismes d'authentification en privilégiant les méthodes les plus robustes adaptées aux risques, en surveillant les tentatives de contournement et en améliorant continuellement la couverture et la résilience du dispositif d'authentificatio"&"n.", IF($F13="Non applicable", "Non applicable.", "")))))) -> Optimiser les mécanismes d'authentification en privilégiant les méthodes les plus robustes adaptées aux risques, en surveillant les tentatives de contournement et en améliorant continuellement la couverture et la résilience du dispositif d'authentification. | J13: =IFERROR(__xludf.DUMMYFUNCTION("""COMPUTED_VALUE"""),"03 - Contrôle d’accès / IAM") -> 03 - Contrôle d’accès / IAM
B14: 12 | C14: Gestion des comptes à privilèges (moindre privilège / PAM) | D14: Limiter, contrôler et tracer l’usage des droits admin (comptes nominatif, séparation des rôles, élévation contrôlée). | E14: Inventaire comptes admin, preuves de séparation des comptes, coffre/PAM/bastion, logs d’admin, revues. | F14: 4 - Confirmé | G14: {=IF(F14="", "", IFERROR(INDEX('Echelle de maturité'!$B$2:$B$7, MATCH(F14, 'Echelle de maturité'!$C$2:$C$7, 0)), ""))} -> Une cartographie précise de ses risques cyber pour l'organisation, un plan d'action cyber approfondi et des moyens humains et budgétaires dédiés. | H14: =IF($F14="1 - Insuffisant", "Réaliser l'inventaire des comptes à privilèges, supprimer les comptes partagés lorsque possible, appliquer le principe du moindre privilège et mettre en place une journalisation des actions administrateurs.", IF($F14="2 - Émergent", "Formaliser la gestion des comptes à privilèges en définissant une politique de séparation des comptes, en documentant l'inventaire des accès administrateurs et en mettant en place une traçabilité des actions sensibles.", IF($F14="3 - Intermédiaire", "Structurer la gestion des accès à privilèges en généralisant la séparation des comptes, en encadrant les accès temporaires et en renforçant la traçabilité des actions réalisées sur les systèmes critiques.", IF($F14="4 - Confirmé", "Maintenir un contrôle régulier des comptes à privilèges, organiser des revues périodiques des droits, améliorer la supervision des actions sensibles et suivre des indicateurs de gestion des accès administrateurs.", IF($F14="5 - Optimal", "Optimiser la gestion des accès à privilèges par la réduction des privilèges permanents, le renforcement des contrôles d'accès dynamiques et l'amélioration continue de la surveillance des activités administrateurs en fonction des risques.", IF($F14="Non applicable", "Non applicable.", "")))))) -> Maintenir un contrôle régulier des comptes à privilèges, organiser des revues périodiques des droits, améliorer la supervision des actions sensibles et suivre des indicateurs de gestion des accès administrateurs. | J14: =IFERROR(__xludf.DUMMYFUNCTION("""COMPUTED_VALUE"""),"03 - Contrôle d’accès / IAM") -> 03 - Contrôle d’accès / IAM
B15: 13 | C15: Revue périodique des droits d’accès (recertification) | D15: Vérifier régulièrement que chaque utilisateur a uniquement les droits nécessaires (suppression des droits inutiles). | E15: Campagnes de recertification, rapports de revue, liste des écarts, actions de correction, périodicité. | F15: 5 - Optimal | G15: {=IF(F15="", "", IFERROR(INDEX('Echelle de maturité'!$B$2:$B$7, MATCH(F15, 'Echelle de maturité'!$C$2:$C$7, 0)), ""))} -> Des objectifs de réduction des risques cyber intégrés à la stratégie de l'organisation. Des moyens humains, budgétaires conséquents, un plan d'action cyber exhaustif, adapté aux menaces stratégiques. | H15: =IF($F15="1 - Insuffisant", "Mettre en place un processus de revue périodique des habilitations (recertification), en priorisant les accès sensibles et administrateurs, avec validation par les responsables métiers et techniques.", IF($F15="2 - Émergent", "Formaliser le processus de recertification des accès en définissant les fréquences de revue, les rôles des validateurs et les modalités de contrôle des droits attribués.", IF($F15="3 - Intermédiaire", "Étendre les campagnes de recertification à l'ensemble des applications et rôles critiques, structurer le suivi des écarts identifiés et assurer la correction des droits inadaptés jusqu'à clôture.", IF($F15="4 - Confirmé", "Maintenir des campagnes de recertification régulières et structurées, suivre les actions correctives associées, et piloter le dispositif à l'aide d'indicateurs de performance et de conformité.", IF($F15="5 - Optimal", "Optimiser la recertification des habilitations par l'automatisation des campagnes, l'amélioration continue du ciblage des accès à risque et l'intégration des résultats dans la gouvernance globale des identités et des accès.", IF($F15="Non applicable", "Non applicable.", "")))))) -> Optimiser la recertification des habilitations par l'automatisation des campagnes, l'amélioration continue du ciblage des accès à risque et l'intégration des résultats dans la gouvernance globale des identités et des accès. | J15: =IFERROR(__xludf.DUMMYFUNCTION("""COMPUTED_VALUE"""),"03 - Contrôle d’accès / IAM") -> 03 - Contrôle d’accès / IAM
A16: Incidents & notification | B16: 14 | C16: Procédure de gestion des incidents cyber (détection, escalade, réponse, rétablissement) | D16: Définir et appliquer une procédure pour traiter un incident : rôles, escalade, communication, actions de réponse et retour d’expérience. | E16: Procédure / playbooks, chaîne d’escalade, RACI incident, astreinte, modèle de fiche incident, registre des incidents. | F16: 5 - Optimal | G16: {=IF(F16="", "", IFERROR(INDEX('Echelle de maturité'!$B$2:$B$7, MATCH(F16, 'Echelle de maturité'!$C$2:$C$7, 0)), ""))} -> Des objectifs de réduction des risques cyber intégrés à la stratégie de l'organisation. Des moyens humains, budgétaires conséquents, un plan d'action cyber exhaustif, adapté aux menaces stratégiques. | H16: =IF($F16="1 - Insuffisant", "Mettre en place une procédure de gestion des incidents de sécurité définissant les rôles, les responsabilités et les modalités d'escalade, et établir un registre centralisé des incidents ainsi que des scénarios de réponse de base.", IF($F16="2 - Émergent", "Formaliser le processus de gestion des incidents en décrivant les étapes clés (détection, qualification, escalade, réponse, rétablissement et retour d'expérience) et en définissant la chaîne d'alerte et les contacts d'astreinte.", IF($F16="3 - Intermédiaire", "Compléter et structurer les procédures de réponse aux incidents, tester les scénarios de réponse, formaliser les mécanismes d'escalade et assurer l'enregistrement systématique ainsi que le traitement des incidents jusqu'à leur clôture.", IF($F16="4 - Confirmé", "Maintenir et améliorer le dispositif de gestion des incidents en intégrant les retours d'expérience, en mettant à jour régulièrement les procédures et en suivant des indicateurs de performance tels que les délais de détection et de résolution.", IF($F16="5 - Optimal", "Optimiser la gestion des incidents de sécurité par une amélioration continue basée sur les retours d'expérience, le renforcement de la détection et de la réponse et l'intégration des enseignements dans la stratégie globale de résilience de l'organisation.", IF($F16="Non applicable", "Non applicable.", "")))))) -> Optimiser la gestion des incidents de sécurité par une amélioration continue basée sur les retours d'expérience, le renforcement de la détection et de la réponse et l'intégration des enseignements dans la stratégie globale de résilience de l'organisation. | J16: =IFERROR(__xludf.DUMMYFUNCTION("""COMPUTED_VALUE"""),"04 - Incidents & notification") -> 04 - Incidents & notification
B17: 15 | C17: Détection et réponse aux incidents (supervision / SOC) | D17: Détecter rapidement les incidents, qualifier les alertes et répondre avec un suivi (MTTD/MTTR). | E17: Organisation SOC interne/externe, périmètre couvert, tickets, rapports d’investigation, KPI MTTD/MTTR, preuves de traitement des alertes. | F17: 5 - Optimal | G17: {=IF(F17="", "", IFERROR(INDEX('Echelle de maturité'!$B$2:$B$7, MATCH(F17, 'Echelle de maturité'!$C$2:$C$7, 0)), ""))} -> Des objectifs de réduction des risques cyber intégrés à la stratégie de l'organisation. Des moyens humains, budgétaires conséquents, un plan d'action cyber exhaustif, adapté aux menaces stratégiques. | H17: =IF($F17="1 - Insuffisant", "Mettre en place une capacité de supervision de sécurité incluant la centralisation des journaux, la génération d'alertes de sécurité et un processus initial de traitement des événements avec rôles et responsabilités définis.", IF($F17="2 - Émergent", "Formaliser le dispositif de supervision en structurant le traitement des alertes, en définissant un processus de qualification et de réponse et en clarifiant les responsabilités des équipes impliquées dans la surveillance.", IF($F17="3 - Intermédiaire", "Étendre la supervision de sécurité à l'ensemble du périmètre critique (systèmes, réseaux, cloud et applications), formaliser les procédures de traitement des alertes et suivre les événements de sécurité de manière structurée.", IF($F17="4 - Confirmé", "Maintenir et améliorer la supervision de sécurité en renforçant la qualité de détection, en intégrant les retours d'incidents et en pilotant l'activité à l'aide d'indicateurs de performance tels que les délais de détection et de réponse.", IF($F17="5 - Optimal", "Optimiser la supervision de sécurité par l'amélioration continue des capacités de détection, l'enrichissement des sources de données et l'adaptation dynamique aux menaces émergentes afin de renforcer la résilience globale de l'organisation.", IF($F17="Non applicable", "Non applicable.", "")))))) -> Optimiser la supervision de sécurité par l'amélioration continue des capacités de détection, l'enrichissement des sources de données et l'adaptation dynamique aux menaces émergentes afin de renforcer la résilience globale de l'organisation. | J17: =IFERROR(__xludf.DUMMYFUNCTION("""COMPUTED_VALUE"""),"04 - Incidents & notification") -> 04 - Incidents & notification
B18: 16 | C18: Exercices de crise cyber (tests et amélioration) | D18: Tester régulièrement l’organisation (scénarios d’attaque) pour vérifier l’escalade, la coordination, la communication et la reprise. | E18: Scénarios, convocations, compte-rendus d’exercice, plan d’amélioration, suivi des actions. | F18: 5 - Optimal | G18: {=IF(F18="", "", IFERROR(INDEX('Echelle de maturité'!$B$2:$B$7, MATCH(F18, 'Echelle de maturité'!$C$2:$C$7, 0)), ""))} -> Des objectifs de réduction des risques cyber intégrés à la stratégie de l'organisation. Des moyens humains, budgétaires conséquents, un plan d'action cyber exhaustif, adapté aux menaces stratégiques. | H18: =IF($F18="1 - Insuffisant", "Mettre en place des exercices de gestion de crise cybersécurité (type table-top) afin de tester les capacités de réponse de l'organisation face à des scénarios réalistes et critiques, puis formaliser les enseignements et les plans d'amélioration associés.", IF($F18="2 - Émergent", "Formaliser la démarche de simulation de crise en définissant une fréquence minimale des exercices, en structurant les scénarios et en assurant la production systématique de comptes rendus documentés.", IF($F18="3 - Intermédiaire", "Organiser des exercices de crise réguliers couvrant différents scénarios de menaces, suivre les actions correctives issues des retours d'expérience et mesurer l'amélioration progressive des capacités de réponse.", IF($F18="4 - Confirmé", "Maintenir un programme structuré d'exercices de crise intégrant des scénarios variés et complexes, en capitalisant sur les retours d'expérience pour améliorer les plans de continuité et de réponse aux incidents.", IF($F18="5 - Optimal", "Optimiser les exercices de gestion de crise en les intégrant pleinement dans la stratégie de résilience de l'organisation, en simulant des scénarios avancés impliquant plusieurs fonctions et en améliorant en continu la capacité de réponse globale.", IF($F18="Non applicable", "Non applicable.", "")))))) -> Optimiser les exercices de gestion de crise en les intégrant pleinement dans la stratégie de résilience de l'organisation, en simulant des scénarios avancés impliquant plusieurs fonctions et en améliorant en continu la capacité de réponse globale. | J18: =IFERROR(__xludf.DUMMYFUNCTION("""COMPUTED_VALUE"""),"04 - Incidents & notification") -> 04 - Incidents & notification
B19: 17 | C19: Processus de notification des incidents significatifs | D19: Être capable d’identifier un incident “significatif” et de notifier selon une procédure et des délais définis, avec traçabilité. | E19: Procédure de notification, critères “incident significatif”, modèles (fiche), registre des notifications, preuves de tests/exercices de notification. | F19: 3 - Intermédiaire | G19: {=IF(F19="", "", IFERROR(INDEX('Echelle de maturité'!$B$2:$B$7, MATCH(F19, 'Echelle de maturité'!$C$2:$C$7, 0)), ""))} -> Une conscience partagée des risques cyber pour l'organisation et la volonté de formaliser un plan d'action cyber complet tout en ajustant les moyens en conséquence. | H19: =IF($F19="1 - Insuffisant", "Définir un processus de notification des incidents de sécurité répondant aux exigences réglementaires, incluant les critères de qualification d'un incident significatif, les responsabilités de notification et les délais associés, ainsi qu'un registre de s"&"uivi.", IF($F19="2 - Émergent", "Formaliser la procédure de notification des incidents en précisant les critères de qualification, les rôles et responsabilités, les délais de notification et les informations minimales à transmettre aux parties concernées.", IF($F19="3 - Intermédiaire", "Tester et structurer le processus de notification des incidents significatifs, formaliser les modèles de communication et assurer la traçabilité complète des notifications et des échanges associés.", IF($F19="4 - Confirmé", "Maintenir et améliorer le dispositif de notification en réalisant des tests réguliers, en intégrant les retours d'expérience et en assurant une mise à jour périodique des procédures et des modèles de communication.", IF($F19="5 - Optimal", "Optimiser le processus de notification des incidents en renforçant la réactivité, la fiabilité et la qualité des informations transmises, et en intégrant les enseignements des exercices et des incidents réels dans une démarche d'amélioration continue.", IF($F19="Non applicable", "Non applicable.", "")))))) -> Tester et structurer le processus de notification des incidents significatifs, formaliser les modèles de communication et assurer la traçabilité complète des notifications et des échanges associés. | J19: =IFERROR(__xludf.DUMMYFUNCTION("""COMPUTED_VALUE"""),"04 - Incidents & notification") -> 04 - Incidents & notification
A20: Continuité / Résilience | B20: 18 | C20: Sauvegardes : stratégie, couverture et responsabilité | D20: Sauvegarder les systèmes et données critiques avec une stratégie définie (RPO/RTO), une couverture complète et des responsabilités claires. | E20: Politique de sauvegarde, périmètre couvert (systèmes/données critiques), RPO/RTO, rapports de succès, preuve de supervision, gestion des exceptions. | F20: 4 - Confirmé | G20: {=IF(F20="", "", IFERROR(INDEX('Echelle de maturité'!$B$2:$B$7, MATCH(F20, 'Echelle de maturité'!$C$2:$C$7, 0)), ""))} -> Une cartographie précise de ses risques cyber pour l'organisation, un plan d'action cyber approfondi et des moyens humains et budgétaires dédiés. | H20: =IF($F20="1 - Insuffisant", "Définir une stratégie de sauvegarde couvrant les actifs critiques, incluant les fréquences de sauvegarde, les objectifs de restauration (RPO/RTO), les responsabilités et les mécanismes de supervision.", IF($F20="2 - Émergent", "Formaliser la politique de sauvegarde en documentant le périmètre, les fréquences, les objectifs de reprise (RPO/RTO), les rôles associés et les modalités de suivi et de reporting.", IF($F20="3 - Intermédiaire", "Étendre la couverture des sauvegardes à l'ensemble des systèmes et données critiques, valider les objectifs de reprise, structurer le suivi des sauvegardes et traiter systématiquement les incidents de sauvegarde.", IF($F20="4 - Confirmé", "Maintenir une stratégie de sauvegarde robuste avec des contrôles réguliers, des tests de restauration, un suivi des indicateurs de performance et une adaptation continue aux évolutions du système d'information.", IF($F20="5 - Optimal", "Optimiser la stratégie de sauvegarde en renforçant l'automatisation, en améliorant la résilience et en intégrant les tests de restauration et les résultats de supervision dans une démarche d'amélioration continue.", IF($F20="Non applicable", "Non applicable.", "")))))) -> Maintenir une stratégie de sauvegarde robuste avec des contrôles réguliers, des tests de restauration, un suivi des indicateurs de performance et une adaptation continue aux évolutions du système d'information. | J20: =IFERROR(__xludf.DUMMYFUNCTION("""COMPUTED_VALUE"""),"05 - Continuité / Résilience") -> 05 - Continuité / Résilience
B21: 19 | C21: Tests de restauration (preuve de restaurabilité) | D21: Tester régulièrement la restauration pour prouver que les sauvegardes sont exploitables (applications/données critiques). | E21: Plan de tests, comptes-rendus, preuves de restaurations réussies, périodicité, suivi des écarts/corrections. | F21: 5 - Optimal | G21: {=IF(F21="", "", IFERROR(INDEX('Echelle de maturité'!$B$2:$B$7, MATCH(F21, 'Echelle de maturité'!$C$2:$C$7, 0)), ""))} -> Des objectifs de réduction des risques cyber intégrés à la stratégie de l'organisation. Des moyens humains, budgétaires conséquents, un plan d'action cyber exhaustif, adapté aux menaces stratégiques. | H21: =IF($F21="1 - Insuffisant", "Définir un plan de tests de restauration des sauvegardes couvrant les actifs critiques, incluant la fréquence minimale des tests, les responsabilités associées et les critères de validation des restaurations.", IF($F21="2 - Émergent", "Formaliser le plan de tests de restauration en précisant les systèmes concernés, les fréquences, les scénarios de test et les critères de succès, ainsi que les modalités de documentation des résultats.", IF($F21="3 - Intermédiaire", "Étendre les tests de restauration à l'ensemble des systèmes critiques, assurer la traçabilité des résultats et suivre systématiquement les actions correctives issues des tests.", IF($F21="4 - Confirmé", "Maintenir des tests de restauration réguliers et représentatifs, analyser les écarts entre objectifs et résultats réels, et intégrer les enseignements dans l'amélioration des plans de continuité et de reprise.", IF($F21="5 - Optimal", "Optimiser les tests de restauration en les intégrant pleinement dans une démarche de résilience globale, en améliorant en continu les capacités de reprise et en renforçant la fiabilité des processus de sauvegarde et de restauration.", IF($F21="Non applicable", "Non applicable.", "")))))) -> Optimiser les tests de restauration en les intégrant pleinement dans une démarche de résilience globale, en améliorant en continu les capacités de reprise et en renforçant la fiabilité des processus de sauvegarde et de restauration. | J21: =IFERROR(__xludf.DUMMYFUNCTION("""COMPUTED_VALUE"""),"05 - Continuité / Résilience") -> 05 - Continuité / Résilience
B22: 20 | C22: PRA / PCA (continuité et reprise d’activité) | D22: Disposer d’un plan de continuité/reprise pour les services critiques (scénarios, RTO/RPO, responsabilités, communication). | E22: PRA/PCA documentés, liste services critiques, RTO/RPO, scénarios (panne, ransomware), responsables, validation direction. | F22: 5 - Optimal | G22: {=IF(F22="", "", IFERROR(INDEX('Echelle de maturité'!$B$2:$B$7, MATCH(F22, 'Echelle de maturité'!$C$2:$C$7, 0)), ""))} -> Des objectifs de réduction des risques cyber intégrés à la stratégie de l'organisation. Des moyens humains, budgétaires conséquents, un plan d'action cyber exhaustif, adapté aux menaces stratégiques. | H22: =IF($F22="1 - Insuffisant", "Identifier et cartographier les services critiques de l'organisation et définir les objectifs de continuité et de reprise (RTO/RPO), puis établir un premier plan de continuité et de reprise d'activité (PCA/PRA) structuré.", IF($F22="2 - Émergent", "Formaliser les plans de continuité et de reprise en documentant les services critiques, les objectifs RTO/RPO, les scénarios de crise et les modalités d'escalade et de coordination.", IF($F22="3 - Intermédiaire", "Compléter et structurer les plans de continuité et de reprise pour l'ensemble des services critiques, assurer leur validation, organiser des revues périodiques et tester régulièrement les dispositifs.", IF($F22="4 - Confirmé", "Maintenir des plans de continuité et de reprise à jour, intégrer les retours d'exercices et d'incidents, et suivre des indicateurs de performance liés à la capacité de reprise et de continuité.", IF($F22="5 - Optimal", "Optimiser les plans de continuité et de reprise en les intégrant pleinement dans la gouvernance de résilience de l'organisation, en améliorant en continu les capacités de reprise et en adaptant les dispositifs aux évolutions des risques et du système d'in"&"formation.", IF($F22="Non applicable", "Non applicable.", "")))))) -> Optimiser les plans de continuité et de reprise en les intégrant pleinement dans la gouvernance de résilience de l'organisation, en améliorant en continu les capacités de reprise et en adaptant les dispositifs aux évolutions des risques et du système d'information. | J22: =IFERROR(__xludf.DUMMYFUNCTION("""COMPUTED_VALUE"""),"05 - Continuité / Résilience") -> 05 - Continuité / Résilience
B23: 21 | C23: Protection des sauvegardes (immutabilité / offline / séparation) | D23: Protéger les sauvegardes contre la compromission (ransomware) via isolation, immutabilité, séparation des comptes et contrôle des accès. | E23: Paramétrage immutabilité/offline, séparation des comptes admin backup, durcissement, logs d’accès, preuves de protection, revues. | F23: 5 - Optimal | G23: {=IF(F23="", "", IFERROR(INDEX('Echelle de maturité'!$B$2:$B$7, MATCH(F23, 'Echelle de maturité'!$C$2:$C$7, 0)), ""))} -> Des objectifs de réduction des risques cyber intégrés à la stratégie de l'organisation. Des moyens humains, budgétaires conséquents, un plan d'action cyber exhaustif, adapté aux menaces stratégiques. | H23: =IF($F23="1 - Insuffisant", "Mettre en place des mécanismes de protection des sauvegardes, incluant la séparation des comptes et des droits, la sécurisation des accès et la journalisation des actions sur les systèmes de sauvegarde.", IF($F23="2 - Émergent", "Formaliser la protection des sauvegardes en définissant les règles de séparation des accès, en documentant les mécanismes de sécurisation (immutabilité ou hors ligne) et en structurant la traçabilité des actions.", IF($F23="3 - Intermédiaire", "Généraliser les mécanismes de protection des sauvegardes à l'ensemble du périmètre critique, renforcer le contrôle des accès et organiser des revues périodiques des habilitations et des journaux d'accès.", IF($F23="4 - Confirmé", "Maintenir un niveau élevé de protection des sauvegardes en contrôlant régulièrement les accès, en surveillant les activités suspectes et en testant périodiquement la résistance des sauvegardes face aux scénarios de compromission.", IF($F23="5 - Optimal", "Optimiser la protection des sauvegardes en renforçant continuellement leur résilience face aux menaces, en adaptant les mécanismes de sécurité aux évolutions des risques et en intégrant ces contrôles dans une démarche globale de gestion des risques et de "&"continuité.", IF($F23="Non applicable", "Non applicable.", "")))))) -> Optimiser la protection des sauvegardes en renforçant continuellement leur résilience face aux menaces, en adaptant les mécanismes de sécurité aux évolutions des risques et en intégrant ces contrôles dans une démarche globale de gestion des risques et de continuité. | J23: =IFERROR(__xludf.DUMMYFUNCTION("""COMPUTED_VALUE"""),"05 - Continuité / Résilience") -> 05 - Continuité / Résilience
A24: Fournisseurs / Supply Chain | B24: 22 | C24: Identification des fournisseurs critiques | D24: Identifier les fournisseurs dont la compromission pourrait impacter les services essentiels ou importants. | E24: Cartographie fournisseurs ,Liste des fournisseurs critiques ,Critères de criticité ,Validation de la direction | F24: 3 - Intermédiaire | G24: {=IF(F24="", "", IFERROR(INDEX('Echelle de maturité'!$B$2:$B$7, MATCH(F24, 'Echelle de maturité'!$C$2:$C$7, 0)), ""))} -> Une conscience partagée des risques cyber pour l'organisation et la volonté de formaliser un plan d'action cyber complet tout en ajustant les moyens en conséquence. | H24: =IF($F24="1 - Insuffisant", "Identifier les fournisseurs intervenant sur les services critiques de l'organisation et établir une cartographie initiale des dépendances externes.", IF($F24="2 - Émergent", "Formaliser les critères de criticité des fournisseurs et structurer une liste consolidée et tenue à jour des prestataires essentiels pour les activités de l'organisation.", IF($F24="3 - Intermédiaire", "Mettre en place des revues périodiques des fournisseurs critiques et intégrer systématiquement les dépendances fournisseurs dans les analyses de risques cybersécurité.", IF($F24="4 - Confirmé", "Maintenir une cartographie actualisée des fournisseurs critiques et suivre de manière continue les évolutions des risques liés aux dépendances externes.", IF($F24="5 - Optimal", "Optimiser la gestion des risques fournisseurs en intégrant pleinement les dépendances critiques dans la gouvernance des risques de l'organisation et en adaptant en continu les mesures de contrôle en fonction de l'évolution des menaces et des enjeux métier"&"s.", IF($F24="Non applicable", "Non applicable.", "")))))) -> Mettre en place des revues périodiques des fournisseurs critiques et intégrer systématiquement les dépendances fournisseurs dans les analyses de risques cybersécurité. | J24: =IFERROR(__xludf.DUMMYFUNCTION("""COMPUTED_VALUE"""),"06 - Fournisseurs / Supply Chain") -> 06 - Fournisseurs / Supply Chain
B25: 23 | C25: Évaluation des risques fournisseurs | D25: Évaluer les risques cybersécurité liés aux fournisseurs avant contractualisation et périodiquement. | E25: Questionnaires de sécurité , Évaluations de risques , Rapports d'analyse , Plan d'actions | F25: 5 - Optimal | G25: {=IF(F25="", "", IFERROR(INDEX('Echelle de maturité'!$B$2:$B$7, MATCH(F25, 'Echelle de maturité'!$C$2:$C$7, 0)), ""))} -> Des objectifs de réduction des risques cyber intégrés à la stratégie de l'organisation. Des moyens humains, budgétaires conséquents, un plan d'action cyber exhaustif, adapté aux menaces stratégiques. | H25: =IF($F25="1 - Insuffisant", "Mettre en place un processus d'évaluation de la maturité cybersécurité des fournisseurs afin d'identifier les risques associés aux prestataires intervenant sur les services critiques.", IF($F25="2 - Émergent", "Formaliser le processus d'évaluation des fournisseurs en définissant des critères standardisés, des questionnaires et une méthodologie homogène d'analyse de la maturité cybersécurité.", IF($F25="3 - Intermédiaire", "Généraliser les évaluations de cybersécurité à l'ensemble des fournisseurs critiques et intégrer les résultats dans les analyses de risques et les décisions d'engagement.", IF($F25="4 - Confirmé", "Maintenir un dispositif d'évaluation régulier des fournisseurs, suivre les plans de remédiation associés et intégrer les résultats dans le pilotage des risques tiers.", IF($F25="5 - Optimal", "Optimiser l'évaluation des fournisseurs en intégrant les résultats dans une démarche continue de gestion des risques tiers, en adaptant les exigences de sécurité en fonction du niveau de risque et en renforçant le suivi des mesures correctives.", IF($F25="Non applicable", "Non applicable.", "")))))) -> Optimiser l'évaluation des fournisseurs en intégrant les résultats dans une démarche continue de gestion des risques tiers, en adaptant les exigences de sécurité en fonction du niveau de risque et en renforçant le suivi des mesures correctives. | J25: =IFERROR(__xludf.DUMMYFUNCTION("""COMPUTED_VALUE"""),"06 - Fournisseurs / Supply Chain") -> 06 - Fournisseurs / Supply Chain
B26: 24 | C26: Clauses cybersécurité dans les contrats | D26: Intégrer des exigences de sécurité, notification d'incidents et droit d'audit dans les contrats. | E26: Contrats ,Clauses sécurité ,SLA sécurité ,Obligations de notification | F26: 5 - Optimal | G26: {=IF(F26="", "", IFERROR(INDEX('Echelle de maturité'!$B$2:$B$7, MATCH(F26, 'Echelle de maturité'!$C$2:$C$7, 0)), ""))} -> Des objectifs de réduction des risques cyber intégrés à la stratégie de l'organisation. Des moyens humains, budgétaires conséquents, un plan d'action cyber exhaustif, adapté aux menaces stratégiques. | H26: =IF($F26="1 - Insuffisant", "Intégrer des clauses de sécurité de base dans les contrats fournisseurs afin de couvrir les exigences minimales de cybersécurité liées aux services et prestations critiques.", IF($F26="2 - Émergent", "Formaliser et standardiser les clauses contractuelles de cybersécurité et les intégrer systématiquement dans les processus d'achat et de contractualisation des fournisseurs.", IF($F26="3 - Intermédiaire", "Étendre les exigences de cybersécurité aux contrats existants lors de leur renouvellement et s'assurer de leur cohérence avec les risques identifiés pour les fournisseurs critiques.", IF($F26="4 - Confirmé", "Maintenir des clauses contractuelles cybersécurité à jour en les révisant régulièrement en fonction de l'évolution des risques, des menaces et des exigences réglementaires applicables.", IF($F26="5 - Optimal", "Optimiser la gestion contractuelle de la cybersécurité en adaptant en continu les exigences contractuelles au niveau de risque des fournisseurs et en renforçant leur intégration dans la gouvernance globale des risques tiers.", IF($F26="Non applicable", "Non applicable.", "")))))) -> Optimiser la gestion contractuelle de la cybersécurité en adaptant en continu les exigences contractuelles au niveau de risque des fournisseurs et en renforçant leur intégration dans la gouvernance globale des risques tiers. | J26: =IFERROR(__xludf.DUMMYFUNCTION("""COMPUTED_VALUE"""),"06 - Fournisseurs / Supply Chain") -> 06 - Fournisseurs / Supply Chain
B27: 25 | C27: Revue périodique des fournisseurs critiques | D27: Vérifier régulièrement le niveau de sécurité des fournisseurs critiques. | E27: Revues annuelles ,Rapports d'audit ,Tableaux de suivi ,Plans de remédiation. | F27: 5 - Optimal | G27: {=IF(F27="", "", IFERROR(INDEX('Echelle de maturité'!$B$2:$B$7, MATCH(F27, 'Echelle de maturité'!$C$2:$C$7, 0)), ""))} -> Des objectifs de réduction des risques cyber intégrés à la stratégie de l'organisation. Des moyens humains, budgétaires conséquents, un plan d'action cyber exhaustif, adapté aux menaces stratégiques. | H27: =IF($F27="1 - Insuffisant", "Mettre en place un programme de revue des fournisseurs critiques afin d'évaluer leur niveau de risque et leur conformité aux exigences de cybersécurité de l'organisation.", IF($F27="2 - Émergent", "Formaliser le processus de revue des fournisseurs en définissant une fréquence, des critères d'évaluation et les responsabilités associées à ces revues.", IF($F27="3 - Intermédiaire", "Généraliser les revues à l'ensemble des fournisseurs critiques et intégrer leurs résultats dans la gestion des risques et les décisions de maintien ou de renouvellement des relations.", IF($F27="4 - Confirmé", "Maintenir un dispositif de revue régulier des fournisseurs critiques, suivre leurs performances et intégrer les résultats dans le pilotage global des risques tiers.", IF($F27="5 - Optimal", "Optimiser la revue des fournisseurs en intégrant les résultats dans une démarche continue de gestion des risques tiers, en adaptant les exigences selon l'évolution du niveau de risque et en renforçant la prise de décision basée sur la performance et la cr"&"iticité.", IF($F27="Non applicable", "Non applicable.", "")))))) -> Optimiser la revue des fournisseurs en intégrant les résultats dans une démarche continue de gestion des risques tiers, en adaptant les exigences selon l'évolution du niveau de risque et en renforçant la prise de décision basée sur la performance et la criticité. | J27: =IFERROR(__xludf.DUMMYFUNCTION("""COMPUTED_VALUE"""),"06 - Fournisseurs / Supply Chain") -> 06 - Fournisseurs / Supply Chain
A28: Protection des données & Cryptographie | B28: 26 | C28: Chiffrement des données au repos | D28: Protéger les données sensibles stockées sur postes, serveurs, bases de données et sauvegardes. | E28: Politique de chiffrement ,Configuration BitLocker/LUKS ,Chiffrement BDD ,Rapports de conformité | F28: 5 - Optimal | G28: {=IF(F28="", "", IFERROR(INDEX('Echelle de maturité'!$B$2:$B$7, MATCH(F28, 'Echelle de maturité'!$C$2:$C$7, 0)), ""))} -> Des objectifs de réduction des risques cyber intégrés à la stratégie de l'organisation. Des moyens humains, budgétaires conséquents, un plan d'action cyber exhaustif, adapté aux menaces stratégiques. | H28: =IF($F28="1 - Insuffisant", "Mettre en place le chiffrement des données sensibles, en particulier sur les systèmes critiques, les échanges et les supports de stockage exposés.", IF($F28="2 - Émergent", "Formaliser une politique de chiffrement définissant les types de données à protéger, les méthodes de chiffrement et les exigences minimales de sécurité, puis étendre progressivement son application.", IF($F28="3 - Intermédiaire", "Étendre la couverture du chiffrement à l'ensemble des données critiques et des flux sensibles, et encadrer les exceptions avec des règles formelles de validation et de traçabilité.", IF($F28="4 - Confirmé", "Maintenir la conformité du chiffrement par des contrôles réguliers, assurer la gestion des exceptions et suivre les évolutions des pratiques et des exigences de sécurité.", IF($F28="5 - Optimal", "Optimiser la protection des données par chiffrement en adaptant continuellement les mécanismes aux évolutions des menaces et des usages, et en renforçant la gouvernance de la protection des données sensibles.", IF($F28="Non applicable", "Non applicable.", "")))))) -> Optimiser la protection des données par chiffrement en adaptant continuellement les mécanismes aux évolutions des menaces et des usages, et en renforçant la gouvernance de la protection des données sensibles. | J28: =IFERROR(__xludf.DUMMYFUNCTION("""COMPUTED_VALUE"""),"07 - Protection des données & Cryptographie") -> 07 - Protection des données & Cryptographie
B29: 27 | C29: Chiffrement des données en transit | D29: Protéger les communications via TLS, VPN ou autres mécanismes sécurisés. | E29: Configuration TLS ,VPN ,Certificats ,Rapports de conformité | F29: 4 - Confirmé | G29: {=IF(F29="", "", IFERROR(INDEX('Echelle de maturité'!$B$2:$B$7, MATCH(F29, 'Echelle de maturité'!$C$2:$C$7, 0)), ""))} -> Une cartographie précise de ses risques cyber pour l'organisation, un plan d'action cyber approfondi et des moyens humains et budgétaires dédiés. | H29: =IF($F29="1 - Insuffisant", "Mettre en place le chiffrement des communications pour les flux sensibles et critiques afin de protéger les échanges de données contre les interceptions et altérations.", IF($F29="2 - Émergent", "Formaliser l'utilisation du chiffrement des communications en définissant les types de flux concernés et en généralisant progressivement son application aux échanges sensibles.", IF($F29="3 - Intermédiaire", "Étendre la couverture du chiffrement des communications à l'ensemble des flux critiques et mettre en place des contrôles réguliers de conformité et d'application.", IF($F29="4 - Confirmé", "Maintenir les mécanismes de chiffrement des communications, surveiller les vulnérabilités associées et assurer une gestion régulière de la conformité et des exceptions.", IF($F29="5 - Optimal", "Optimiser la protection des communications en adaptant continuellement les mécanismes de chiffrement aux évolutions technologiques et aux menaces, et en renforçant la résilience globale des échanges de données.", IF($F29="Non applicable", "Non applicable.", "")))))) -> Maintenir les mécanismes de chiffrement des communications, surveiller les vulnérabilités associées et assurer une gestion régulière de la conformité et des exceptions. | J29: =IFERROR(__xludf.DUMMYFUNCTION("""COMPUTED_VALUE"""),"07 - Protection des données & Cryptographie") -> 07 - Protection des données & Cryptographie
B30: 28 | C30: Gestion des clés cryptographiques | D30: Assurer la génération, le stockage, la rotation et la révocation des clés. | E30: Politique de gestion des clés ,Coffre de clés ,Rotation documentée ,Inventaire des certificats | F30: 5 - Optimal | G30: {=IF(F30="", "", IFERROR(INDEX('Echelle de maturité'!$B$2:$B$7, MATCH(F30, 'Echelle de maturité'!$C$2:$C$7, 0)), ""))} -> Des objectifs de réduction des risques cyber intégrés à la stratégie de l'organisation. Des moyens humains, budgétaires conséquents, un plan d'action cyber exhaustif, adapté aux menaces stratégiques. | H30: =IF($F30="1 - Insuffisant", "Définir une politique de gestion des clés cryptographiques couvrant leur cycle de vie, leur utilisation et les principes de sécurité associés.", IF($F30="2 - Émergent", "Formaliser les procédures de gestion des clés cryptographiques, incluant leur génération, stockage, rotation, sauvegarde et révocation.", IF($F30="3 - Intermédiaire", "Mettre en place des contrôles réguliers de l'application des procédures de gestion des clés et encadrer strictement les accès aux éléments cryptographiques sensibles.", IF($F30="4 - Confirmé", "Maintenir un dispositif robuste de gestion des clés cryptographiques, assurer des contrôles réguliers et surveiller les risques liés à leur utilisation et à leur protection.", IF($F30="5 - Optimal", "Optimiser la gestion des clés cryptographiques en adaptant en continu les mécanismes de protection aux évolutions des menaces et des technologies, et en renforçant la gouvernance globale du cycle de vie des clés.", IF($F30="Non applicable", "Non applicable.", "")))))) -> Optimiser la gestion des clés cryptographiques en adaptant en continu les mécanismes de protection aux évolutions des menaces et des technologies, et en renforçant la gouvernance globale du cycle de vie des clés. | J30: =IFERROR(__xludf.DUMMYFUNCTION("""COMPUTED_VALUE"""),"07 - Protection des données & Cryptographie") -> 07 - Protection des données & Cryptographie
A31: Sensibilisation & Surveillance | B31: 29 | C31: Programme de sensibilisation cybersécurité | D31: Former régulièrement les collaborateurs aux risques cyber et aux bonnes pratiques. | E31: Plan de sensibilisation ,Supports de formation ,Feuilles de présence ,Taux de participation | F31: 4 - Confirmé | G31: {=IF(F31="", "", IFERROR(INDEX('Echelle de maturité'!$B$2:$B$7, MATCH(F31, 'Echelle de maturité'!$C$2:$C$7, 0)), ""))} -> Une cartographie précise de ses risques cyber pour l'organisation, un plan d'action cyber approfondi et des moyens humains et budgétaires dédiés. | H31: =IF($F31="1 - Insuffisant", "Mettre en place un programme de sensibilisation à la cybersécurité pour l'ensemble des collaborateurs afin de développer une culture de sécurité de base au sein de l'organisation.", IF($F31="2 - Émergent", "Formaliser un plan annuel de sensibilisation à la cybersécurité en définissant les thématiques prioritaires en fonction des risques et les populations cibles.", IF($F31="3 - Intermédiaire", "Structurer le programme de sensibilisation en suivant la participation des collaborateurs et en renforçant la diffusion des bonnes pratiques de cybersécurité.", IF($F31="4 - Confirmé", "Maintenir un programme de sensibilisation régulier et structuré, actualiser les contenus en fonction de l'évolution des menaces et suivre des indicateurs d'efficacité.", IF($F31="5 - Optimal", "Optimiser la sensibilisation à la cybersécurité en adaptant continuellement les contenus aux risques émergents, en renforçant l'engagement des collaborateurs et en mesurant l'impact du programme sur les comportements de sécurité.", IF($F31="Non applicable", "Non applicable.", "")))))) -> Maintenir un programme de sensibilisation régulier et structuré, actualiser les contenus en fonction de l'évolution des menaces et suivre des indicateurs d'efficacité. | J31: =IFERROR(__xludf.DUMMYFUNCTION("""COMPUTED_VALUE"""),"08 - Sensibilisation & Surveillance") -> 08 - Sensibilisation & Surveillance
B32: 30 | C32: Formation des administrateurs et équipes IT | D32: Maintenir les compétences techniques des équipes ayant des responsabilités de sécurité. | E32: Plan de formation ,Certifications ,Registre des formations | F32: 5 - Optimal | G32: {=IF(F32="", "", IFERROR(INDEX('Echelle de maturité'!$B$2:$B$7, MATCH(F32, 'Echelle de maturité'!$C$2:$C$7, 0)), ""))} -> Des objectifs de réduction des risques cyber intégrés à la stratégie de l'organisation. Des moyens humains, budgétaires conséquents, un plan d'action cyber exhaustif, adapté aux menaces stratégiques. | H32: =IF($F32="1 - Insuffisant", "Mettre en place un plan de formation en cybersécurité adapté aux rôles et responsabilités techniques et opérationnels au sein de l'organisation.", IF($F32="2 - Émergent", "Formaliser les besoins de formation en cybersécurité, définir les parcours par profil et assurer un suivi structuré des formations réalisées.", IF($F32="3 - Intermédiaire", "Évaluer régulièrement les compétences en cybersécurité et compléter les formations afin de couvrir les besoins identifiés et les écarts de compétences.", IF($F32="4 - Confirmé", "Maintenir et développer le niveau de compétence en cybersécurité, encourager la montée en expertise (formations avancées, certifications) et suivre l'évolution des besoins techniques.", IF($F32="5 - Optimal", "Optimiser la gestion des compétences en cybersécurité en intégrant une démarche continue de développement des savoirs, en anticipant les évolutions technologiques et en alignant les compétences sur les enjeux stratégiques de sécurité.", IF($F32="Non applicable", "Non applicable.", "")))))) -> Optimiser la gestion des compétences en cybersécurité en intégrant une démarche continue de développement des savoirs, en anticipant les évolutions technologiques et en alignant les compétences sur les enjeux stratégiques de sécurité. | J32: =IFERROR(__xludf.DUMMYFUNCTION("""COMPUTED_VALUE"""),"08 - Sensibilisation & Surveillance") -> 08 - Sensibilisation & Surveillance
B33: 31 | C33: Campagnes de phishing simulé | D33: Évaluer périodiquement la vigilance des utilisateurs face aux attaques. | E33: Résultats des campagnes ,Statistiques de clic ,Actions correctives | F33: Non applicable | G33: {=IF(F33="", "", IFERROR(INDEX('Echelle de maturité'!$B$2:$B$7, MATCH(F33, 'Echelle de maturité'!$C$2:$C$7, 0)), ""))} -> Le critère ou l'exigence évalué n'est pas pertinent au regard des activités, du périmètre technique ou du cadre réglementaire de l'organisation. | H33: =IF($F33="1 - Insuffisant", "Mettre en place des campagnes de simulation de phishing afin d'évaluer la sensibilisation des utilisateurs aux risques d'hameçonnage et aux comportements à risque.", IF($F33="2 - Émergent", "Formaliser les campagnes de simulation de phishing en définissant leur fréquence, leur périmètre et les modalités d'analyse des résultats obtenus.", IF($F33="3 - Intermédiaire", "Exploiter les résultats des campagnes de simulation de phishing pour adapter et renforcer les actions de sensibilisation et corriger les comportements à risque identifiés.", IF($F33="4 - Confirmé", "Maintenir des campagnes régulières de simulation de phishing et suivre des indicateurs d'évolution des comportements des utilisateurs afin d'améliorer continuellement le niveau de vigilance.", IF($F33="5 - Optimal", "Optimiser la résilience humaine face au phishing en intégrant les résultats des simulations dans une démarche globale d'amélioration continue de la culture de cybersécurité et de réduction des comportements à risque.", IF($F33="Non applicable", "Non applicable.", "")))))) -> Non applicable. | J33: =IFERROR(__xludf.DUMMYFUNCTION("""COMPUTED_VALUE"""),"08 - Sensibilisation & Surveillance") -> 08 - Sensibilisation & Surveillance
B34: 32 | C34: Journalisation des événements de sécurité | D34: Collecter et conserver les journaux nécessaires à la détection et à l'investigation des incidents. | E34: Politique de logs ,Configuration SIEM ,Durée de conservation ,Rapports | F34: Non applicable | G34: {=IF(F34="", "", IFERROR(INDEX('Echelle de maturité'!$B$2:$B$7, MATCH(F34, 'Echelle de maturité'!$C$2:$C$7, 0)), ""))} -> Le critère ou l'exigence évalué n'est pas pertinent au regard des activités, du périmètre technique ou du cadre réglementaire de l'organisation. | H34: =IF($F34="1 - Insuffisant", "Définir une politique de journalisation de sécurité identifiant les événements à collecter, les systèmes concernés et les objectifs de traçabilité.", IF($F34="2 - Émergent", "Formaliser la centralisation des journaux de sécurité, définir les durées de conservation et mettre en place un stockage adapté pour les événements critiques.", IF($F34="3 - Intermédiaire", "Étendre la couverture de journalisation à l'ensemble des systèmes critiques et améliorer la qualité des logs en assurant leur complétude, leur cohérence et leur exploitabilité.", IF($F34="4 - Confirmé", "Maintenir un dispositif de journalisation efficace, surveiller régulièrement la qualité et la disponibilité des logs et suivre des indicateurs de couverture et d'intégrité des événements de sécurité.", IF($F34="5 - Optimal", "Optimiser la journalisation en renforçant la capacité d'analyse et d'exploitation des événements de sécurité, en adaptant continuellement la couverture aux menaces et en intégrant la journalisation dans une stratégie globale de détection et de réponse.", IF($F34="Non applicable", "Non applicable.", "")))))) -> Non applicable. | J34: =IFERROR(__xludf.DUMMYFUNCTION("""COMPUTED_VALUE"""),"08 - Sensibilisation & Surveillance") -> 08 - Sensibilisation & Surveillance
B35: 33 | C35: Surveillance continue des événements de sécurité | D35: Analyser les événements de sécurité afin d'identifier rapidement les activités suspectes. | E35: Règles de détection ,Alertes ,Tableaux de bord ,Rapports SOC | F35: 4 - Confirmé | G35: {=IF(F35="", "", IFERROR(INDEX('Echelle de maturité'!$B$2:$B$7, MATCH(F35, 'Echelle de maturité'!$C$2:$C$7, 0)), ""))} -> Une cartographie précise de ses risques cyber pour l'organisation, un plan d'action cyber approfondi et des moyens humains et budgétaires dédiés. | H35: =IF($F35="1 - Insuffisant", "Mettre en place une capacité de surveillance des événements de sécurité et des mécanismes d'alerte afin d'identifier les activités suspectes sur le système d'information.", IF($F35="2 - Émergent", "Formaliser les processus de surveillance de sécurité en définissant les responsabilités, les règles de détection et les modalités de traitement des alertes.", IF($F35="3 - Intermédiaire", "Étendre la couverture de détection à l'ensemble des systèmes critiques et améliorer le traitement des alertes de sécurité de manière structurée et priorisée.", IF($F35="4 - Confirmé", "Maintenir et ajuster les capacités de détection de sécurité, optimiser les règles de corrélation et suivre des indicateurs de performance tels que le MTTD, le taux de faux positifs et les incidents détectés.", IF($F35="5 - Optimal", "Optimiser la détection des menaces en améliorant continuellement les capacités de surveillance, en adaptant les règles aux nouvelles menaces et en renforçant l'efficacité globale du dispositif de détection et de réponse.", IF($F35="Non applicable", "Non applicable.", "")))))) -> Maintenir et ajuster les capacités de détection de sécurité, optimiser les règles de corrélation et suivre des indicateurs de performance tels que le MTTD, le taux de faux positifs et les incidents détectés. | J35: =IFERROR(__xludf.DUMMYFUNCTION("""COMPUTED_VALUE"""),"08 - Sensibilisation & Surveillance") -> 08 - Sensibilisation & Surveillance
A36: Sécurité des réseaux et systèmes | B36: 34 | C36: Segmentation et cloisonnement réseau | D36: Segmenter les réseaux afin de limiter la propagation d'un incident de sécurité et isoler les systèmes critiques, les environnements d'administration et les flux sensibles. | E36: Cartographie réseau, Architecture réseau documentée, VLAN, ACL, Configuration Firewall, DMZ, Règles de filtrage, Revues périodiques des flux. | F36: 5 - Optimal | G36: {=IF(F36="", "", IFERROR(INDEX('Echelle de maturité'!$B$2:$B$7, MATCH(F36, 'Echelle de maturité'!$C$2:$C$7, 0)), ""))} -> Des objectifs de réduction des risques cyber intégrés à la stratégie de l'organisation. Des moyens humains, budgétaires conséquents, un plan d'action cyber exhaustif, adapté aux menaces stratégiques. | H36: =IF($F36="1 - Insuffisant", "Mettre en place une segmentation réseau afin de séparer les environnements critiques, utilisateurs et administratifs pour limiter la propagation des menaces.", IF($F36="2 - Émergent", "Formaliser la segmentation réseau en documentant les zones de sécurité existantes et en définissant des règles de filtrage des flux entre ces zones.", IF($F36="3 - Intermédiaire", "Contrôler régulièrement l'efficacité de la segmentation réseau, identifier les écarts de configuration et renforcer les règles de cloisonnement entre environnements.", IF($F36="4 - Confirmé", "Maintenir une architecture réseau sécurisée et cohérente, réaliser des revues périodiques de segmentation et adapter les règles aux évolutions des risques et du système d'information.", IF($F36="5 - Optimal", "Optimiser la segmentation réseau en renforçant en continu le cloisonnement des environnements critiques, en adaptant dynamiquement les règles de segmentation aux menaces et en intégrant cette approche dans une stratégie globale de sécurité du réseau.", IF($F36="Non applicable", "Non applicable.", "")))))) -> Optimiser la segmentation réseau en renforçant en continu le cloisonnement des environnements critiques, en adaptant dynamiquement les règles de segmentation aux menaces et en intégrant cette approche dans une stratégie globale de sécurité du réseau. | J36: 09 - Sécurité des réseaux et systèmes
B37: 35 | C37: Durcissement des systèmes et équipements | D37: Définir et appliquer des configurations sécurisées pour les postes de travail, serveurs, équipements réseau, systèmes industriels et services cloud afin de réduire la surface d'attaque. | E37: Standards de configuration, Benchmarks CIS ou ANSSI, GPO, Rapports de conformité, Procédures de durcissement, Gestion des exceptions. | F37: 5 - Optimal | G37: {=IF(F37="", "", IFERROR(INDEX('Echelle de maturité'!$B$2:$B$7, MATCH(F37, 'Echelle de maturité'!$C$2:$C$7, 0)), ""))} -> Des objectifs de réduction des risques cyber intégrés à la stratégie de l'organisation. Des moyens humains, budgétaires conséquents, un plan d'action cyber exhaustif, adapté aux menaces stratégiques. | H37: =IF($F37="1 - Insuffisant", "Définir des standards de configuration sécurisée pour l'ensemble des systèmes afin de réduire les risques liés aux mauvaises configurations.", IF($F37="2 - Émergent", "Formaliser des configurations de référence sécurisées (baseline) et les documenter pour les principaux systèmes et environnements.", IF($F37="3 - Intermédiaire", "Contrôler périodiquement la conformité des configurations aux standards définis et corriger les écarts identifiés sur les systèmes critiques.", IF($F37="4 - Confirmé", "Maintenir les standards de configuration sécurisée et adapter régulièrement les configurations aux nouveaux risques, aux évolutions technologiques et aux exigences de sécurité.", IF($F37="5 - Optimal", "Optimiser la gestion des configurations sécurisées en intégrant une amélioration continue des standards, en automatisant les contrôles de conformité et en adaptant en permanence les configurations aux menaces émergentes.", IF($F37="Non applicable", "Non applicable.", "")))))) -> Optimiser la gestion des configurations sécurisées en intégrant une amélioration continue des standards, en automatisant les contrôles de conformité et en adaptant en permanence les configurations aux menaces émergentes. | J37: 09 - Sécurité des réseaux et systèmes
B38: 36 | C38: Sécurisation des architectures et des communications | D38: Mettre en œuvre des mécanismes de protection des communications et des architectures critiques afin d'assurer leur disponibilité, intégrité et confidentialité. | E38: Schémas d'architecture, Configuration VPN, Chiffrement des flux, Reverse Proxy, WAF, Documentation réseau, Rapports d'audit. | F38: 5 - Optimal | G38: {=IF(F38="", "", IFERROR(INDEX('Echelle de maturité'!$B$2:$B$7, MATCH(F38, 'Echelle de maturité'!$C$2:$C$7, 0)), ""))} -> Des objectifs de réduction des risques cyber intégrés à la stratégie de l'organisation. Des moyens humains, budgétaires conséquents, un plan d'action cyber exhaustif, adapté aux menaces stratégiques. | H38: =IF($F38="1 - Insuffisant", "Mettre en œuvre des mécanismes de sécurisation des communications et des architectures critiques afin de réduire les risques d'interception, de compromission et de propagation des attaques.", IF($F38="2 - Émergent", "Formaliser les mesures de sécurité existantes et documenter une architecture cible sécurisée en précisant les principes de protection des communications et des systèmes critiques.", IF($F38="3 - Intermédiaire", "Contrôler régulièrement l'efficacité des mesures de protection mises en place et corriger les écarts entre l'architecture cible et l'architecture réelle.", IF($F38="4 - Confirmé", "Maintenir les mesures de sécurité de l'architecture et des communications et les adapter en continu aux évolutions technologiques et aux nouveaux risques identifiés.", IF($F38="5 - Optimal", "Optimiser la sécurité des architectures et des communications en intégrant une démarche d'amélioration continue, en renforçant la résilience des systèmes et en adaptant en permanence les mécanismes de protection aux menaces émergentes.", IF($F38="Non applicable", "Non applicable.", "")))))) -> Optimiser la sécurité des architectures et des communications en intégrant une démarche d'amélioration continue, en renforçant la résilience des systèmes et en adaptant en permanence les mécanismes de protection aux menaces émergentes. | J38: 09 - Sécurité des réseaux et systèmes
A39: Développement sécurisé et gestion des configurations | B39: 37 | C39: Cycle de développement sécurisé (Secure SDLC) | D39: Intégrer les exigences de cybersécurité dans toutes les phases du cycle de développement des applications et services. | E39: Politique Secure SDLC, Procédures DevSecOps, Exigences de sécurité projet, Checklists de validation, Documentation de conception sécurisée. | F39: 3 - Intermédiaire | G39: {=IF(F39="", "", IFERROR(INDEX('Echelle de maturité'!$B$2:$B$7, MATCH(F39, 'Echelle de maturité'!$C$2:$C$7, 0)), ""))} -> Une conscience partagée des risques cyber pour l'organisation et la volonté de formaliser un plan d'action cyber complet tout en ajustant les moyens en conséquence. | H39: =IF($F39="1 - Insuffisant", "Intégrer des exigences de cybersécurité dès la conception des projets afin de réduire les risques dès les phases initiales de développement.", IF($F39="2 - Émergent", "Formaliser un processus de développement sécurisé en définissant les exigences de sécurité, les bonnes pratiques et les responsabilités associées aux équipes projets.", IF($F39="3 - Intermédiaire", "Contrôler le respect des exigences de sécurité dans les projets et s'assurer de leur prise en compte tout au long du cycle de vie des développements.", IF($F39="4 - Confirmé", "Améliorer en continu les pratiques de développement sécurisé en intégrant les retours d'expérience, les audits et les évolutions des menaces dans les standards de développement.", IF($F39="5 - Optimal", "Optimiser le développement sécurisé en intégrant la sécurité de manière systématique et automatisée dans les processus de développement, tout en renforçant la maturité globale des pratiques DevSecOps.", IF($F39="Non applicable", "Non applicable.", "")))))) -> Contrôler le respect des exigences de sécurité dans les projets et s'assurer de leur prise en compte tout au long du cycle de vie des développements. | J39: 10 - Développement sécurisé et gestion des configurations
B40: 38 | C40: Revue de code et tests de sécurité applicatifs | D40: Réaliser des revues de code et des analyses de sécurité avant toute mise en production afin d'identifier les vulnérabilités. | E40: Rapports SAST, Rapports DAST, Revues de code, Résultats de tests de pénétration applicatifs, Tickets de correction. | F40: 4 - Confirmé | G40: {=IF(F40="", "", IFERROR(INDEX('Echelle de maturité'!$B$2:$B$7, MATCH(F40, 'Echelle de maturité'!$C$2:$C$7, 0)), ""))} -> Une cartographie précise de ses risques cyber pour l'organisation, un plan d'action cyber approfondi et des moyens humains et budgétaires dédiés. | H40: =IF($F40="1 - Insuffisant", "Mettre en place des revues de code et des tests de sécurité applicatifs afin d'identifier les vulnérabilités dès les phases de développement.", IF($F40="2 - Émergent", "Formaliser les contrôles de sécurité applicative en définissant leur fréquence, leur périmètre et les responsabilités associées (revues de code, tests de sécurité).", IF($F40="3 - Intermédiaire", "Mesurer l'efficacité des contrôles de sécurité applicative et assurer le suivi des corrections des vulnérabilités identifiées jusqu'à leur résolution.", IF($F40="4 - Confirmé", "Maintenir et renforcer l'automatisation des contrôles de sécurité applicative et intégrer les pratiques DevSecOps dans les processus de développement et de livraison.", IF($F40="5 - Optimal", "Optimiser la sécurité applicative en intégrant une démarche DevSecOps mature, en automatisant les contrôles de sécurité tout au long du cycle de développement et en améliorant continuellement la détection et la correction des vulnérabilités.", IF($F40="Non applicable", "Non applicable.", "")))))) -> Maintenir et renforcer l'automatisation des contrôles de sécurité applicative et intégrer les pratiques DevSecOps dans les processus de développement et de livraison. | J40: 10 - Développement sécurisé et gestion des configurations
B41: 39 | C41: Gestion des configurations sécurisées | D41: Maintenir des configurations approuvées, documentées et contrôlées pour l'ensemble des systèmes, applications et équipements critiques. | E41: Baselines de sécurité, CMDB, Inventaire des configurations, Procédures de changement, Rapports de conformité, Revues périodiques. | F41: 1 - Insuffisant | G41: {=IF(F41="", "", IFERROR(INDEX('Echelle de maturité'!$B$2:$B$7, MATCH(F41, 'Echelle de maturité'!$C$2:$C$7, 0)), ""))} -> Une conscience insuffisante des risques cyber pesant sur l'organisation. Pas ou peu de mesures spécifiques mises en oeuvre en matière de cybersécurité. | H41: =IF($F41="1 - Insuffisant", "Définir et documenter les configurations de référence sécurisées pour les systèmes et composants critiques de l'organisation.", IF($F41="2 - Émergent", "Formaliser les processus de gestion des configurations en définissant les standards, les responsabilités et les modalités de mise à jour des configurations de référence.", IF($F41="3 - Intermédiaire", "Mettre en place des contrôles réguliers de conformité des configurations afin d'identifier et de corriger les écarts par rapport aux standards définis.", IF($F41="4 - Confirmé", "Maintenir les contrôles de conformité et automatiser la détection des écarts de configuration pour améliorer la réactivité et la fiabilité du dispositif.", IF($F41="5 - Optimal", "Optimiser la gestion des configurations sécurisées en intégrant une automatisation avancée des contrôles, en adaptant en continu les standards aux menaces et en renforçant la cohérence globale de l'environnement.", IF($F41="Non applicable", "Non applicable.", "")))))) -> Définir et documenter les configurations de référence sécurisées pour les systèmes et composants critiques de l'organisation. | J41: 10 - Développement sécurisé et gestion des configurations
A42: Résilience avancée et amélioration continue | B42: 40 | C42: Veille sur les menaces cyber (Threat Intelligence) | D42: Surveiller les menaces émergentes et exploiter les informations de sécurité afin d'anticiper les risques pouvant affecter l'organisation. | E42: Abonnements CERT-FR, Flux IOC, Rapports de veille, Bulletins de sécurité, Procédure de traitement des alertes, Comptes-rendus d'analyse. | F42: 5 - Optimal | G42: {=IF(F42="", "", IFERROR(INDEX('Echelle de maturité'!$B$2:$B$7, MATCH(F42, 'Echelle de maturité'!$C$2:$C$7, 0)), ""))} -> Des objectifs de réduction des risques cyber intégrés à la stratégie de l'organisation. Des moyens humains, budgétaires conséquents, un plan d'action cyber exhaustif, adapté aux menaces stratégiques. | H42: =IF($F42="1 - Insuffisant", "Mettre en place une activité de veille en cybersécurité afin d'identifier les menaces émergentes et les évolutions du paysage des risques.", IF($F42="2 - Émergent", "Formaliser les sources de renseignement en cybersécurité et structurer leur collecte, leur analyse et leur exploitation au sein de l'organisation.", IF($F42="3 - Intermédiaire", "Diffuser les informations pertinentes issues de la veille cybersécurité aux parties prenantes concernées afin d'améliorer la réactivité face aux menaces.", IF($F42="4 - Confirmé", "Maintenir et renforcer les capacités de veille en cybersécurité en améliorant continuellement la qualité des sources, l'analyse des menaces et la diffusion des informations.", IF($F42="5 - Optimal", "Optimiser la veille en cybersécurité en intégrant une approche proactive de renseignement sur les menaces, en adaptant en continu les capacités d'analyse et en renforçant la prise de décision basée sur l'intelligence des risques.", IF($F42="Non applicable", "Non applicable.", "")))))) -> Optimiser la veille en cybersécurité en intégrant une approche proactive de renseignement sur les menaces, en adaptant en continu les capacités d'analyse et en renforçant la prise de décision basée sur l'intelligence des risques. | J42: 11 - Résilience avancée et amélioration continue
B43: 41 | C43: Tests de sécurité et audits techniques | D43: Réaliser régulièrement des évaluations techniques afin de vérifier l'efficacité des mesures de cybersécurité mises en œuvre. | E43: Rapports de pentest, Rapports d'audit, Scans de vulnérabilités, Plans de remédiation, Suivi des actions correctives. | F43: 5 - Optimal | G43: {=IF(F43="", "", IFERROR(INDEX('Echelle de maturité'!$B$2:$B$7, MATCH(F43, 'Echelle de maturité'!$C$2:$C$7, 0)), ""))} -> Des objectifs de réduction des risques cyber intégrés à la stratégie de l'organisation. Des moyens humains, budgétaires conséquents, un plan d'action cyber exhaustif, adapté aux menaces stratégiques. | H43: =IF($F43="1 - Insuffisant", "Mettre en place un programme de tests et d'audits de sécurité afin d'évaluer régulièrement le niveau de protection des systèmes et des processus.", IF($F43="2 - Émergent", "Formaliser la fréquence et le périmètre des évaluations de sécurité en définissant les types d'audits, les systèmes concernés et les responsabilités associées.", IF($F43="3 - Intermédiaire", "Suivre les plans de remédiation issus des audits et tests de sécurité et vérifier leur mise en œuvre ainsi que leur efficacité dans le temps.", IF($F43="4 - Confirmé", "Maintenir des évaluations de sécurité régulières et structurées et améliorer en continu la couverture des contrôles afin de renforcer la posture de sécurité globale.", IF($F43="5 - Optimal", "Optimiser le dispositif d'audit et de tests de sécurité en intégrant une démarche d'amélioration continue, en renforçant la profondeur des évaluations et en adaptant les contrôles aux menaces émergentes.", IF($F43="Non applicable", "Non applicable.", "")))))) -> Optimiser le dispositif d'audit et de tests de sécurité en intégrant une démarche d'amélioration continue, en renforçant la profondeur des évaluations et en adaptant les contrôles aux menaces émergentes. | J43: 11 - Résilience avancée et amélioration continue
B44: 42 | C44: Gestion de crise cyber | D44: Mettre en place une organisation permettant de piloter efficacement les situations de crise cyber majeures et de coordonner les actions de réponse. | E44: Plan de gestion de crise, Cellule de crise, Annuaire d'urgence, Procédure de communication, Comptes-rendus d'exercices. | F44: 5 - Optimal | G44: {=IF(F44="", "", IFERROR(INDEX('Echelle de maturité'!$B$2:$B$7, MATCH(F44, 'Echelle de maturité'!$C$2:$C$7, 0)), ""))} -> Des objectifs de réduction des risques cyber intégrés à la stratégie de l'organisation. Des moyens humains, budgétaires conséquents, un plan d'action cyber exhaustif, adapté aux menaces stratégiques. | H44: =IF($F44="1 - Insuffisant", "Définir une organisation et un plan de gestion de crise cyber afin de structurer la réponse de l'organisation en cas d'incident majeur.", IF($F44="2 - Émergent", "Formaliser les rôles, responsabilités et procédures d'escalade dans le cadre de la gestion de crise cyber afin d'assurer une coordination efficace.", IF($F44="3 - Intermédiaire", "Tester régulièrement le dispositif de gestion de crise cyber afin de valider son efficacité et d'identifier les axes d'amélioration.", IF($F44="4 - Confirmé", "Maintenir des exercices de gestion de crise cyber et améliorer en continu les plans et dispositifs de réponse afin de renforcer la résilience organisationnelle.", IF($F44="5 - Optimal", "Optimiser la gestion de crise cyber en intégrant une approche proactive et intégrée, en améliorant continuellement les capacités de réponse et en renforçant la coordination entre les parties prenantes.", IF($F44="Non applicable", "Non applicable.", "")))))) -> Optimiser la gestion de crise cyber en intégrant une approche proactive et intégrée, en améliorant continuellement les capacités de réponse et en renforçant la coordination entre les parties prenantes. | J44: 11 - Résilience avancée et amélioration continue
B45: 43 | C45: Mesure de la performance cybersécurité et amélioration continue | D45: Définir, suivre et analyser des indicateurs de performance afin d'évaluer l'efficacité du dispositif de cybersécurité et d'améliorer en continu son niveau de maturité. | E45: Tableaux de bord KPI/KRI, Rapports de suivi, Revues de direction, Plans d'amélioration, Historique des indicateurs. | F45: 5 - Optimal | G45: {=IF(F45="", "", IFERROR(INDEX('Echelle de maturité'!$B$2:$B$7, MATCH(F45, 'Echelle de maturité'!$C$2:$C$7, 0)), ""))} -> Des objectifs de réduction des risques cyber intégrés à la stratégie de l'organisation. Des moyens humains, budgétaires conséquents, un plan d'action cyber exhaustif, adapté aux menaces stratégiques. | H45: =IF($F45="1 - Insuffisant", "Définir des indicateurs de performance permettant de mesurer l'efficacité du dispositif de cybersécurité de l'organisation.", IF($F45="2 - Émergent", "Formaliser le suivi et l'analyse des indicateurs de cybersécurité en définissant les méthodes de collecte, de reporting et de revue.", IF($F45="3 - Intermédiaire", "Utiliser les résultats des indicateurs pour orienter les plans d'amélioration et renforcer progressivement la maturité du dispositif de cybersécurité.", IF($F45="4 - Confirmé", "Maintenir un pilotage structuré de la cybersécurité basé sur des indicateurs pertinents et améliorer en continu la maturité du dispositif à partir des résultats obtenus.", IF($F45="5 - Optimal", "Optimiser le pilotage de la cybersécurité par les indicateurs en intégrant une approche de gestion de la performance avancée et en adaptant en continu les objectifs et mesures aux évolutions des risques.", IF($F45="Non applicable", "Non applicable.", "")))))) -> Optimiser le pilotage de la cybersécurité par les indicateurs en intégrant une approche de gestion de la performance avancée et en adaptant en continu les objectifs et mesures aux évolutions des risques. | J45: 11 - Résilience avancée et amélioration continue
A46: Score global NIS2 | F46: =(COUNTIF(F3:F45,"1 - Insuffisant")*1 +COUNTIF(F3:F45,"2 - Émergent")*2 +COUNTIF(F3:F45,"3 - Intermédiaire")*3 +COUNTIF(F3:F45,"4 - Confirmé")*4 +COUNTIF(F3:F45,"5 - Optimal")*5) & "/" & (ROWS(F3:F45)*5) -> 177/215 | G46: =ROUND((LEFT(F46,SEARCH("/",F46)-1)/RIGHT(F46,LEN(F46)-SEARCH("/",F46)))*5,2)&" / 5" -> 4,12 / 5

Sheet Dashboard NIS2
A1: Niveau | B1: Nombre
A2: Insuffisant | B2: =COUNTIF('NIS2'!F:F,"*Insuffisant*") -> 1
A3: Émergent | B3: =COUNTIF('NIS2'!F:F , "*Émergent*") -> 0
A4: Intermédiaire | B4: =COUNTIF('NIS2'!F:F , "*Intermédiaire*") -> 6
A5: Confirmé | B5: =COUNTIF('NIS2'!F:F , "*Confirmé*") -> 7
A6: Optimal | B6: =COUNTIF('NIS2'!F:F , "*Optimal*") -> 26
A7: Non applicable | B7: =COUNTIF('NIS2'!F:F , "*Non applicable*") -> 3
A21: {=LET(raw_domains, 'NIS2'!A3:A45, levels, 'NIS2'!F3:F45, domains, SCAN("", raw_domains, LAMBDA(a, v, IF(v="", a, v))), unique_domains, UNIQUE(domains), headers, {"Domaine", "1 - Insuffisant", "2 - Émergent", "3 - Intermédiaire", "4 - Confirmé", "5 - Optimal", "Non applicable", "Total général"}, mat_levels, {"1 - Insuffisant", "2 - Émergent", "3 - Intermédiaire", "4 - Confirmé", "5 - Optimal", "Non applicable"}, counts, MAKEARRAY(ROWS(unique_domains), 6, LAMBDA(r, c, COUNTIFS(domains, INDEX(unique_domains, r), levels, INDEX(mat_levels, 1, c)))), row_totals, BYROW(counts, LAMBDA(row, SUM(row))), col_totals, BYCOL(counts, LAMBDA(col, SUM(col))), grand_total, SUM(row_totals), body, HSTACK(unique_domains, counts, row_totals), bottom, HSTACK("Total général", col_totals, grand_total), VSTACK(headers, body, bottom))} -> Domaine | B21: 1 - Insuffisant | C21: 2 - Émergent | D21: 3 - Intermédiaire | E21: 4 - Confirmé | F21: 5 - Optimal | G21: Non applicable | H21: Total général
A22: Gouvernance | B22: 0 | C22: 0 | D22: 2 | E22: 0 | F22: 2 | G22: 0 | H22: 4
A23: Gestion des risques | B23: 0 | C23: 0 | D23: 1 | E23: 1 | F23: 2 | G23: 1 | H23: 5
A24: Contrôle d’accès / IAM | B24: 0 | C24: 0 | D24: 0 | E24: 1 | F24: 3 | G24: 0 | H24: 4
A25: Incidents & notification | B25: 0 | C25: 0 | D25: 1 | E25: 0 | F25: 3 | G25: 0 | H25: 4
A26: Continuité / Résilience | B26: 0 | C26: 0 | D26: 0 | E26: 1 | F26: 3 | G26: 0 | H26: 4
A27: Fournisseurs / Supply Chain | B27: 0 | C27: 0 | D27: 1 | E27: 0 | F27: 3 | G27: 0 | H27: 4
A28: Protection des données & Cryptographie | B28: 0 | C28: 0 | D28: 0 | E28: 1 | F28: 2 | G28: 0 | H28: 3
A29: Sensibilisation & Surveillance | B29: 0 | C29: 0 | D29: 0 | E29: 2 | F29: 1 | G29: 2 | H29: 5
A30: Sécurité des réseaux et systèmes | B30: 0 | C30: 0 | D30: 0 | E30: 0 | F30: 3 | G30: 0 | H30: 3
A31: Développement sécurisé et gestion des configurations | B31: 1 | C31: 0 | D31: 1 | E31: 1 | F31: 0 | G31: 0 | H31: 3
A32: Résilience avancée et amélioration continue | B32: 0 | C32: 0 | D32: 0 | E32: 0 | F32: 4 | G32: 0 | H32: 4
A33: Total général | B33: 1 | C33: 0 | D33: 6 | E33: 7 | F33: 26 | G33: 3 | H33: 43

Sheet CIS Controls
A2: Contrôle CIS | B2: Contrôle CIS | C2: ID Contrôle | D2: ID Mesure | E2: ID Mesure | F2: Description complète | G2: Description | H2: Type d'actifs | I2: Fonction de Sécurité | J2: Groupe (IG) | K2: Niveau de Maturité | L2: Preuves / Commentaires | M2: Recommendation | R2: Contrôle CIS (Tri)
A3: INVENTAIRE ET CONTRÔLE DES ACTIFS MATÉRIELS | B3: Inventaire et contrôle des actifs matériels | C3: 1 | D3: 46023 | E3: Établir et maintenir un inventaire détaillé des actifs de l'entreprise (matériels, cloud, etc.) | F3: Établir et tenir à jour un inventaire précis, détaillé et actualisé de tous les actifs de l'entreprise susceptibles de stocker ou de traiter des données, à savoir : les appareils des utilisateurs finaux (y compris les appareils portables et mobiles), les appareils du réseau, les appareils non informatiques/IoT et les serveurs. L'inventaire doit indiquer l'adresse réseau (si elle est statique), l'adresse du matériel, le nom de la machine, le propriétaire de l'actif de l'entreprise, le service pour chaque actif et si l'actif a été autorisé à se connecter au réseau. Pour les appareils mobiles des utilisateurs finaux, des outils de type MDM peuvent soutenir ce processus, le cas échéant. Cet inventaire comprend les biens connectés à l'infrastructure physiquement, virtuellement, à distance et ceux qui se trouvent dans des environnements en nuage. En outre, il inclut les actifs qui sont régulièrement connectés à l'infrastructure du réseau de l'entreprise, même s'ils ne sont pas sous le contrôle de l'entreprise. Examiner et mettre à jour l'inventaire de tous les actifs de l'entreprise deux fois par an, ou plus fréquemment. | G3: Maintenir un registre à jour de tous les équipements (physiques, virtuels, cloud) connectés à l'entreprise pour savoir ce qui doit être protégé. | H3: Matériel | I3: Identifier | J3: IG1/2/3 | K3: Non applicable | L3: Fichier Excel existant mais mis à jour manuellement une fois par an. Cloud absent. | M3: Mettre en place un outil d'inventaire automatisé (ex: OCS Inventory, GLPI). | R3: =IFERROR(__xludf.DUMMYFUNCTION("ARRAYFORMULA(LET(filled, SCAN("""", A3:A62, LAMBDA(acc, v, IF(v="""", acc, v))), IF(filled="""","""", TEXT(MATCH(filled, UNIQUE(FILTER(A3:A62, A3:A62<>"""")), 0), ""00"") & "" - "" & filled)))"),"01 - INVENTAIRE ET CONTRÔLE DES ACTIFS MATÉRIELS") -> 01 - INVENTAIRE ET CONTRÔLE DES ACTIFS MATÉRIELS
B4: Inventaire et contrôle des actifs matériels | C4: 1 | D4: 46054 | E4: Traiter les actifs non autorisés (les retirer du réseau, les isoler ou les autoriser) | F4: S'assurer qu'il existe un processus permettant de traiter les biens non autorisés sur une base hebdomadaire. L'entreprise peut choisir de retirer l'actif du réseau, d'empêcher l'actif de se connecter à distance au réseau ou de le mettre en quarantaine. | G4: Mettre en place un processus hebdomadaire pour détecter et isoler ou déconnecter tout matériel non répertorié sur le réseau. | H4: Matériel | I4: Répondre | J4: IG1/2/3 | K4: 2 - Émergent | L4: Aucun filtrage réseau en place. Les prises réseau sont en accès libre dans les bureaux. | M4: Configurer le port security ou le protocole 802.1x sur les switchs d'accès. | R4: =IFERROR(__xludf.DUMMYFUNCTION("""COMPUTED_VALUE"""),"01 - INVENTAIRE ET CONTRÔLE DES ACTIFS MATÉRIELS") -> 01 - INVENTAIRE ET CONTRÔLE DES ACTIFS MATÉRIELS
B5: Inventaire et contrôle des actifs matériels | C5: 1 | D5: 46082 | E5: Utiliser un outil de découverte active pour identifier les actifs connectés | F5: Utiliser un outil de découverte active pour identifier les actifs connectés au réseau de l'entreprise. Configurer l'outil de découverte active pour qu'il s'exécute quotidiennement ou plus fréquemment. | G5: Déployer un outil de scan automatique quotidien pour identifier activement tous les appareils connectés au réseau. | H5: Matériel | I5: Identifier | J5: IG2/3 | K5: 5 - Optimal | R5: =IFERROR(__xludf.DUMMYFUNCTION("""COMPUTED_VALUE"""),"01 - INVENTAIRE ET CONTRÔLE DES ACTIFS MATÉRIELS") -> 01 - INVENTAIRE ET CONTRÔLE DES ACTIFS MATÉRIELS
B6: Inventaire et contrôle des actifs matériels | C6: 1 | D6: 46113 | E6: Mettre à jour l'inventaire via l'enregistrement des requêtes DHCP | F6: Utiliser la journalisation DHCP sur tous les serveurs DHCP ou les outils de gestion des adresses IP (Internet Protocol) pour mettre à jour l'inventaire des actifs de l'entreprise. Examiner et utiliser les journaux pour mettre à jour l'inventaire des actifs de l'entreprise chaque semaine, ou plus fréquemment. | G6: Exploiter les journaux des serveurs DHCP pour mettre à jour l'inventaire matériel au moins une fois par semaine. | H6: Matériel | I6: Identifier | J6: IG2/3 | K6: 3 - Intermédiaire | R6: =IFERROR(__xludf.DUMMYFUNCTION("""COMPUTED_VALUE"""),"01 - INVENTAIRE ET CONTRÔLE DES ACTIFS MATÉRIELS") -> 01 - INVENTAIRE ET CONTRÔLE DES ACTIFS MATÉRIELS
B7: Inventaire et contrôle des actifs matériels | C7: 1 | D7: 46143 | E7: Utiliser un outil de découverte passive pour identifier les actifs connectés | F7: Utiliser un outil de découverte passive pour identifier les actifs connectés au réseau de l'entreprise. Examiner et utiliser les analyses pour mettre à jour l'inventaire des actifs de l'entreprise au moins une fois par semaine, voire plus fréquemment. | G7: Utiliser des outils d'écoute réseau (passive) pour identifier les équipements sans perturber le trafic. | H7: Matériel | I7: Identifier | J7: IG3 | K7: 1 - Insuffisant | R7: =IFERROR(__xludf.DUMMYFUNCTION("""COMPUTED_VALUE"""),"01 - INVENTAIRE ET CONTRÔLE DES ACTIFS MATÉRIELS") -> 01 - INVENTAIRE ET CONTRÔLE DES ACTIFS MATÉRIELS
